Workbook

Sheet MARA
A1: CÓDIGO | B1: DESCRIPCIÓN | C1: EAN UMA | D1: UMA | E1: CONVERSIÓN CAMA / PQT | F1: CONVERSION PAL / CAM | G1: CONVERSION PAL / PQT | H1: __PowerAppsId__
A2: 5905005 | B2: JABON. SPA 90GR 10BLI | C2: 17750672000784 | D2: CJA | E2: 11 | F2: 6 | G2: 66 | H2: 7c9221e9-3d38-455d-a8c5-99100cdbf07e
A3: 5905006 | B3: JABON. SPA 90GR 4UND 12PCK | C3: 17750672000777 | D3: CJA | E3: 19 | F3: 7 | G3: 133 | H3: 9ed4e050-66a3-4cbc-a7eb-d6e87a741ee6
A4: 5905007 | B4: JABON. SPA 150GR 3UND 21PCK | C4: 17750672000760 | D4: CJA | E4: 11 | F4: 6 | G4: 66 | H4: a49a73c1-f94e-46b1-b9ef-9cb9a5d84ab7
A5: 5905008 | B5: JABON. SPA PREMIUM MIX 4UND 320GR 25PCK | C5: 17750672001422 | D5: CJA | E5: 8 | F5: 8 | G5: 64 | H5: 281e4bf3-ba22-4820-aacd-f6cb925a7ae3
A6: 5905009 | B6: JABON. SPA PREMIUM MIX 3UND 390GR 18PCK | C6: 17750672001408 | D6: CJA | E6: 16 | F6: 6 | G6: 96 | H6: 42d292df-03ff-4a85-b9aa-66d334dbbeca
A7: 5905010 | B7: JABON. SPA PREMIUM EXOT 3UND 390GR 18PCK | C7: 17750672001415 | D7: CJA | E7: 16 | F7: 6 | G7: 96 | H7: ddeb2234-2cdb-4528-bd02-518639f3d705
A8: 5905102 | B8: JABON. SPA REFRESCANT 90GR 60UND | C8: 17750672000722 | D8: CJA | E8: 19 | F8: 7 | G8: 133 | H8: 84a3146c-f69b-47fd-ae6d-f43e11867ea9
A9: 5905103 | B9: JABON. SPA REFRESCANT 150GR 72UND | C9: 17750672000678 | D9: CJA | E9: 11 | F9: 6 | G9: 66 | H9: c2aaa844-f089-44c5-91c7-c3ae0d26cb58
A10: 5905104 | B10: JABON. SPA REFRESCANT TRIPCK 450GR | C10: 17750672001187 | D10: CJA | E10: 12 | F10: 6 | G10: 72 | H10: b4563778-1863-4636-a76b-42997a529709
A11: 5905105 | B11: JABON. SPA PREMIUM REFRES 80GR 60UND | C11: 17750672001002 | D11: CJA | E11: 19 | F11: 8 | G11: 152 | H11: 10334ca6-6053-49f2-8822-a9983cef0376
A12: 5905106 | B12: JABON. SPA PREMIUM REFRES 130GR 72UND | C12: 17750672001064 | D12: CJA | E12: 8 | F12: 8 | G12: 64 | H12: 4a69cbf5-36aa-4347-86e0-12d0d26eebf0
A13: 5905107 | B13: JABON. SPA PREMI REFRES 3UND 390GR 18PCK | C13: 17750672001385 | D13: CJA | E13: 16 | F13: 6 | G13: 96 | H13: 0d616c6b-91a2-4c1c-b718-79c4ff23ba5d
... A41: 5905812 | B41: JABÓN SPA PREMIUM RADIANTE 115GR 72UND | C41: 17750672002801 | D41: CJA | E41: 8 | F41: 8 | G41: 64 | H41: f1b01acf-89c6-465c-a6e8-1c6e32fdb142
A42: 5905813 | B42: JABÓN SPA | D42: CJA | E42: 8 | F42: 8 | G42: 64 | H42: d517776e-5660-4807-974c-158c02cba6d8
A43: 5905814 | B43: JABÓN PREM HUMECT SPA 115GR 72U NO USAR | D43: CJA | E43: 8 | F43: 8 | G43: 64 | H43: 972c525b-ee98-42db-9106-c012276ea039
A44: 5905822 | B44: JABÓN PREMIUM HUMECTANTE SPA 115GR 72UND | C44: 17750672003020 | D44: CJA | E44: 8 | F44: 8 | G44: 64 | H44: dc04cb7c-5f5c-4bc0-8818-5f69754e65d2
A45: 5905903 | B45: JABON. SPA PREM VERANO 130GR 72UND | C45: 17750672001781 | D45: CJA | E45: 8 | F45: 8 | G45: 64 | H45: 520d35c6-a817-4f91-8695-55d3cfe5cd2c
A46: 8300003 | B46: LEJIA SAPOLIO ORIGINAL 5000G 4BOT | C46: 17751851027028 | D46: CJA | E46: 9 | F46: 3 | G46: 27 | H46: 5811de45-5af9-4c99-8fb5-311af318a233
A47: 8300013 | B47: LEJIA 4.63% ORIG SAPOLIO JC 5GL 1UND | C47: 7751851029292 | D47: UND | E47: 17 | F47: 2 | G47: 34 | H47: 587da3c0-f2ac-4ef2-881d-baa0dc48f6b2
A48: 8300014 | B48: HIPOCLO. SODIO 8% SAPOLIO JC 5GL 1UND | C48: 7751851029315 | D48: UND | E48: 17 | F48: 2 | G48: 34 | H48: 01775046-fe70-43a8-81c9-a4d04c04da5e
A49: 8300021 | B49: LEJIA ORIG.SAPOLIO 250GR + 34% 15UND | C49: 27751851021412 | D49: CJA | E49: 19 | F49: 6 | G49: 114 | H49: 3bbdb84b-d439-4e58-ada4-9f24b3e99619
A50: 8300022 | B50: LEJIA ORIG.SAPOLIO 500GR + 34% 15UND | C50: 27751851021429 | D50: CJA | E50: 13 | F50: 5 | G50: 65 | H50: 080597ab-4d39-4d4d-a33d-bbfe8f595fc9
A51: 8300023 | B51: LEJIA ORIG.SAPOLIO 1000GR + 10% 12UND | C51: 17751851017340 | D51: CJA | E51: 11 | F51: 4 | G51: 44 | H51: 4704b186-7b78-425a-bbed-cc3149172739
A52: 8300038 | B52: LEJ.SAP.HIPOCLORITO D/SODI.8% GRANELXKG | D52: KG | H52: ef811415-c739-4f6e-aa7d-604cd210b54e
A53: 8300041 | B53: LEJIA PROFESIONAL SAPOLIO 4.63% 5KG.4UND | C53: 17750243060643 | D53: CJA | E53: 9 | F53: 3 | G53: 27 | H53: 04eab122-2188-4a5e-8398-b5f27a5e189b
A54: 8300052 | B54: LEJIA SAPOLIO 5.25% 4KG.4UND EXP.TRI | C54: 17750243060735 | D54: CJA | E54: 9 | F54: 4 | G54: 36 | H54: 27eb09f8-1f06-418b-bc2d-c3584ae8ee6f
A55: 8300062 | B55: LEJIA SAPOLIO LAVANDA 640GR 15 UND | C55: 17750243066393 | D55: CJA | E55: 13 | F55: 5 | G55: 65 | H55: bb94aa17-67d9-4a4a-9c86-5dbf512a3ecb
A56: 8300073 | B56: LEJIA SAPOLIO ORIGINAL 670GR 15UND | C56: 17750243067819 | D56: CJA | E56: 13 | F56: 5 | G56: 65 | H56: 66ed9914-3cbe-4211-a090-a5d22889f378
A57: 8300074 | B57: LEJIA SAPOLIO ORIGINAL 1KG 12UND | C57: 17750243067826 | D57: CJA | E57: 11 | F57: 4 | G57: 44 | H57: c224db2a-705c-4eea-97e6-6135ba75e23e
A58: 8300079 | B58: LAVANDINA SAPOL.F.BLANC.RED.1L 12UND BOL | C58: 17750243073292 | D58: CJA | E58: 11 | F58: 4 | G58: 44 | H58: 1953bb10-5070-4ca2-bf5e-a841680fd6d7
A59: 8300080 | B59: LAVANDINA SAPOL.BLANC.RED.1893ML 6UN BOL | C59: 17750243073308 | D59: CJA | E59: 10 | F59: 4 | G59: 40 | H59: 1af3dde0-e5dd-4f2b-a8fb-2330e4faab5b
A60: 8300085 | B60: LEJIA PATITO ORIGINAL 370GR 15UND | C60: 17750243073353 | D60: CJA | E60: 19 | F60: 6 | G60: 114 | H60: d6a03feb-09a7-4cce-bd68-a2f08f6c45e4
A61: 8300089 | B61: LEJIA CLORO SAPOLIO ORIGINAL 400GR 15UND | C61: 17750243074077 | D61: CJA | E61: 19 | F61: 5 | G61: 95 | H61: f14eea4c-9e84-4e2b-b128-5334be0c8a43
A62: 8300091 | B62: LEJIA CLORO SAPOL ORIGINAL 1.16KG 12UND | C62: 17750243074091 | D62: CJA | E62: 11 | F62: 3 | G62: 33 | H62: 5e5f5c87-76bc-4247-ae87-12b73eafaaa5
A63: 8300093 | B63: LEJIA CLORO SAPOLIO ORIGINAL 5KG 4UND | C63: 27751851027025 | D63: CJA | E63: 9 | F63: 3 | G63: 27 | H63: 1abb80ab-2d11-4901-837a-7b61f972e2ca
A64: 8300095 | B64: LEJIA CLORO SAP. ORIG. 790GR 15UND. S/P | C64: 27750243074081 | D64: CJA | E64: 13 | F64: 4 | G64: 52 | H64: d64188a0-2d0e-4aad-bed0-1798f621f24f
... A194: 8305041 | B194: LAVAV.LIQ.UL LIMA LIMON SAP. 500ML 12FCO | C194: 17751851026465 | D194: CJA | E194: 16 | F194: 4 | G194: 64 | H194: 0a331e1e-dc70-4f80-8c9c-3515685cf8e1
A195: 8305051 | B195: LAVAV.LIQ.UL MANZANA SAP.1250ML+ESP.6UND | D195: CJA | E195: 20 | F195: 3 | G195: 60 | H195: eb23da16-7eaf-4c8e-afc9-4b5e3006d205
A196: 8305076 | B196: LAVAVAJILLA PATITO LIMÓN 1000G 6UND | C196: 17751851023396 | D196: CJA | E196: 8 | F196: 8 | G196: 64 | H196: 6daf671b-7022-43f2-8bfb-01a861f1b11b
A197: 8305078 | B197: LAVAVAJILLA LIMON SAPOLIO 1000GR 6UND | C197: 17751851003596 | D197: CJA | E197: 8 | F197: 8 | G197: 64 | H197: 47077c2e-cf31-4064-9213-3f66c9b08cff
A198: 8305090 | B198: LAVAVAJ.CREMA SAPOLIO NARANJA 360G 12UND | C198: 17751851013540 | D198: CJA | E198: 10 | F198: 7 | G198: 70 | H198: 915b8e5f-587a-4df5-83c1-8e527e40346a
A199: 8305103 | B199: LAVAV.CREMA PATITO LIMÓN 900GR 6UND | C199: 17751851025581 | D199: CJA | E199: 8 | F199: 9 | G199: 72 | H199: 36bc3fe0-ab35-459f-8ded-cb24462513fa
A200: 8305105 | B200: LAVAV.CREMA PATITO UVA 900GR 6UND | C200: 17751851025604 | D200: CJA | E200: 8 | F200: 9 | G200: 72 | H200: c1e26a21-784f-44b8-89c8-6b87faca50e6
A201: 8305162 | B201: LAVAV. PROF.SAPOLIO AB LIMON 1KG.6FCO | C201: 17750243060698 | D201: CJA | E201: 8 | F201: 9 | G201: 72 | H201: 747d2706-6b1c-4c02-9852-f5e2a5be5a39
A202: 8305163 | B202: LAVAV.LIQ.UL PROF.SAP. LIMON 1.25L 6FCO | C202: 17750243060704 | D202: CJA | E202: 20 | F202: 3 | G202: 60 | H202: 04d3e5a5-79cf-4e74-a8d8-72fbf7a880b7
A203: 8305186 | B203: LAVAV.LIQ.SAPOL.LIMON 300ML+ESP 12UND | C203: 17750243064405 | D203: CJA | E203: 16 | F203: 4 | G203: 64 | H203: 3d2a1976-1073-458b-87c7-1bfec284152e
A204: 8305190 | B204: SAP.PROF.LAVAV. LIQ. LIMÓN 1.25L 6FCO | C204: 17750243080528 | D204: CJA | E204: 20 | F204: 3 | G204: 60 | H204: f95aa266-774f-4cae-b5f6-38435a22f6a9
A205: 8305191 | B205: SAP.PROF.LAVAV. LIQ. LIMÓN 5L 4FCO | C205: 17750243080535 | D205: CJA | E205: 9 | F205: 3 | G205: 27 | H205: 00acabde-ae81-4601-a023-49e113be0e4c
A206: 8305192 | B206: SAP.PROF.LAVAV. LIQ. MANZANA 5L 4FCO | C206: 17750243080542 | D206: CJA | E206: 9 | F206: 3 | G206: 27 | H206: 69ad1845-1518-4182-8949-af4be6daa497
A207: 8305234 | B207: LAVAV.SAPOL.LIMON.AB.MELL.360GRX2 6PCK | C207: 17750243066997 | D207: CJA | E207: 10 | F207: 8 | G207: 80 | H207: 580ecf93-2821-46cd-a392-a2d5d972f53b
... A698: 8321123 | B698: ACOND CTRL HUMEDAD AMARAS 12TUB 260ML | C698: 17750243073018 | D698: CJA | E698: 32 | F698: 4 | G698: 128 | H698: 73b448db-d474-4285-984a-69fbe3af69e5
A699: 8321141 | B699: TRATAMIENTO AMARAS REPARA 30ML SAMPL | D699: CJA | E699: 10 | F699: 8 | G699: 80 | H699: 15c222ca-41d8-41d7-bc7b-6d026d486d04
A700: 8321146 | B700: SHAMPOO MAGIA ANDINA AMARAS 12FCO 700 ML | C700: 17750243076378 | D700: CJA | E700: 15 | F700: 4 | G700: 60 | H700: b0b1117a-0834-4c3a-aefb-1792fd3d0f43
A701: 8321147 | B701: SHAMPOO MAGIA ANDINA AMARAS 12FCO 400ML | C701: 17750243076453 | D701: CJA | E701: 25 | F701: 4 | G701: 100 | H701: 5ee00ed8-469a-44ab-98d1-92ed546acf50
A702: 8321148 | B702: SHAMPOO MAGIA AND AMARAS 10TIR12SCT35ML | C702: 17750243076477 | D702: CJA | E702: 10 | F702: 7 | G702: 70 | H702: aa30322d-77a0-4b93-bdd0-9fb907eccf2d
A703: 8321149 | B703: TRATAMIENTO MAGIA AND AMARAS 12FCO 300ML | C703: 17750243076484 | D703: CJA | E703: 10 | F703: 11 | G703: 110 | H703: b59775be-35c5-4230-83d4-9d64bb87cc92
A704: 8321150 | B704: ACONDICIONADOR MAGIA AND AMARAS 12X260ML | C704: 17750243076491 | D704: CJA | E704: 32 | F704: 4 | G704: 128 | H704: 38b19289-5feb-4f3d-80e8-c60a6f9a4b4e
A705: 8321151 | B705: ACONDIC MAGIA ANDINA AMARAS 12FCO 475ML | C705: 17750243076507 | D705: CJA | E705: 18 | F705: 4 | G705: 72 | H705: 592b58a2-ea96-49f7-930d-ccb4807127f6
A706: 8321152 | B706: TRATAMIENTO MAGIA ANDI AMARAS 10X12X30ML | C706: 17750243076514 | D706: CJA | E706: 10 | F706: 7 | G706: 70 | H706: d030549d-eb90-4dc1-9395-c16f345181db
A707: 8321153 | B707: SHAMP 22ML+ACO 10ML MAGIA AND AMARAS | C707: 17750243076880 | D707: CJA | E707: 8 | F707: 8 | G707: 64 | H707: 26b6eb41-f0e0-465b-b950-35c7c0f189cb
A708: 8321154 | B708: TRAT AMPOLLETA MAGIA AMARAS 12TBO 90ML | C708: 17750243076873 | D708: CJA | E708: 45 | F708: 6 | G708: 270 | H708: 00f9454f-8dda-43b3-8996-426af5f47867
A709: 8321162 | B709: CREMA PEINAR ONDA AMARAS RIZOS 12FC300ML | C709: 17750243077429 | D709: CJA | E709: 27 | F709: 5 | G709: 135 | H709: e6816b45-a716-40ba-966f-43e5de7c0c0e
A710: 8321163 | B710: TRATAMIENTO AMARAS RIZOS 12FCO 300ML | C710: 17750243077436 | D710: CJA | E710: 10 | F710: 11 | G710: 110 | H710: d807959d-2781-475e-bf5b-712ae1c4fa89
A711: 8321164 | B711: CO-WASH AMARAS RIZOS 12FC400ML | C711: 17750243077665 | D711: CJA | E711: 25 | F711: 4 | G711: 100 | H711: 5eb717e6-4441-4fef-a2b2-fd93f8e9b989
... A790: 8325057 | B790: INSEC.MATAACAROS SAPOLIO 2A 360ML 12UND | C790: 37751851011199 | D790: CJA | E790: 26 | F790: 4 | G790: 104 | H790: cde04d37-7bd7-4235-a6f0-40c8416334c0
A791: 8325070 | B791: INSEC.SAPOL.MATAMOSCAS 360MLX2 6PCK | D791: PCK | E791: 312 | F791: 4 | G791: 1248 | H791: bfc7acc6-67aa-4bcd-8b1c-93c769d93950
A792: 8325072 | B792: INSEC.SAP.MATA ACAROS SP.360ML.12UND ECU | C792: 27751851011192 | D792: CJA | E792: 26 | F792: 4 | G792: 104 | H792: c7180731-1e6a-4ad5-be54-cf1eaae9f68c
A793: 8325074 | B793: INSEC. SAP. MATA CUC&HORM 360ML 12UND | C793: 57751851006618 | D793: CJA | E793: 26 | F793: 4 | G793: 104 | H793: b83a097a-9218-4355-bb9f-0483a02339c1
A794: 8325082 | B794: INSEC. SAP. MATA MOS Y ZANC 360ML 12UND | C794: 57751851006625 | D794: CJA | E794: 26 | F794: 4 | G794: 104 | H794: 1200a7a7-86f5-4715-adc0-9cbc1e55cb9a
A795: 8325084 | B795: INSE. SAP. MAT MOS Y ZANC BO 360ML 12UND | C795: 67751851006622 | D795: CJA | E795: 26 | F795: 4 | G795: 104 | H795: 1f6eb41a-b48a-46c8-ae72-e8782bee1dd0
A796: 8325085 | B796: INSE.SAP.MOSC.360ML+ DETERG 200G 6PCK | C796: 7750243079648 | D796: PCK | E796: 54 | F796: 5 | G796: 270 | H796: f1de2dd2-6fb6-4430-b37b-25af013aaef1
A797: 8325087 | B797: ELEC.ZANCUDOS PASTILLA SAPOLIO 2A 12UND | C797: 27751851006358 | D797: PQT | E797: 45 | F797: 12 | G797: 540 | H797: 34053edc-6a89-4730-9f7a-280587c93af3
A798: 8325088 | B798: ELEC.ZANCUD LIQ.RPTO SAP 40ML 2A 12UN | C798: 27751851006365 | D798: PQT | E798: 27 | F798: 13 | G798: 351 | H798: 374b1b14-6cb2-4a02-bd9c-2de59136628e
A799: 8325089 | B799: ELEC.ZANC EMANADOR+6UN PASTILLA SAP. 2A | C799: 27751851018597 | D799: PQT | E799: 25 | F799: 12 | G799: 300 | H799: 2328a333-12db-437c-916c-becf39d80747
A800: 8325090 | B800: ELEC.ZANC.EMAN+6UN PAST+LIQ SAP.40ML 2A | C800: 27751851006341 | D800: PQT | E800: 20 | F800: 14 | G800: 280 | H800: b91bffee-cb91-4615-bc63-3fba887e7d05
A801: 8325091 | B801: INSEC.MATATERMITAS SAPOLIO 2A 360ML 12UN | C801: 37751851006669 | D801: CJA | E801: 26 | F801: 4 | G801: 104 | H801: 8cb24c02-cae2-4520-8765-21dd95d2af33
A802: 8325092 | B802: INSEC.MATAARAÑAS SAPOLIO 2A 360ML 12UND | C802: 37751851010284 | D802: CJA | E802: 26 | F802: 4 | G802: 104 | H802: 93245bcf-af71-49e5-bb31-76b3d17ef92c
A803: 8325093 | B803: INSEC.MATATODO SAPOLIO 2A 360ML 12UND | C803: 27751851020156 | D803: CJA | E803: 26 | F803: 4 | G803: 104 | H803: 8818eefb-c8a9-4dab-8bde-b134137dea17
... A893: 8326219 | B893: PD DENTO TA TRIPACK 133G 24PCK ARY | C893: 17750243088494 | D893: CJA | E893: 10 | F893: 4 | G893: 40 | H893: 1439afd5-88ea-4b8c-a049-6af8628dab3e
A894: 8400072 | B894: DETER. BOLIV NEGROS INTENSOS 2.6KG 7BOL | D894: PQT | E894: 5 | F894: 6 | G894: 30 | H894: 2bc04389-da4c-4d48-8cd0-973a54b1b871
A895: 8400370 | B895: DETER. BOLIV TEC.ACTIVEDU FL 150GR 60BOL | C895: 17750243053904 | D895: PQT | E895: 5 | F895: 10 | G895: 50 | H895: b7bbfb5c-24ee-4243-9023-9d5c1163ef34
A896: 8400374 | B896: DETER. BOLIV TEC.ACTIVEDU FL 1.5KG 8BOL | C896: 17750243053942 | D896: PQT | E896: 5 | F896: 8 | G896: 40 | H896: 0e4e5267-c694-44c1-ac46-cae58ad6f70e
A897: 8400375 | B897: DETER. BOLIV TEC.ACTIVEDU FL 2.6KG 7BOL | C897: 17750243053959 | D897: PQT | E897: 5 | F897: 6 | G897: 30 | H897: b4da6358-b840-45a9-8cdb-2126085ad934
A898: 8400377 | B898: DETER. BOLIV TEC.ACTIVEDU FL 5.8KG 3BOL | C898: 17750243053973 | D898: PQT | E898: 5 | F898: 5 | G898: 25 | H898: 0ab0bd2e-6043-409d-95a2-38299a37bdcf
A899: 8400382 | B899: DETER. BOLIV COLORES VIVOS 2.6KG 7BOL | C899: 17750243054024 | D899: PQT | E899: 5 | F899: 6 | G899: 30 | H899: 5210bb14-c099-4459-8ab5-e1ed6924ff2f
A900: 8400383 | B900: DETER. BOLIV COLORES VIVOS 4.5KG 4BOL | C900: 17750243054031 | D900: PQT | E900: 5 | F900: 6 | G900: 30 | H900: a33673d7-77d1-43a9-b17a-8cf8bc7ea247
A901: 8400389 | B901: DET.BOLIVAR MATIC 350GR.30BOL | C901: 17750243054093 | D901: PQT | E901: 5 | F901: 9 | G901: 45 | H901: a4372985-dfd3-457e-8042-c1be2764c7b7
A902: 8400392 | B902: DETER. BOLIV MATIC 2.6KG 7BOL | C902: 17750243054123 | D902: PQT | E902: 5 | F902: 6 | G902: 30 | H902: 20be8fa4-6466-45c9-a443-60dcdd7b1eb0
A903: 8400399 | B903: DETER. BOLIV FLORAL 9KG 1BOL | C903: 7750243055260 | D903: UND | E903: 7 | F903: 8 | G903: 56 | H903: 07069e8a-e844-4747-ad2c-ac3ae700fa4a
A904: 8400404 | B904: DET.UNO ARMONIA FLORAL 3.8KGX4BOL | C904: 17750243055441 | D904: PQT | E904: 5 | F904: 7 | G904: 35 | H904: 079b1679-000c-46e7-acd4-f0941968daa8
A905: 8400408 | B905: DET.UNO FRESCURA LIMON 3.8 KGX4BOL | C905: 17750243055489 | D905: PQT | E905: 5 | F905: 7 | G905: 35 | H905: 4465f3b5-2d41-4663-a08d-17e3a0672861
A906: 8400414 | B906: DETER. BOLIV TEC.ANTIPER.FL 780GR 15BOL | C906: 17750243055793 | D906: PQT | E906: 5 | F906: 8 | G906: 40 | H906: f534e7ee-8b58-49d8-a63e-72e396e7f7ec
... A1312: 8412061 | B1312: DETER. PATITO BEBE 130GR 60UND EXP. | C1312: 17750243084830 | D1312: PQT | E1312: 5 | F1312: 11 | G1312: 55 | H1312: d42e9e6e-f17e-4b44-a9bb-32bcd973db6f
A1313: 8412062 | B1313: DET.PATITO BICARB.FLORAL 2X5.5KG.2BOL PE | D1313: PQT | E1313: 5 | F1313: 10 | G1313: 50 | H1313: 4b2e0832-caf3-44b5-a2e9-dd8d7cfb0b6b
A1314: 8412063 | B1314: DET.PATITO BICARB.LIMON 2X5.5KG.2BOL PE | D1314: PQT | E1314: 5 | F1314: 10 | G1314: 50 | H1314: 8ff82d99-a98b-458d-8caa-e8120e1c7a5c
A1315: 8412064 | B1315: DET.PATITO.BICARB FLORAL 500GX15BOL | C1315: 17750243088647 | D1315: PQT | E1315: 5 | F1315: 10 | G1315: 50 | H1315: 504365c6-4e17-41c7-9594-ef470fd60c37
A1316: 8412065 | B1316: DET.PATITO.BICARB LIMÓN 500GX15BOL | C1316: 17750243088654 | D1316: PQT | E1316: 5 | F1316: 10 | G1316: 50 | H1316: 24c188de-ad2a-44b6-8a97-d5534475d79a
A1317: 8412066 | B1317: DET.PATITOBICARB FLORAL 4.7KG X 2BOL | C1317: 17750243088661 | D1317: PQT | E1317: 5 | F1317: 10 | G1317: 50 | H1317: 94aeeb23-f76c-4423-8a26-34f54e9cd046
A1318: 8412067 | B1318: DET.PATITOBICARB LIMÓN 4.7KG X 2BOL | C1318: 17750243088678 | D1318: PQT | E1318: 5 | F1318: 10 | G1318: 50 | H1318: fc1c2eec-d174-438d-a6c2-af1bdf1b798b
...

Sheet sap
A1: Ubicación | B1: Tipo almacén | C1: Producto | D1: Descripción producto | E1: Lote | F1: FeCaduc/FePreferCons | G1: Tipo de stock | H1: Ctd.embalada (UMA) | I1: Un.medida alternat. | J1: Ctd. | K1: Fecha EM | L1: Documento | M1: Grupo consolidación | N1: Control de calidad | O1: Peso de carga | P1: __PowerAppsId__
A2: PP-07-001-1 | B2: PERP | C2: 8300013 | D2: LEJIA 4.63% ORIG SAPOLIO JC 5GL 1UND | E2: 2608045060 | F2: 46485 | G2: 1F | H2: 19 | I2: UND | J2: 19 | K2: 08.08.2026 | O2: 395.276 | P2: 51f2c59c-bd7b-4501-9c2e-229a7a27d82f
A3: PP-07-008-1 | B3: PERP | C3: 8300041 | D3: LEJIA PROFESIONAL SAPOLIO 4.63% 5KG.4UND | E3: 2607275060 | F3: 27/07/2027 | G3: 1F | H3: 22 | I3: CJA | J3: 88 | K3: 28.07.2026 | O3: 467.94 | P3: c579347c-65bf-4362-bf4d-b53021a0813c
A4: PP-15-042-1 | B4: PERP | C4: 8300110 | D4: LEJÍA I PATITO B CLORO 370G 15 UND | E4: 2605275060 | F4: 27/05/2027 | G4: 1F | H4: 36 | I4: CJA | J4: 540 | K4: 28.07.2026 | O4: 219.564 | P4: c2507bd9-4257-4c09-9713-8679666b7745
A5: PP-15-010-1 | B5: PERP | C5: 8300111 | D5: LEJÍA I PATITO B CLORO 650G 12 UND | E5: 2608245060 | F5: 24/08/2027 | G5: 1F | H5: 61 | I5: CJA | J5: 732 | K5: 25.08.2026 | O5: 511.851 | P5: b4919487-8935-46c2-b564-51d7001887e4
A6: PP-09-006-1 | B6: PERP | C6: 8300112 | D6: LEJÍA I PATITO B CLORO 1KG 12 UND | E6: 2607075060 | F6: 46575 | G6: 1F | H6: 44 | I6: CJA | J6: 528 | K6: 28.07.2026 | O6: 564.96 | P6: b8ce338d-6f14-4c94-934d-a3ffbccc84f6
A7: PP-15-033-1 | B7: PERP | C7: 8300113 | D7: LEJIA SAPOLIO CLORO B 400GR 15UND | E7: 2608105060 | F7: 46668 | G7: 1F | H7: 16 | I7: CJA | J7: 240 | K7: 28.08.2026 | O7: 104.784 | P7: 996e5039-2e37-4b4e-a710-5e405aaac412
A8: PP-08-047-1 | B8: PERP | C8: 8300115 | D8: LEJIA SAPOLIO CLORO B 1.16KG 12UND | E8: 2608065060 | F8: 46546 | G8: 1F | H8: 32 | I8: CJA | J8: 384 | K8: 07.08.2026 | O8: 473.472 | P8: 34988c58-9a14-4561-93bb-1698fd6e9fa9
A9: PP-08-048-1 | B9: PERP | C9: 8300115 | D9: LEJIA SAPOLIO CLORO B 1.16KG 12UND | E9: 2608055060 | F9: 46515 | G9: 1F | H9: 11 | I9: CJA | J9: 132 | K9: 07.08.2026 | O9: 162.756 | P9: 59cb97b9-f9d5-48f2-ac08-7f127eda5009
A10: PP-08-051-1 | B10: PERP | C10: 8300116 | D10: LEJIA SAPOLIO CLORO B 2.5KG 6UND | E10: 2608155060 | F10: 15/08/2027 | G10: 1F | H10: 6 | I10: CJA | J10: 36 | K10: 29.08.2026 | O10: 95.784 | P10: 584cde7d-4746-4c4f-aebb-b7870f9290d4
A11: PP-07-026-1 | B11: PERP | C11: 8300117 | D11: LEJIA SAPOLIO CLORO B 4.8 KG 4UND | E11: 2608215060 | F11: 21/08/2027 | G11: 1F | H11: 9 | I11: CJA | J11: 36 | K11: 21.08.2026 | O11: 183.735 | P11: 5317276b-7dac-4df9-84c9-4478c3ad9beb
A12: PP-07-027-1 | B12: PERP | C12: 8300117 | D12: LEJIA SAPOLIO CLORO B 4.8 KG 4UND | E12: 2608225060 | F12: 22/08/2027 | G12: 1F | H12: 27 | I12: CJA | J12: 108 | K12: 22.08.2026 | O12: 551.205 | P12: e0c57497-53bf-4d2f-9e22-2c598f2a6892
A13: PP-09-008-1 | B13: PERP | C13: 8300120 | D13: LEJIA SAPOLIO CLORO B 770GR 15UND | E13: 2608135060 | F13: 13/08/2027 | G13: 1F | H13: 46 | I13: CJA | J13: 690 | K13: 15.08.2026 | O13: 584.614 | P13: 0c61a65a-93d7-4e02-ae73-ae9645799174
A14: PP-09-009-1 | B14: PERP | C14: 8300120 | D14: LEJIA SAPOLIO CLORO B 770GR 15UND | E14: 2608055060 | F14: 46515 | G14: 1F | H14: 25 | I14: CJA | J14: 375 | K14: 31.08.2026 | O14: 317.725 | P14: 8a7d576d-23df-4b1a-9dbf-9c257cac8957
A15: PP-08-006-1 | B15: PERP | C15: 8301100 | D15: CEP DENTO LIMPIALEN RT SUAVE 14UND 6DSP | E15: 2605125060 | F15: 47457 | G15: 1F | H15: 45 | I15: CJA | J15: 3780 | K15: 28.07.2026 | O15: 103.95 | P15: 4e727f3e-ab43-41da-a1c6-d30f0d691972
A16: PP-08-010-1 | B16: PERP | C16: 8301101 | D16: CEP DENTO PREMIUM GRAB RT MED.14UND 6DSP | E16: 2608125060 | F16: 47460 | G16: 1F | H16: 68 | I16: CJA | J16: 5712 | K16: 15.08.2026 | O16: 157.08 | P16: 5c9d6561-906c-455f-9258-7b5fce48d5cb
A17: PP-08-009-1 | B17: PERP | C17: 8301102 | D17: CEP DENTO PREMIUM GRAB RT DUR.14UND 6DSP | E17: 2608145060 | F17: 14/08/2029 | G17: 1F | H17: 48 | I17: CJA | J17: 4032 | K17: 18.08.2026 | O17: 110.88 | P17: 6f268184-2667-4ee9-bf7e-081b6f4ea22e
A18: PP-08-004-1 | B18: PERP | C18: 8301104 | D18: CEP DENTO GALAXY NIÑOS 14UND 6DSP | E18: 2608175060 | F18: 17/08/2029 | G18: 1F | H18: 53 | I18: CJA | J18: 4452 | K18: 20.08.2026 | O18: 106 | P18: df5d184b-097e-4793-a57d-74bdf4547acf
A19: PP-08-018-1 | B19: PERP | C19: 8301105 | D19: ENJ.BUCAL DENTO MENTA NATURAL 250ML 12UN | E19: 2608205070 | F19: 20/08/2029 | G19: 1F | H19: 13 | I19: CJA | J19: 156 | K19: 25.08.2026 | O19: 48.1 | P19: 188631e7-7f47-4a49-bd56-8ce5f70c5e0e
A20: PP-08-019-1 | B20: PERP | C20: 8301106 | D20: ENJ.BUCAL DENTO GLACIAL 250ML 12UND | E20: 2608085070 | F20: 47338 | G20: 1F | H20: 139 | I20: CJA | J20: 1668 | K20: 18.08.2026 | O20: 514.3 | P20: 3bf770e8-e55c-449f-b775-fdb22b9291aa
A21: PP-08-020-1 | B21: PERP | C21: 8301108 | D21: ENJ.BUCAL DENTITO TUTI FRUTI 250ML 12UND | E21: 2608015070 | F21: 47126 | G21: 1F | H21: 25 | I21: CJA | J21: 300 | K21: 09.08.2026 | O21: 92.5 | P21: bfcb7d9e-1d22-4aec-99f1-f4b0f6033b41
A22: PP-08-017-1 | B22: PERP | C22: 8301109 | D22: ENJ.DENTITO CHICHA MORADA 250ML 12UND | E22: 2605215070 | F22: 21/05/2029 | G22: 1F | H22: 40 | I22: CJA | J22: 480 | K22: 27.08.2026 | O22: 148 | P22: ad7d628c-c036-4f6b-885b-50d196944963
A23: PP-08-008-1 | B23: PERP | C23: 8301256 | D23: CEP DENTO PREMIUM GRAB RT SUA14UND 6DSP | E23: 2607275060 | F23: 27/07/2029 | G23: 1F | H23: 40 | I23: CJA | J23: 3360 | K23: 05.08.2026 | O23: 92.4 | P23: 30598d3d-a61e-4cea-b7b7-0227c3d8af79
A24: PP-08-005-1 | B24: PERP | C24: 8301260 | D24: CEP DENTO LIMPIALEN RT MEDIO 14UND 6DSP | E24: 2608045060 | F24: 47216 | G24: 1F | H24: 49 | I24: CJA | J24: 4116 | K24: 12.08.2026 | O24: 113.19 | P24: c01e8691-3e35-463f-8930-a491b0eeb510
A25: PP-08-016-1 | B25: PERP | C25: 8301271 | D25: CEP DENTO LIMPIALEN ZZ MED.X3 8BLS 6DSP | E25: 2606225060 | F25: 22/06/2029 | G25: 1F | H25: 11 | I25: CJA | J25: 528 | K25: 13.08.2026 | O25: 37.488 | P25: b8d98e97-35bb-4323-be14-6e076e1799a4
A26: PP-08-014-1 | B26: PERP | C26: 8301272 | D26: CEP DENTO LIMPIALEN ZZ DURO X3 8BLS 6DSP | E26: 2506235060 | F26: 23/06/2028 | G26: 1F | H26: 12 | I26: CJA | J26: 576 | K26: 29.08.2026 | O26: 40.896 | P26: dda1bbe7-de68-4a64-8515-b9724d56c2e3
A27: PP-08-015-1 | B27: PERP | C27: 8301274 | D27: CEP DENTO LIMPIALEN ZZ SUAV.X3 8BLS 6DSP | E27: 2603045060 | F27: 47211 | G27: 1F | H27: 8 | I27: CJA | J27: 384 | K27: 13.08.2026 | O27: 27.264 | P27: 2b1cb4fe-bc98-4e38-bbbb-74754353b766
A28: PP-08-043-1 | B28: PERP | C28: 8303001 | D28: DET LÍQ LAVAROPA FLORES SAP.1000ML 12UND | E28: 2607015060 | F28: 46759 | G28: 1F | H28: 33 | I28: CJA | J28: 396 | K28: 28.07.2026 | O28: 448.734 | P28: 2fe1ee11-1bdd-437b-92de-fce575740c1a
A29: PP-08-039-1 | B29: PERP | C29: 8303003 | D29: DETER.SAPO LIQ.LAVARO LIMON 2000ML 6UND | E29: 2607235060 | F29: 23/07/2028 | G29: 1F | H29: 27 | I29: CJA | J29: 162 | K29: 01.08.2026 | O29: 356.4 | P29: 252dd454-b14d-4e7b-a2c7-e9e88bfb6364
A30: PP-08-042-1 | B30: PERP | C30: 8303004 | D30: DET LÍQ LAVAROPA FLORES SAP.2000ML 6UN | E30: 2606085060 | F30: 46971 | G30: 1F | H30: 2 | I30: CJA | J30: 12 | K30: 28.08.2026 | O30: 26.556 | P30: 6795a590-1d2a-4afb-9e72-77857e7f9579
A31: PP-07-004-1 | B31: PERP | C31: 8303007 | D31: DET.LIQUIDO FRESCO LIMON SAP. 5L 4UND | E31: 2606045060 | F31: 46849 | G31: 1F | H31: 7 | I31: CJA | J31: 28 | K31: 28.07.2026 | O31: 154.35 | P31: d0a246bd-048a-4114-9bd4-96d5769981d6
A32: PP-07-014-1 | B32: PERP | C32: 8303008 | D32: DET.LIQUIDO FERIA DE FLORES SAP. 5L 4UND | E32: 2608195060 | F32: 19/08/2028 | G32: 1F | H32: 27 | I32: CJA | J32: 108 | K32: 25.08.2026 | O32: 602.262 | P32: d4d62356-eb45-4266-b674-013171024be2
A33: PP-12-041-1 | B33: PERP | C33: 8303020 | D33: DETERG.AMDC/ASA FLORAL SAPOLIO 6KG 2UND | E33: 2607025030 | F33: 47156 | G33: 1F | H33: 13 | I33: PQT | J33: 26 | K33: 28.07.2026 | O33: 158.08 | P33: 66466d45-69aa-4d4d-b12d-97560c14324a
A34: PP-11-019-1 | B34: PERP | C34: 8303023 | D34: DETER.SAPOLIO AMD C/ASA BEBE 8KG 2UND | E34: 2604115030 | F34: 47426 | G34: 1F | H34: 13 | I34: PQT | J34: 26 | K34: 28.07.2026 | O34: 210.548 | P34: ae23e357-2f7c-41b1-96f6-21cd41c85dfb
A35: PP-11-004-1 | B35: PERP | C35: 8303025 | D35: DETERG.AMDC/ASALIMON SAPOLIO 4000GR 4UND | E35: 2608030120 | F35: 47185 | G35: 1F | H35: 28 | I35: PQT | J35: 112 | K35: 30.08.2026 | O35: 456.624 | P35: 7831359f-d430-4150-8407-3e975be0ba18
A36: PP-11-005-1 | B36: PERP | C36: 8303028 | D36: DETER.SAPOLIO AMD C/ASA BEBE 4000GR 4UND | E36: 2608285030 | F36: 28/08/2029 | G36: 1F | H36: 13 | I36: PQT | J36: 52 | K36: 29.08.2026 | O36: 211.991 | P36: 13eedc99-3757-4412-9ead-38105b4bac6d
A37: PP-12-047-1 | B37: PERP | C37: 8303029 | D37: DET.SAP.LIMON 2KG.6UND | E37: 2608030120 | F37: 47185 | G37: 1F | H37: 31 | I37: PQT | J37: 186 | K37: 29.08.2026 | O37: 385.919 | P37: 4ddd8b19-9a9e-4ef5-ba57-283c14a5b5fd
A38: PP-12-044-1 | B38: PERP | C38: 8303031 | D38: DET.SAP.FLORAL 2KG.6UND | E38: 2608275030 | F38: 27/08/2029 | G38: 1F | H38: 33 | I38: PQT | J38: 198 | K38: 29.08.2026 | O38: 404.25 | P38: 5884d100-9273-4d69-884e-407680a3f922
A39: PP-11-047-1 | B39: PERP | C39: 8303032 | D39: DET.SAP.BEBE 2KG.6UND | E39: 2608180120 | F39: 18/08/2029 | G39: 1F | H39: 17 | I39: PQT | J39: 102 | K39: 19.08.2026 | O39: 222.7 | P39: be24e65d-8627-4b18-9afb-47faa4fd2bd8
A40: PP-11-048-1 | B40: PERP | C40: 8303032 | D40: DET.SAP.BEBE 2KG.6UND | E40: 2608180120 | F40: 18/08/2029 | G40: 1F | H40: 13 | I40: PQT | J40: 78 | K40: 19.08.2026 | O40: 170.3 | P40: 9d794e02-2515-43b3-907b-a67dadd9b5c0
A41: PP-07-002-1 | B41: PERP | C41: 8303047 | D41: DET.LIQUIDO FLORES SAP. JC 5GL 1UND | E41: 2607235060 | F41: 24/07/2029 | G41: 1F | H41: 34 | I41: UND | J41: 34 | K41: 28.07.2026 | O41: 691.39 | P41: bc401fdf-bb13-4c90-861e-75fb534b7dcb
A42: PP-09-005-1 | B42: PERP | C42: 8304003 | D42: LIBRE ENJUAGUE FLORES AMOR 2000ML 6UND | E42: 2502045010 | F42: 46479 | G42: 1F | H42: 1 | I42: CJA | J42: 6 | K42: 28.07.2026 | O42: 12.876 | P42: 47ce868a-4419-441f-b874-bda62c7f8ac5
A43: PP-09-003-1 | B43: PERP | C43: 8304004 | D43: LIBRE ENJUAGUE LAVANDA AMOR 2000ML 6UND | E43: 2606035060 | F43: 46818 | G43: 1F | H43: 2 | I43: CJA | J43: 12 | K43: 28.07.2026 | O43: 25.752 | P43: e6dcf845-8d62-436b-9fe2-770db817b30c
A44: PP-15-040-1 | B44: PERP | C44: 8304013 | D44: LIBRE ENJUA.B.FLORES AMOR 80ML 72UND | E44: 2608215060 | F44: 21/08/2028 | G44: 1F | H44: 62 | I44: CJA | J44: 4464 | K44: 25.08.2026 | O44: 392.832 | P44: 1a9210bd-367a-4b07-9aa2-b60aaf88c2c0
A45: PP-09-004-1 | B45: PERP | C45: 8304019 | D45: LIBRE ENJUAGUE BEBE AMOR 2000ML 6UND | E45: 2608205060 | F45: 20/08/2028 | G45: 1F | H45: 47 | I45: CJA | J45: 282 | K45: 25.08.2026 | O45: 605.172 | P45: ddb20e64-e0f0-4834-9bb2-5ce34cec32cf
A46: PP-08-037-1 | B46: PERP | C46: 8304020 | D46: LIBRE ENJUAGUE FLORES AMOR 1000ML 12UND | E46: 2607025060 | F46: 46790 | G46: 1F | H46: 2 | I46: CJA | J46: 24 | K46: 28.07.2026 | O46: 26.14 | P46: cc5c9cab-f455-494d-ab90-b856d7353ae7
A47: PP-09-001-1 | B47: PERP | C47: 8304021 | D47: LIBRE ENJUAGUE LAVANDAAMOR 1000ML 12UND. | E47: 2607025060 | F47: 46790 | G47: 1F | H47: 24 | I47: CJA | J47: 288 | K47: 28.07.2026 | O47: 313.68 | P47: 9e60adc8-2f0c-44a7-929b-b5b837df5ea9
A48: PP-08-036-1 | B48: PERP | C48: 8304022 | D48: LIBRE ENJUAGUE BEBE AMOR 1000ML 12UND | E48: 2607165060 | F48: 16/07/2028 | G48: 1F | H48: 27 | I48: CJA | J48: 324 | K48: 28.07.2026 | O48: 352.89 | P48: 16168c97-78c8-4dd5-8294-d43f3057ab62
A49: PP-07-011-1 | B49: PERP | C49: 8304033 | D49: AMOR LIBRE ENJUAGUE FLORES C/A/ 5L X 4 | E49: 2608205060 | F49: 20/08/2028 | G49: 1F | H49: 22 | I49: CJA | J49: 88 | K49: 26.08.2026 | O49: 462.352 | P49: d60f73a0-6cd9-4db6-8443-a0e1702f7e4f
A50: PP-07-010-1 | B50: PERP | C50: 8304034 | D50: AMOR LIBRE ENJUAGUE LAVANDA C/A 5L X4 | E50: 2607175060 | F50: 17/07/2028 | G50: 1F | H50: 22 | I50: CJA | J50: 88 | K50: 28.07.2026 | O50: 462.704 | P50: 27e9de1e-59ce-4849-91b7-3755e6e170a8
A51: PP-07-009-1 | B51: PERP | C51: 8304035 | D51: AMOR LIBRE ENJUAGUE BEBE C/A 5L X4 | E51: 2607305060 | F51: 30/07/2028 | G51: 1F | H51: 15 | I51: CJA | J51: 60 | K51: 19.08.2026 | O51: 317.415 | P51: 46e5d80f-8996-449a-b181-e0b5f51f97b4
A52: PP-08-052-1 | B52: PERP | C52: 8304142 | D52: SUAV.KLINTEX 3785ML 4UND | E52: 2607235060 | F52: 23/07/2029 | G52: 1F | H52: 12 | I52: CJA | J52: 48 | K52: 21.08.2026 | O52: 196.344 | P52: fd5b7278-976e-46fd-a79a-ee55f6bde7e0
A53: PP-15-009-1 | B53: PERP | C53: 8305190 | D53: SAP.PROF.LAVAV. LIQ. LIMÓN 1.25L 6FCO | E53: 2607155060 | F53: 15/07/2029 | G53: 1F | H53: 3 | I53: CJA | J53: 18 | K53: 28/07/2026 | O53: 25.554 | P53: 006167ec-28e4-47ad-a2fc-4714b1b81463
A54: PP-07-005-1 | B54: PERP | C54: 8305191 | D54: SAP.PROF.LAVAV. LIQ. LIMÓN 5L 4FCO | E54: 2509245060 | F54: 24/09/2028 | G54: 1F | H54: 19 | I54: CJA | J54: 76 | K54: 28/07/2026 | O54: 410.21 | P54: c9d41184-852f-4361-892f-5a36a8e7f785
A55: PP-07-006-1 | B55: PERP | C55: 8305192 | D55: SAP.PROF.LAVAV. LIQ. MANZANA 5L 4FCO | E55: 2509045060 | F55: 46852 | G55: 1F | H55: 10 | I55: CJA | J55: 40 | K55: 28/07/2026 | O55: 215.9 | P55: 7ab84673-48ad-41b0-bd1a-100c0f674898
A56: PP-16-039-1 | B56: PERP | C56: 8305269 | D56: LAVAV. LIQ.SAPOLIO LIMÓN 300ML 12FCO PE | E56: 2607275060 | F56: 27/07/2029 | G56: 1F | H56: 63 | I56: CJA | J56: 756 | K56: 46030 | O56: 264.6 | P56: 60bc55e2-6699-4b5e-bb30-bf2f6e2dffc6
A57: PP-15-029-1 | B57: PERP | C57: 8305271 | D57: LAVAV. LIQ.SAPOLIO LIMÓN 500ML 12FCO PE | E57: 2606125060 | F57: 47458 | G57: 1F | H57: 21 | I57: CJA | J57: 252 | K57: 28/07/2026 | O57: 145.257 | P57: 921f435c-a130-4ced-b387-e4092dcf0e7c
A58: PP-15-031-1 | B58: PERP | C58: 8305272 | D58: LAVAV.LIQ.SAPOLIO MANZANA 500ML 12FCO PE | E58: 2607145060 | F58: 14/07/2029 | G58: 1F | H58: 3 | I58: CJA | J58: 36 | K58: 28/07/2026 | O58: 20.751 | P58: 463503ba-a6e2-4eac-8bb4-aa7b430ca046
A59: PP-15-032-1 | B59: PERP | C59: 8305273 | D59: LAVAV.LIQ.SAPOLIO LIMALIMÓN 500ML12FC PE | E59: 2606095060 | F59: 47367 | G59: 1F | H59: 32 | I59: CJA | J59: 384 | K59: 28/07/2026 | O59: 221.344 | P59: af5f1621-3217-4adc-893e-6b6c6c611fe7
A60: PP-10-024-1 | B60: PERP | C60: 8305274 | D60: LAVAV. LIQ.SAPOLIO LIMÓN 750ML 12FCO PE. | E60: 2608125060 | F60: 47460 | G60: 1F | H60: 60 | I60: CJA | J60: 720 | K60: 18/08/2026 | O60: 607.32 | P60: 2c482f1e-829f-42a3-ba1a-7e1986415fdf
A61: PP-10-025-1 | B61: PERP | C61: 8305274 | D61: LAVAV. LIQ.SAPOLIO LIMÓN 750ML 12FCO PE. | E61: 2608125060 | F61: 47460 | G61: 1F | H61: 4 | I61: CJA | J61: 48 | K61: 18/08/2026 | O61: 40.488 | P61: 84e1c3d4-68ee-49ac-ace2-bd27721fe30f
A62: PP-15-011-1 | B62: PERP | C62: 8305275 | D62: LAVAV. LIQ.SAPOLIO LIMÓN 1250ML 6FCO PE | E62: 2608065060 | F62: 47277 | G62: 1F | H62: 46 | I62: CJA | J62: 276 | K62: 30/08/2026 | O62: 383.64 | P62: f7a3eb96-d2c7-451d-97d6-28a9b8c063f5
A63: PP-15-012-1 | B63: PERP | C63: 8305276 | D63: LAVAV.LIQ.SAPOLIO MANZANA 1250ML 6FCO PE | E63: 2607205060 | F63: 20/07/2029 | G63: 1F | H63: 26 | I63: CJA | J63: 156 | K63: 30/07/2026 | O63: 216.84 | P63: a25994c9-690f-4cbd-ac4b-2fdf121093ee
A64: PP-15-013-1 | B64: PERP | C64: 8305277 | D64: LAVAV.LIQ.SAPOLIO LIMALIMÓN 1250ML6FC PE | E64: 2607155060 | F64: 15/07/2029 | G64: 1F | H64: 29 | I64: CJA | J64: 174 | K64: 28/07/2026 | O64: 241.86 | P64: 5891bd5d-547e-4a3b-9e0f-2a0415ea9284
A65: PP-10-026-1 | B65: PERP | C65: 8305290 | D65: LAVAV.LIQ. MANZANA SAPOLIO 750ML 12FC PE | E65: 2606135060 | F65: 13/06/2029 | G65: 1F | H65: 38 | I65: CJA | J65: 456 | K65: 28/07/2026 | O65: 387.904 | P65: a4bd1f94-c4d5-4e15-996b-03407e737e70
A66: PP-15-049-1 | B66: PERP | C66: 8305322 | D66: LAVAV. SAPOLIO LIMÓN 200GR 24UND. NV | E66: 2608105030 | F66: 47034 | G66: 1F | H66: 20 | I66: CJA | J66: 480 | K66: 21/08/2026 | O66: 105.24 | P66: ebeb2131-837c-483e-8ab2-b962765ccff1
A67: PP-16-041-1 | B67: PERP | C67: 8305323 | D67: LAVAV. SAPOLIO LIMÓN 330GR 12UND. NV | E67: 2607235030 | F67: 23/07/2028 | G67: 1F | H67: 14 | I67: CJA | J67: 168 | K67: 30/07/2026 | O67: 64.414 | P67: 057191ae-e19e-4bde-9526-c587bc420138
A68: PP-16-043-1 | B68: PERP | C68: 8305323 | D68: LAVAV. SAPOLIO LIMÓN 330GR 12UND. NV | E68: 2607235030 | F68: 23/07/2028 | G68: 1F | H68: 19 | I68: CJA | J68: 228 | K68: 30/07/2026 | O68: 87.419 | P68: 95391b25-b9ee-41a5-bb7d-eb1fb9247058
A69: PP-15-051-1 | B69: PERP | C69: 8305324 | D69: LAVAV. SAPOLIO LIMON 800GR 6UND. NV | E69: 2608125030 | F69: 47095 | G69: 1F | H69: 20 | I69: CJA | J69: 120 | K69: 22/08/2026 | O69: 104.28 | P69: 46629e4e-4857-489a-9169-8a9ce82bbfc5
A70: PP-15-052-1 | B70: PERP | C70: 8305324 | D70: LAVAV. SAPOLIO LIMON 800GR 6UND. NV | E70: 2608125030 | F70: 47095 | G70: 1F | H70: 19 | I70: CJA | J70: 114 | K70: 21/08/2026 | O70: 99.066 | P70: 85c0eef9-46ce-4190-ab4c-9451a7fb1166
A71: PP-15-050-1 | B71: PERP | C71: 8305325 | D71: LAVAV. SAPOLIO MANZANA 800GR 6UND.NV | E71: 2607225030 | F71: 22/07/2028 | G71: 1F | H71: 17 | I71: CJA | J71: 102 | K71: 28/08/2026 | O71: 88.638 | P71: 85a07d34-e145-47b1-87cc-233efd1136df
A72: PP-15-039-1 | B72: PERP | C72: 8305326 | D72: LAVAV. SAPOLIO LIMON 1000GR 6UND NV | E72: 2606135030 | F72: 13/06/2028 | G72: 1F | H72: 35 | I72: CJA | J72: 210 | K72: 14/08/2026 | O72: 224.49 | P72: dbb04d5f-29fc-48e6-bf33-73a1657665b6
A73: PP-15-048-1 | B73: PERP | C73: 8305327 | D73: LAVAV.SAPOL.LIMON ANTIB.800GR 6UND | E73: 2607225030 | F73: 22/07/2028 | G73: 1F | H73: 40 | I73: CJA | J73: 240 | K73: 46120 | O73: 211.36 | P73: 5bde5a77-41d9-4eb3-b460-4f53b922e08d
A74: PP-15-036-1 | B74: PERP | C74: 8305328 | D74: LAVAVAJILLA PATITO LIMÓN 1000G 6UND NV | E74: 2608145030 | F74: 14/08/2028 | G74: 1F | H74: 80 | I74: CJA | J74: 480 | K74: 20/08/2026 | O74: 517.6 | P74: b00258b3-0786-443d-8b54-6aa7b2dc331a
A75: PP-15-037-1 | B75: PERP | C75: 8305328 | D75: LAVAVAJILLA PATITO LIMÓN 1000G 6UND NV | E75: 2608145030 | F75: 14/08/2028 | G75: 1F | H75: 56 | I75: CJA | J75: 336 | K75: 20/08/2026 | O75: 362.32 | P75: c953414e-e1c0-41fa-ae44-d55a3b6cad2c
A76: PP-15-035-1 | B76: PERP | C76: 8305329 | D76: LAVAV. PROF.SAPOLIO AB LIMON 1KG.6FCO NV | E76: 2608065030 | F76: 46912 | G76: 1F | H76: 22 | I76: CJA | J76: 132 | K76: 46364 | O76: 142.824 | P76: 68903969-df2d-4b01-a9db-32cc0e267993
A77: PP-07-042-1 | B77: PERP | C77: 8305332 | D77: SAP.PROF.LAVAV. LIQ. LIMÓN 4L 4FCO | E77: 2608125060 | F77: 47460 | G77: 1F | H77: 20 | I77: CJA | J77: 80 | K77: 14/08/2026 | O77: 347.76 | P77: 6f6d9291-1adf-4c04-97e7-0650f2a35ba4
A78: PP-15-038-1 | B78: PERP | C78: 8305334 | D78: LAVAVAJILLA PATITO UVA 1KG 6UND | E78: 2607075030 | F78: 46941 | G78: 1F | H78: 51 | I78: CJA | J78: 306 | K78: 19/08/2026 | O78: 329.97 | P78: df67ee1a-e633-40b9-b1f2-d055f2c48aab
A79: PP-10-023-1 | B79: PERP | C79: 8305337 | D79: LAVAV. LIQ. PATITO LIMÓM 750ML 12 FCO | E79: 2606165060 | F79: 16/06/2029 | G79: 1F | H79: 42 | I79: CJA | J79: 504 | K79: 28/07/2026 | O79: 423.402 | P79: 6f617717-9d29-4098-9d4a-d0ab70a95b1a
A80: PP-15-034-1 | B80: PERP | C80: 8305338 | D80: LAV. LIQUIDO LAVAX DP LIMON TE180MLX36U | E80: 210932 | F80: 46664 | G80: 1F | H80: 10 | I80: CJA | J80: 360 | K80: 28/07/2026 | O80: 68.67 | P80: 14880d69-3a4f-4193-8227-f5308eeca97f
A81: PP-15-007-1 | B81: PERP | C81: 8305339 | D81: CREM LAVAVAJILLA LAVAX VERDE 700G X 12 U | E81: 260508000 | F81: 46970 | G81: 1F | H81: 48 | I81: CJA | J81: 576 | K81: 27/08/2026 | O81: 421.056 | P81: 1d93ea0b-9cf0-482b-a2f7-e7c07a116bf2
A82: PP-15-008-1 | B82: PERP | C82: 8305343 | D82: CREMA LAVAVAJILLA LAVAX ROSADO 700 GX12U | E82: 228442 | F82: 29/04/2028 | G82: 1F | H82: 36 | I82: CJA | J82: 432 | K82: 28/07/2026 | O82: 315.792 | P82: 903e20b8-dc00-4f24-88c7-c7037768f4d3
A83: PP-15-006-1 | B83: PERP | C83: 8305344 | D83: CREMA LAVAVAJILLA LAVAX UVA 700 G X 12 U | E83: 230709 | F83: 23/06/2028 | G83: 1F | H83: 23 | I83: CJA | J83: 276 | K83: 17/08/2026 | O83: 201.756 | P83: 364519b0-1a51-4984-a0c7-bb17b3e39a3f
A84: PP-10-039-1 | B84: PERP | C84: 8305345 | D84: CREMA LAVAVAJILLA LAVAX ALOE 850 G X 12U | E84: 231073 | F84: 46759 | G84: 1F | H84: 22 | I84: CJA | J84: 264 | K84: 15/08/2026 | O84: 232.584 | P84: ea1aa15c-6d15-4740-9b1d-e77c5b8c0531
A85: PP-10-041-1 | B85: PERP | C85: 8305347 | D85: CREMA LAVAVAJILLA LAVAX ROSADO 850 GX12U | E85: 228781 | F85: 46970 | G85: 1F | H85: 40 | I85: CJA | J85: 480 | K85: 28/07/2026 | O85: 422.88 | P85: 6070355e-e2ab-42ec-91cf-4318f48e6522
A86: PP-10-040-1 | B86: PERP | C86: 8305349 | D86: CREMA LAVAVAJILLA LAVAX AVENA 850G X 12U | E86: 228834 | F86: 47062 | G86: 1F | H86: 22 | I86: CJA | J86: 264 | K86: 28/07/2026 | O86: 232.584 | P86: 9e228271-1ba0-4cf8-8a8a-3c3acc64cf91
A87: PP-16-037-1 | B87: PERP | C87: 8305350 | D87: CREMA LAVAVAJILLA LAVAX VERDE 300G X 12U | E87: 223514 | F87: 27/03/2028 | G87: 1F | H87: 24 | I87: CJA | J87: 288 | K87: 28/07/2026 | O87: 92.448 | P87: 215af0e2-e6f6-4736-b060-4fd9711fd567
A88: PP-10-005-1 | B88: PERP | C88: 8305351 | D88: LAV. LIQ LAVAX DP LIMON TE V. 1500MLX6U | E88: 230597 | F88: 19/06/2028 | G88: 1F | H88: 44 | I88: CJA | J88: 264 | K88: 46030 | O88: 404.8 | P88: 459d5218-a08e-4b0c-88f1-d64fecd50676
A89: PP-10-004-1 | B89: PERP | C89: 8305352 | D89: LAV. LIQUIDO LAVAX DP SANDIA 1500MLX6U | E89: 230600 | F89: 19/06/2028 | G89: 1F | H89: 42 | I89: CJA | J89: 252 | K89: 28/07/2026 | O89: 386.4 | P89: 2dba7195-aab6-4c68-8fd8-7d06fed48e96
A90: PP-15-047-1 | B90: PERP | C90: 8305353 | D90: LAV. LIQUIDO LAVAX DP SANDIA 450MLX12U | E90: 251103000 | F90: 46457 | G90: 1F | H90: 7 | I90: CJA | J90: 84 | K90: 28/07/2026 | O90: 38.92 | P90: a8584d70-4330-46f2-84ab-a868f26a8a51
A91: PP-15-046-1 | B91: PERP | C91: 8305354 | D91: LAV. LIQ LAVAX DP LIMON TE V. 450MLX12U | E91: 223333 | F91: 23/03/2028 | G91: 1F | H91: 50 | I91: CJA | J91: 600 | K91: 28/07/2026 | O91: 278 | P91: 8822ab3d-ed5a-4dc9-a19d-2aaacd41ac7f
A92: PP-15-002-1 | B92: PERP | C92: 8305355 | D92: LAV. LIQ LAVAX DP SANDIA PEPIN 600MLX14U | E92: 251009002 | F92: 46640 | G92: 1F | H92: 16 | I92: CJA | J92: 224 | K92: 28/07/2026 | O92: 143.824 | P92: 950ea9c8-d424-4cf9-b540-9052af963b4c
A93: PP-15-001-1 | B93: PERP | C93: 8305356 | D93: LAV. LIQ LAVAX DP LIMON TE V. 600MLX14U | E93: 251010002 | F93: 46670 | G93: 1F | H93: 8 | I93: CJA | J93: 112 | K93: 28/07/2026 | O93: 71.912 | P93: 3a40fe6f-e7f8-499a-908b-63e9a7422bea
A94: PP-15-015-1 | B94: PERP | C94: 8305357 | D94: CREMA LAVAVAJILLA LAVAX LIMON 200G X 36U | E94: 221299 | F94: 46785 | G94: 1F | H94: 9 | I94: CJA | J94: 324 | K94: 28/07/2026 | O94: 70.632 | P94: d43f4fba-9211-4210-ba2b-e8981391c566
A95: PP-15-020-1 | B95: PERP | C95: 8305358 | D95: CREMA LAVAVAJILLA LAVAX LIMON 400G X 18U | E95: 250710002 | F95: 46667 | G95: 1F | H95: 22 | I95: CJA | J95: 396 | K95: 26/08/2026 | O95: 167.464 | P95: 522a0ac3-6799-45c0-89c8-af0835f236ed
A96: PP-10-038-1 | B96: PERP | C96: 8305360 | D96: CREMA LAVAVAJILLA LAVAX LIMON 850G X 12U | E96: 220685 | F96: 16/01/2028 | G96: 1F | H96: 30 | I96: CJA | J96: 360 | K96: 28/07/2026 | O96: 317.16 | P96: 45284425-a983-4bea-a665-fa13ca4a54fb
A97: PP-16-023-1 | B97: PERP | C97: 8305361 | D97: CREMA LAVAVAJILLA LAVAX VERDE 175G X 15U | E97: 227564 | F97: 46969 | G97: 1F | H97: 8 | I97: CJA | J97: 120 | K97: 28/07/2026 | O97: 22.816 | P97: 0830a045-1449-4038-aa1d-f49a8e932e9b
A98: PP-16-019-1 | B98: PERP | C98: 8305362 | D98: CREMA LAVAVAJILLA LAVAX ROSADO 175GX15U | E98: 230402 | F98: 16/06/2028 | G98: 1F | H98: 64 | I98: CJA | J98: 960 | K98: 28/07/2026 | O98: 182.528 | P98: b3c9f6f7-a578-439d-9494-eaae04518046
A99: PP-16-021-1 | B99: PERP | C99: 8305363 | D99: CREMA LAVAVAJILLA LAVAX UVA 175G X 15U | E99: 260410001 | F99: 47030 | G99: 1F | H99: 1 | I99: CJA | J99: 15 | K99: 28/07/2026 | O99: 2.852 | P99: 85e855d0-1fbb-4663-a6c3-10ccfa1345ba
A100: PP-16-035-1 | B100: PERP | C100: 8305365 | D100: CREMA LAVAVAJILLA LAVAX ROSADO 300GX12U | E100: 224261 | F100: 46787 | G100: 1F | H100: 25 | I100: CJA | J100: 300 | K100: 28/07/2026 | O100: 96.3 | P100: d37e6b6c-5f29-413b-b576-2967b3851c32
...

Sheet CANTIDAD
A1: PASILLO | B1: Ubicación | C1: Producto | D1: EAN | E1: Descripción producto | F1: CANT. | G1: UMA CANT. | H1: Lote | I1: FeCaduc/FePreferCons | J1: Tipo de stock | K1: Ctd. | L1: CAMA | M1: UMA | N1: __PowerAppsId__
A2: ="PASILLO " & VALUE(MID(B2, 4, 2)) -> PASILLO 1 | B2: AP-01-005-1 | C2: =IFERROR(VLOOKUP(CANTIDAD[[#This Row],[Ubicación]],SAP[],3,FALSE),"") -> 8325056 | D2: =IFERROR(VLOOKUP(CANTIDAD[[#This Row],[Producto]],MARA[],3,FALSE),"") -> 37751851006645 | E2: =IFERROR(VLOOKUP(CANTIDAD[[#This Row],[Ubicación]],SAP[],4,FALSE),"") -> INSEC.CASA&JARDIN SAPOLIO 2A 360ML 12UND | F2: =IFERROR(VLOOKUP(CANTIDAD[[#This Row],[Ubicación]],SAP[],8,FALSE),"") -> 5 | G2: =IFERROR(VLOOKUP(CANTIDAD[[#This Row],[Ubicación]],SAP[],9,FALSE),"") -> CJA | H2: =IFERROR(VLOOKUP(CANTIDAD[[#This Row],[Ubicación]],SAP[],5,FALSE),"") -> 2601205060 | I2: =IFERROR(VLOOKUP(CANTIDAD[[#This Row],[Ubicación]],SAP[],6,FALSE),"") -> 20/01/2028 | J2: =IFERROR(VLOOKUP(CANTIDAD[[#This Row],[Ubicación]],SAP[],7,FALSE),"") -> 1F | K2: =IFERROR(VLOOKUP(CANTIDAD[[#This Row],[Ubicación]],SAP[],10,FALSE),"") -> 60 | L2: =IFERROR(VLOOKUP(CANTIDAD[[#This Row],[Producto]],MARA[],5,FALSE),"") -> 26 | M2: =IFERROR(VLOOKUP(CANTIDAD[[#This Row],[Producto]],MARA[],4,FALSE),"") -> CJA | N2: eb6e5dc7-cdbb-41ce-a519-9db63379b734
A3: ="PASILLO " & VALUE(MID(B3, 4, 2)) -> PASILLO 1 | B3: AP-01-006-1 | C3: =IFERROR(VLOOKUP(CANTIDAD[[#This Row],[Ubicación]],SAP[],3,FALSE),"") -> 8325096 | D3: =IFERROR(VLOOKUP(CANTIDAD[[#This Row],[Producto]],MARA[],3,FALSE),"") -> 37751851006652 | E3: =IFERROR(VLOOKUP(CANTIDAD[[#This Row],[Ubicación]],SAP[],4,FALSE),"") -> INSEC.MATAPOLILLAS SAPOLIO 2A 360ML 12UN | F3: =IFERROR(VLOOKUP(CANTIDAD[[#This Row],[Ubicación]],SAP[],8,FALSE),"") -> 9 | G3: =IFERROR(VLOOKUP(CANTIDAD[[#This Row],[Ubicación]],SAP[],9,FALSE),"") -> CJA | H3: =IFERROR(VLOOKUP(CANTIDAD[[#This Row],[Ubicación]],SAP[],5,FALSE),"") -> 2607215060 | I3: =IFERROR(VLOOKUP(CANTIDAD[[#This Row],[Ubicación]],SAP[],6,FALSE),"") -> 21/07/2028 | J3: =IFERROR(VLOOKUP(CANTIDAD[[#This Row],[Ubicación]],SAP[],7,FALSE),"") -> 1F | K3: =IFERROR(VLOOKUP(CANTIDAD[[#This Row],[Ubicación]],SAP[],10,FALSE),"") -> 108 | L3: =IFERROR(VLOOKUP(CANTIDAD[[#This Row],[Producto]],MARA[],5,FALSE),"") -> 26 | M3: =IFERROR(VLOOKUP(CANTIDAD[[#This Row],[Producto]],MARA[],4,FALSE),"") -> CJA | N3: bf79d15c-aead-4215-ab87-f93820c18ac9
A4: ="PASILLO " & VALUE(MID(B4, 4, 2)) -> PASILLO 1 | B4: AP-01-007-1 | C4: =IFERROR(VLOOKUP(CANTIDAD[[#This Row],[Ubicación]],SAP[],3,FALSE),"") -> 8315030 | D4: =IFERROR(VLOOKUP(CANTIDAD[[#This Row],[Producto]],MARA[],3,FALSE),"") -> 27751851006129 | E4: =IFERROR(VLOOKUP(CANTIDAD[[#This Row],[Ubicación]],SAP[],4,FALSE),"") -> LIMPIAHORNOS SAPOLIO 360ML 12UND | F4: =IFERROR(VLOOKUP(CANTIDAD[[#This Row],[Ubicación]],SAP[],8,FALSE),"") -> 39 | G4: =IFERROR(VLOOKUP(CANTIDAD[[#This Row],[Ubicación]],SAP[],9,FALSE),"") -> CJA | H4: =IFERROR(VLOOKUP(CANTIDAD[[#This Row],[Ubicación]],SAP[],5,FALSE),"") -> 2606235060 | I4: =IFERROR(VLOOKUP(CANTIDAD[[#This Row],[Ubicación]],SAP[],6,FALSE),"") -> 23/06/2029 | J4: =IFERROR(VLOOKUP(CANTIDAD[[#This Row],[Ubicación]],SAP[],7,FALSE),"") -> 1F | K4: =IFERROR(VLOOKUP(CANTIDAD[[#This Row],[Ubicación]],SAP[],10,FALSE),"") -> 468 | L4: =IFERROR(VLOOKUP(CANTIDAD[[#This Row],[Producto]],MARA[],5,FALSE),"") -> 26 | M4: =IFERROR(VLOOKUP(CANTIDAD[[#This Row],[Producto]],MARA[],4,FALSE),"") -> CJA | N4: 56647ca4-6783-4baa-891e-d0534a8178df
A5: ="PASILLO " & VALUE(MID(B5, 4, 2)) -> PASILLO 1 | B5: AP-01-008-1 | C5: =IFERROR(VLOOKUP(CANTIDAD[[#This Row],[Ubicación]],SAP[],3,FALSE),"") -> 8315000 | D5: =IFERROR(VLOOKUP(CANTIDAD[[#This Row],[Producto]],MARA[],3,FALSE),"") -> 17751851007556 | E5: =IFERROR(VLOOKUP(CANTIDAD[[#This Row],[Ubicación]],SAP[],4,FALSE),"") -> LUSTRAMUEBLE LAVANDA PREMIO 360ML 12UND | F5: =IFERROR(VLOOKUP(CANTIDAD[[#This Row],[Ubicación]],SAP[],8,FALSE),"") -> 15 | G5: =IFERROR(VLOOKUP(CANTIDAD[[#This Row],[Ubicación]],SAP[],9,FALSE),"") -> CJA | H5: =IFERROR(VLOOKUP(CANTIDAD[[#This Row],[Ubicación]],SAP[],5,FALSE),"") -> 2608175060 | I5: =IFERROR(VLOOKUP(CANTIDAD[[#This Row],[Ubicación]],SAP[],6,FALSE),"") -> 17/08/2028 | J5: =IFERROR(VLOOKUP(CANTIDAD[[#This Row],[Ubicación]],SAP[],7,FALSE),"") -> 1F | K5: =IFERROR(VLOOKUP(CANTIDAD[[#This Row],[Ubicación]],SAP[],10,FALSE),"") -> 180 | L5: =IFERROR(VLOOKUP(CANTIDAD[[#This Row],[Producto]],MARA[],5,FALSE),"") -> 26 | M5: =IFERROR(VLOOKUP(CANTIDAD[[#This Row],[Producto]],MARA[],4,FALSE),"") -> CJA | N5: 2f444ee8-6d2d-4f83-a7ae-0eb2397a2f8e
A6: ="PASILLO " & VALUE(MID(B6, 4, 2)) -> PASILLO 1 | B6: AP-01-009-1 | C6: =IFERROR(VLOOKUP(CANTIDAD[[#This Row],[Ubicación]],SAP[],3,FALSE),"") -> 8315001 | D6: =IFERROR(VLOOKUP(CANTIDAD[[#This Row],[Producto]],MARA[],3,FALSE),"") -> 17751851007563 | E6: =IFERROR(VLOOKUP(CANTIDAD[[#This Row],[Ubicación]],SAP[],4,FALSE),"") -> LUSTRAMUEBLE LIMON PREMIO 360ML 12UND | F6: =IFERROR(VLOOKUP(CANTIDAD[[#This Row],[Ubicación]],SAP[],8,FALSE),"") -> 57 | G6: =IFERROR(VLOOKUP(CANTIDAD[[#This Row],[Ubicación]],SAP[],9,FALSE),"") -> CJA | H6: =IFERROR(VLOOKUP(CANTIDAD[[#This Row],[Ubicación]],SAP[],5,FALSE),"") -> 2608045060 | I6: =IFERROR(VLOOKUP(CANTIDAD[[#This Row],[Ubicación]],SAP[],6,FALSE),"") -> 46851 | J6: =IFERROR(VLOOKUP(CANTIDAD[[#This Row],[Ubicación]],SAP[],7,FALSE),"") -> 1F | K6: =IFERROR(VLOOKUP(CANTIDAD[[#This Row],[Ubicación]],SAP[],10,FALSE),"") -> 684 | L6: =IFERROR(VLOOKUP(CANTIDAD[[#This Row],[Producto]],MARA[],5,FALSE),"") -> 26 | M6: =IFERROR(VLOOKUP(CANTIDAD[[#This Row],[Producto]],MARA[],4,FALSE),"") -> CJA | N6: b07e50f8-9315-4b9e-b0c8-cc043904071c
A7: ="PASILLO " & VALUE(MID(B7, 4, 2)) -> PASILLO 1 | B7: AP-01-010-1 | C7: =IFERROR(VLOOKUP(CANTIDAD[[#This Row],[Ubicación]],SAP[],3,FALSE),"") -> 8325116 | D7: =IFERROR(VLOOKUP(CANTIDAD[[#This Row],[Producto]],MARA[],3,FALSE),"") -> 47751851011196 | E7: =IFERROR(VLOOKUP(CANTIDAD[[#This Row],[Ubicación]],SAP[],4,FALSE),"") -> INSEC. MATA ACAROS SAPOLIO RE 360ML 12UN | F7: =IFERROR(VLOOKUP(CANTIDAD[[#This Row],[Ubicación]],SAP[],8,FALSE),"") -> 76 | G7: =IFERROR(VLOOKUP(CANTIDAD[[#This Row],[Ubicación]],SAP[],9,FALSE),"") -> CJA | H7: =IFERROR(VLOOKUP(CANTIDAD[[#This Row],[Ubicación]],SAP[],5,FALSE),"") -> 2608175060 | I7: =IFERROR(VLOOKUP(CANTIDAD[[#This Row],[Ubicación]],SAP[],6,FALSE),"") -> 17/08/2028 | J7: =IFERROR(VLOOKUP(CANTIDAD[[#This Row],[Ubicación]],SAP[],7,FALSE),"") -> 1F | K7: =IFERROR(VLOOKUP(CANTIDAD[[#This Row],[Ubicación]],SAP[],10,FALSE),"") -> 912 | L7: =IFERROR(VLOOKUP(CANTIDAD[[#This Row],[Producto]],MARA[],5,FALSE),"") -> 26 | M7: =IFERROR(VLOOKUP(CANTIDAD[[#This Row],[Producto]],MARA[],4,FALSE),"") -> CJA | N7: 86660267-3bff-4639-990e-ebfe8586daf3
A8: ="PASILLO " & VALUE(MID(B8, 4, 2)) -> PASILLO 1 | B8: AP-01-011-1 | C8: =IFERROR(VLOOKUP(CANTIDAD[[#This Row],[Ubicación]],SAP[],3,FALSE),"") -> 8325118 | D8: =IFERROR(VLOOKUP(CANTIDAD[[#This Row],[Producto]],MARA[],3,FALSE),"") -> 47751851006666 | E8: =IFERROR(VLOOKUP(CANTIDAD[[#This Row],[Ubicación]],SAP[],4,FALSE),"") -> INSEC MATA TERMITAS SAPOLIO RE 360ML12UN | F8: =IFERROR(VLOOKUP(CANTIDAD[[#This Row],[Ubicación]],SAP[],8,FALSE),"") -> 76 | G8: =IFERROR(VLOOKUP(CANTIDAD[[#This Row],[Ubicación]],SAP[],9,FALSE),"") -> CJA | H8: =IFERROR(VLOOKUP(CANTIDAD[[#This Row],[Ubicación]],SAP[],5,FALSE),"") -> 2608245060 | I8: =IFERROR(VLOOKUP(CANTIDAD[[#This Row],[Ubicación]],SAP[],6,FALSE),"") -> 24/08/2028 | J8: =IFERROR(VLOOKUP(CANTIDAD[[#This Row],[Ubicación]],SAP[],7,FALSE),"") -> 1F | K8: =IFERROR(VLOOKUP(CANTIDAD[[#This Row],[Ubicación]],SAP[],10,FALSE),"") -> 912 | L8: =IFERROR(VLOOKUP(CANTIDAD[[#This Row],[Producto]],MARA[],5,FALSE),"") -> 26 | M8: =IFERROR(VLOOKUP(CANTIDAD[[#This Row],[Producto]],MARA[],4,FALSE),"") -> CJA | N8: 6c13cb54-22ce-4c19-b500-f8fc16c234e7
A9: ="PASILLO " & VALUE(MID(B9, 4, 2)) -> PASILLO 1 | B9: AP-01-012-1 | C9: =IFERROR(VLOOKUP(CANTIDAD[[#This Row],[Ubicación]],SAP[],3,FALSE),"") -> 8309033 | D9: =IFERROR(VLOOKUP(CANTIDAD[[#This Row],[Producto]],MARA[],3,FALSE),"") -> 17751851019634 | E9: =IFERROR(VLOOKUP(CANTIDAD[[#This Row],[Ubicación]],SAP[],4,FALSE),"") -> PERFU.RPTO V/FRANCESA SAPOLIO 240ML 12UN | F9: =IFERROR(VLOOKUP(CANTIDAD[[#This Row],[Ubicación]],SAP[],8,FALSE),"") -> 50 | G9: =IFERROR(VLOOKUP(CANTIDAD[[#This Row],[Ubicación]],SAP[],9,FALSE),"") -> CJA | H9: =IFERROR(VLOOKUP(CANTIDAD[[#This Row],[Ubicación]],SAP[],5,FALSE),"") -> 2607205060 | I9: =IFERROR(VLOOKUP(CANTIDAD[[#This Row],[Ubicación]],SAP[],6,FALSE),"") -> 20/07/2029 | J9: =IFERROR(VLOOKUP(CANTIDAD[[#This Row],[Ubicación]],SAP[],7,FALSE),"") -> 1F | K9: =IFERROR(VLOOKUP(CANTIDAD[[#This Row],[Ubicación]],SAP[],10,FALSE),"") -> 600 | L9: =IFERROR(VLOOKUP(CANTIDAD[[#This Row],[Producto]],MARA[],5,FALSE),"") -> 18 | M9: =IFERROR(VLOOKUP(CANTIDAD[[#This Row],[Producto]],MARA[],4,FALSE),"") -> CJA | N9: 8d3996ca-5273-4b86-957d-4630e9ca50f2
A10: ="PASILLO " & VALUE(MID(B10, 4, 2)) -> PASILLO 1 | B10: AP-01-013-1 | C10: =IFERROR(VLOOKUP(CANTIDAD[[#This Row],[Ubicación]],SAP[],3,FALSE),"") -> 8325095 | D10: =IFERROR(VLOOKUP(CANTIDAD[[#This Row],[Producto]],MARA[],3,FALSE),"") -> 37751851006638 | E10: =IFERROR(VLOOKUP(CANTIDAD[[#This Row],[Ubicación]],SAP[],4,FALSE),"") -> INSEC.MATAPULGAS SAPOLIO 2A 360ML 12UND | F10: =IFERROR(VLOOKUP(CANTIDAD[[#This Row],[Ubicación]],SAP[],8,FALSE),"") -> 44 | G10: =IFERROR(VLOOKUP(CANTIDAD[[#This Row],[Ubicación]],SAP[],9,FALSE),"") -> CJA | H10: =IFERROR(VLOOKUP(CANTIDAD[[#This Row],[Ubicación]],SAP[],5,FALSE),"") -> 2607245060 | I10: =IFERROR(VLOOKUP(CANTIDAD[[#This Row],[Ubicación]],SAP[],6,FALSE),"") -> 24/07/2028 | J10: =IFERROR(VLOOKUP(CANTIDAD[[#This Row],[Ubicación]],SAP[],7,FALSE),"") -> 1F | K10: =IFERROR(VLOOKUP(CANTIDAD[[#This Row],[Ubicación]],SAP[],10,FALSE),"") -> 528 | L10: =IFERROR(VLOOKUP(CANTIDAD[[#This Row],[Producto]],MARA[],5,FALSE),"") -> 26 | M10: =IFERROR(VLOOKUP(CANTIDAD[[#This Row],[Producto]],MARA[],4,FALSE),"") -> CJA | N10: 99f2985a-bd91-41b2-9f53-d6e81ef26d63
A11: ="PASILLO " & VALUE(MID(B11, 4, 2)) -> PASILLO 1 | B11: AP-01-014-1 | C11: =IFERROR(VLOOKUP(CANTIDAD[[#This Row],[Ubicación]],SAP[],3,FALSE),"") -> 8325093 | D11: =IFERROR(VLOOKUP(CANTIDAD[[#This Row],[Producto]],MARA[],3,FALSE),"") -> 27751851020156 | E11: =IFERROR(VLOOKUP(CANTIDAD[[#This Row],[Ubicación]],SAP[],4,FALSE),"") -> INSEC.MATATODO SAPOLIO 2A 360ML 12UND | F11: =IFERROR(VLOOKUP(CANTIDAD[[#This Row],[Ubicación]],SAP[],8,FALSE),"") -> 19 | G11: =IFERROR(VLOOKUP(CANTIDAD[[#This Row],[Ubicación]],SAP[],9,FALSE),"") -> CJA | H11: =IFERROR(VLOOKUP(CANTIDAD[[#This Row],[Ubicación]],SAP[],5,FALSE),"") -> 2608125060 | I11: =IFERROR(VLOOKUP(CANTIDAD[[#This Row],[Ubicación]],SAP[],6,FALSE),"") -> 47095 | J11: =IFERROR(VLOOKUP(CANTIDAD[[#This Row],[Ubicación]],SAP[],7,FALSE),"") -> 1F | K11: =IFERROR(VLOOKUP(CANTIDAD[[#This Row],[Ubicación]],SAP[],10,FALSE),"") -> 228 | L11: =IFERROR(VLOOKUP(CANTIDAD[[#This Row],[Producto]],MARA[],5,FALSE),"") -> 26 | M11: =IFERROR(VLOOKUP(CANTIDAD[[#This Row],[Producto]],MARA[],4,FALSE),"") -> CJA | N11: a24b12da-2175-4335-a43b-bc36a0f420a0
A12: ="PASILLO " & VALUE(MID(B12, 4, 2)) -> PASILLO 1 | B12: AP-01-015-1 | C12: =IFERROR(VLOOKUP(CANTIDAD[[#This Row],[Ubicación]],SAP[],3,FALSE),"") | D12: =IFERROR(VLOOKUP(CANTIDAD[[#This Row],[Producto]],MARA[],3,FALSE),"") | E12: =IFERROR(VLOOKUP(CANTIDAD[[#This Row],[Ubicación]],SAP[],4,FALSE),"") | F12: =IFERROR(VLOOKUP(CANTIDAD[[#This Row],[Ubicación]],SAP[],8,FALSE),"") | G12: =IFERROR(VLOOKUP(CANTIDAD[[#This Row],[Ubicación]],SAP[],9,FALSE),"") | H12: =IFERROR(VLOOKUP(CANTIDAD[[#This Row],[Ubicación]],SAP[],5,FALSE),"") | I12: =IFERROR(VLOOKUP(CANTIDAD[[#This Row],[Ubicación]],SAP[],6,FALSE),"") | J12: =IFERROR(VLOOKUP(CANTIDAD[[#This Row],[Ubicación]],SAP[],7,FALSE),"") | K12: =IFERROR(VLOOKUP(CANTIDAD[[#This Row],[Ubicación]],SAP[],10,FALSE),"") | L12: =IFERROR(VLOOKUP(CANTIDAD[[#This Row],[Producto]],MARA[],5,FALSE),"") | M12: =IFERROR(VLOOKUP(CANTIDAD[[#This Row],[Producto]],MARA[],4,FALSE),"") | N12: 0d4755c9-4429-449f-a0e1-b88b765d999f
A13: ="PASILLO " & VALUE(MID(B13, 4, 2)) -> PASILLO 1 | B13: AP-01-016-1 | C13: =IFERROR(VLOOKUP(CANTIDAD[[#This Row],[Ubicación]],SAP[],3,FALSE),"") -> 8325084 | D13: =IFERROR(VLOOKUP(CANTIDAD[[#This Row],[Producto]],MARA[],3,FALSE),"") -> 67751851006622 | E13: =IFERROR(VLOOKUP(CANTIDAD[[#This Row],[Ubicación]],SAP[],4,FALSE),"") -> INSE. SAP. MAT MOS Y ZANC BO 360ML 12UND | F13: =IFERROR(VLOOKUP(CANTIDAD[[#This Row],[Ubicación]],SAP[],8,FALSE),"") -> 60 | G13: =IFERROR(VLOOKUP(CANTIDAD[[#This Row],[Ubicación]],SAP[],9,FALSE),"") -> CJA | H13: =IFERROR(VLOOKUP(CANTIDAD[[#This Row],[Ubicación]],SAP[],5,FALSE),"") -> 2608245060 | I13: =IFERROR(VLOOKUP(CANTIDAD[[#This Row],[Ubicación]],SAP[],6,FALSE),"") -> 24/08/2028 | J13: =IFERROR(VLOOKUP(CANTIDAD[[#This Row],[Ubicación]],SAP[],7,FALSE),"") -> 1F | K13: =IFERROR(VLOOKUP(CANTIDAD[[#This Row],[Ubicación]],SAP[],10,FALSE),"") -> 720 | L13: =IFERROR(VLOOKUP(CANTIDAD[[#This Row],[Producto]],MARA[],5,FALSE),"") -> 26 | M13: =IFERROR(VLOOKUP(CANTIDAD[[#This Row],[Producto]],MARA[],4,FALSE),"") -> CJA | N13: 8f336a74-22ba-46ed-8de8-f35e61e7d517
... A601: ="PASILLO " & VALUE(MID(B601, 4, 2)) -> PASILLO 16 | B601: PP-16-052-1 | C601: =IFERROR(VLOOKUP(CANTIDAD[[#This Row],[Ubicación]],SAP[],3,FALSE),"") | D601: =IFERROR(VLOOKUP(CANTIDAD[[#This Row],[Producto]],MARA[],3,FALSE),"") | E601: =IFERROR(VLOOKUP(CANTIDAD[[#This Row],[Ubicación]],SAP[],4,FALSE),"") | F601: =IFERROR(VLOOKUP(CANTIDAD[[#This Row],[Ubicación]],SAP[],8,FALSE),"") | G601: =IFERROR(VLOOKUP(CANTIDAD[[#This Row],[Ubicación]],SAP[],9,FALSE),"") | H601: =IFERROR(VLOOKUP(CANTIDAD[[#This Row],[Ubicación]],SAP[],5,FALSE),"") | I601: =IFERROR(VLOOKUP(CANTIDAD[[#This Row],[Ubicación]],SAP[],6,FALSE),"") | J601: =IFERROR(VLOOKUP(CANTIDAD[[#This Row],[Ubicación]],SAP[],7,FALSE),"") | K601: =IFERROR(VLOOKUP(CANTIDAD[[#This Row],[Ubicación]],SAP[],10,FALSE),"") | L601: =IFERROR(VLOOKUP(CANTIDAD[[#This Row],[Producto]],MARA[],5,FALSE),"") | M601: =IFERROR(VLOOKUP(CANTIDAD[[#This Row],[Producto]],MARA[],4,FALSE),"") | N601: 5568628d-4aa1-4aa8-a75e-21420380742a

Sheet OPERARIOS
A1: NOMBRE | B1: __PowerAppsId__
A2: RUTH | B2: e4194c23-ddd4-4eb1-b4a1-b9461f030591
A3: MARCO | B3: 254aa4c5-88b2-4813-9a06-4a16f37819dc
A4: LUIS | B4: c40951da-15a6-417f-9e2c-3604e50754d8
A5: DOÑES | B5: d4337582-fd70-4db0-88a0-45d81f35fc21
A6: SCOOBY | B6: 64ba0427-8251-4ae1-bece-9fc4c6a830ae
A7: carlos | B7: a9fc3486-e27b-4efe-8b26-d4919ac43f89

Sheet Tiempos
A1: Pasillo | B1: Estado | C1: Operario | D1: Avance | E1: Ub. Registradas | F1: Total de Ubicaciones | G1: Inicio | H1: Fin | I1: DuracionMin | J1: DIFERENCIAS | K1: STATUS | L1: DIFERENCIAS2 | M1: STATUS RECONTEO | N1: __PowerAppsId__
A2: Pasillo 1 | B2: En Proceso | C2: RUTH | D2: =IFERROR(Tiempos[[#This Row],[Ub. Registradas]]/Tiempos[[#This Row],[Total de Ubicaciones]],"") -> 0.05 | E2: {=IFERROR(ROWS(_xlfn.UNIQUE(_xlfn._xlws.FILTER('Registros'!D:D, ('Registros'!C:C=Tiempos[[#This Row],[Pasillo]]) * ('Registros'!E:E<>"")))), 0)} -> 2 | F2: =COUNTIF('CRUCE'!A:A, Tiempos[[#This Row],[Pasillo]]) -> 40 | G2: 46293.749 | I2: =IF(OR(Tiempos[[#This Row],[Inicio]]="", Tiempos[[#This Row],[Fin]]=""), "", (Tiempos[[#This Row],[Fin]]-Tiempos[[#This Row],[Inicio]])*1440) | J2: =COUNTIFS(CRUCE[PASILLO], Tiempos[[#This Row],[Pasillo]], CRUCE[STATUS], "<>CUADRADO",CRUCE[STATUS], "<>PENDIENTE") -> 0 | K2: =IF(Tiempos[[#This Row],[Estado]]="PENDIENTE", "", IF(Tiempos[[#This Row],[DIFERENCIAS]]=0, "Cuadrado", "Reconteo")) -> Cuadrado | L2: =COUNTIFS(CRUCE[PASILLO], Tiempos[[#This Row],[Pasillo]], CRUCE[STATUS2], "<>CUADRADO",CRUCE[STATUS2], "<>PENDIENTE") -> 0 | M2: =IF(Tiempos[[#This Row],[STATUS]]="cuadrado", "", IF(Tiempos[[#This Row],[DIFERENCIAS2]]=0, "Cuadrado", "Reconteo")) | N2: 1f1ee163-8703-45b8-a9ad-78909e947f5e
A3: Pasillo 5 | B3: Pendiente | D3: =IFERROR(Tiempos[[#This Row],[Ub. Registradas]]/Tiempos[[#This Row],[Total de Ubicaciones]],"") -> 0 | E3: {=IFERROR(ROWS(_xlfn.UNIQUE(_xlfn._xlws.FILTER('Registros'!D:D, ('Registros'!C:C=Tiempos[[#This Row],[Pasillo]]) * ('Registros'!E:E<>"")))), 0)} -> 0 | F3: =COUNTIF('CRUCE'!A:A, Tiempos[[#This Row],[Pasillo]]) -> 48 | I3: =IF(OR(Tiempos[[#This Row],[Inicio]]="", Tiempos[[#This Row],[Fin]]=""), "", (Tiempos[[#This Row],[Fin]]-Tiempos[[#This Row],[Inicio]])*1440) | J3: =COUNTIFS(CRUCE[PASILLO], Tiempos[[#This Row],[Pasillo]], CRUCE[STATUS], "<>CUADRADO",CRUCE[STATUS], "<>PENDIENTE") -> 0 | K3: =IF(Tiempos[[#This Row],[Estado]]="PENDIENTE", "", IF(Tiempos[[#This Row],[DIFERENCIAS]]=0, "Cuadrado", "Reconteo")) | L3: =COUNTIFS(CRUCE[PASILLO], Tiempos[[#This Row],[Pasillo]], CRUCE[STATUS2], "<>CUADRADO",CRUCE[STATUS2], "<>PENDIENTE") -> 0 | M3: =IF(Tiempos[[#This Row],[STATUS]]="cuadrado", "", IF(Tiempos[[#This Row],[DIFERENCIAS2]]=0, "Cuadrado", "Reconteo")) -> Cuadrado | N3: 194d4492-109e-45a6-bf45-6caf709d5b34
A4: Pasillo 6 | B4: Pendiente | D4: =IFERROR(Tiempos[[#This Row],[Ub. Registradas]]/Tiempos[[#This Row],[Total de Ubicaciones]],"") -> 0 | E4: {=IFERROR(ROWS(_xlfn.UNIQUE(_xlfn._xlws.FILTER('Registros'!D:D, ('Registros'!C:C=Tiempos[[#This Row],[Pasillo]]) * ('Registros'!E:E<>"")))), 0)} -> 0 | F4: =COUNTIF('CRUCE'!A:A, Tiempos[[#This Row],[Pasillo]]) -> 51 | I4: =IF(OR(Tiempos[[#This Row],[Inicio]]="", Tiempos[[#This Row],[Fin]]=""), "", (Tiempos[[#This Row],[Fin]]-Tiempos[[#This Row],[Inicio]])*1440) | J4: =COUNTIFS(CRUCE[PASILLO], Tiempos[[#This Row],[Pasillo]], CRUCE[STATUS], "<>CUADRADO",CRUCE[STATUS], "<>PENDIENTE") -> 0 | K4: =IF(Tiempos[[#This Row],[Estado]]="PENDIENTE", "", IF(Tiempos[[#This Row],[DIFERENCIAS]]=0, "Cuadrado", "Reconteo")) | L4: =COUNTIFS(CRUCE[PASILLO], Tiempos[[#This Row],[Pasillo]], CRUCE[STATUS2], "<>CUADRADO",CRUCE[STATUS2], "<>PENDIENTE") -> 0 | M4: =IF(Tiempos[[#This Row],[STATUS]]="cuadrado", "", IF(Tiempos[[#This Row],[DIFERENCIAS2]]=0, "Cuadrado", "Reconteo")) -> Cuadrado | N4: 76c65302-dbca-4bc5-ad98-ec0a172c413f
A5: Pasillo 7 | B5: Pendiente | D5: =IFERROR(Tiempos[[#This Row],[Ub. Registradas]]/Tiempos[[#This Row],[Total de Ubicaciones]],"") -> 0 | E5: {=IFERROR(ROWS(_xlfn.UNIQUE(_xlfn._xlws.FILTER('Registros'!D:D, ('Registros'!C:C=Tiempos[[#This Row],[Pasillo]]) * ('Registros'!E:E<>"")))), 0)} -> 0 | F5: =COUNTIF('CRUCE'!A:A, Tiempos[[#This Row],[Pasillo]]) -> 51 | I5: =IF(OR(Tiempos[[#This Row],[Inicio]]="", Tiempos[[#This Row],[Fin]]=""), "", (Tiempos[[#This Row],[Fin]]-Tiempos[[#This Row],[Inicio]])*1440) | J5: =COUNTIFS(CRUCE[PASILLO], Tiempos[[#This Row],[Pasillo]], CRUCE[STATUS], "<>CUADRADO",CRUCE[STATUS], "<>PENDIENTE") -> 0 | K5: =IF(Tiempos[[#This Row],[Estado]]="PENDIENTE", "", IF(Tiempos[[#This Row],[DIFERENCIAS]]=0, "Cuadrado", "Reconteo")) | L5: =COUNTIFS(CRUCE[PASILLO], Tiempos[[#This Row],[Pasillo]], CRUCE[STATUS2], "<>CUADRADO",CRUCE[STATUS2], "<>PENDIENTE") -> 0 | M5: =IF(Tiempos[[#This Row],[STATUS]]="cuadrado", "", IF(Tiempos[[#This Row],[DIFERENCIAS2]]=0, "Cuadrado", "Reconteo")) -> Cuadrado | N5: fdbe60f2-c6db-4617-ae2f-6f07885345d0
A6: Pasillo 8 | B6: Pendiente | D6: =IFERROR(Tiempos[[#This Row],[Ub. Registradas]]/Tiempos[[#This Row],[Total de Ubicaciones]],"") -> 0 | E6: {=IFERROR(ROWS(_xlfn.UNIQUE(_xlfn._xlws.FILTER('Registros'!D:D, ('Registros'!C:C=Tiempos[[#This Row],[Pasillo]]) * ('Registros'!E:E<>"")))), 0)} -> 0 | F6: =COUNTIF('CRUCE'!A:A, Tiempos[[#This Row],[Pasillo]]) -> 52 | I6: =IF(OR(Tiempos[[#This Row],[Inicio]]="", Tiempos[[#This Row],[Fin]]=""), "", (Tiempos[[#This Row],[Fin]]-Tiempos[[#This Row],[Inicio]])*1440) | J6: =COUNTIFS(CRUCE[PASILLO], Tiempos[[#This Row],[Pasillo]], CRUCE[STATUS], "<>CUADRADO",CRUCE[STATUS], "<>PENDIENTE") -> 0 | K6: =IF(Tiempos[[#This Row],[Estado]]="PENDIENTE", "", IF(Tiempos[[#This Row],[DIFERENCIAS]]=0, "Cuadrado", "Reconteo")) | L6: =COUNTIFS(CRUCE[PASILLO], Tiempos[[#This Row],[Pasillo]], CRUCE[STATUS2], "<>CUADRADO",CRUCE[STATUS2], "<>PENDIENTE") -> 1 | M6: =IF(Tiempos[[#This Row],[STATUS]]="cuadrado", "", IF(Tiempos[[#This Row],[DIFERENCIAS2]]=0, "Cuadrado", "Reconteo")) -> Reconteo | N6: f507ee28-44dd-46fa-8952-12d603c9893f
A7: Pasillo 9 | B7: Pendiente | D7: =IFERROR(Tiempos[[#This Row],[Ub. Registradas]]/Tiempos[[#This Row],[Total de Ubicaciones]],"") -> 0 | E7: {=IFERROR(ROWS(_xlfn.UNIQUE(_xlfn._xlws.FILTER('Registros'!D:D, ('Registros'!C:C=Tiempos[[#This Row],[Pasillo]]) * ('Registros'!E:E<>"")))), 0)} -> 0 | F7: =COUNTIF('CRUCE'!A:A, Tiempos[[#This Row],[Pasillo]]) -> 51 | I7: =IF(OR(Tiempos[[#This Row],[Inicio]]="", Tiempos[[#This Row],[Fin]]=""), "", (Tiempos[[#This Row],[Fin]]-Tiempos[[#This Row],[Inicio]])*1440) | J7: =COUNTIFS(CRUCE[PASILLO], Tiempos[[#This Row],[Pasillo]], CRUCE[STATUS], "<>CUADRADO",CRUCE[STATUS], "<>PENDIENTE") -> 0 | K7: =IF(Tiempos[[#This Row],[Estado]]="PENDIENTE", "", IF(Tiempos[[#This Row],[DIFERENCIAS]]=0, "Cuadrado", "Reconteo")) | L7: =COUNTIFS(CRUCE[PASILLO], Tiempos[[#This Row],[Pasillo]], CRUCE[STATUS2], "<>CUADRADO",CRUCE[STATUS2], "<>PENDIENTE") -> 0 | M7: =IF(Tiempos[[#This Row],[STATUS]]="cuadrado", "", IF(Tiempos[[#This Row],[DIFERENCIAS2]]=0, "Cuadrado", "Reconteo")) -> Cuadrado | N7: 8ee267b8-1051-42c9-a3ca-eeda55364e76
A8: Pasillo 10 | B8: Pendiente | D8: =IFERROR(Tiempos[[#This Row],[Ub. Registradas]]/Tiempos[[#This Row],[Total de Ubicaciones]],"") -> 0 | E8: {=IFERROR(ROWS(_xlfn.UNIQUE(_xlfn._xlws.FILTER('Registros'!D:D, ('Registros'!C:C=Tiempos[[#This Row],[Pasillo]]) * ('Registros'!E:E<>"")))), 0)} -> 0 | F8: =COUNTIF('CRUCE'!A:A, Tiempos[[#This Row],[Pasillo]]) -> 51 | I8: =IF(OR(Tiempos[[#This Row],[Inicio]]="", Tiempos[[#This Row],[Fin]]=""), "", (Tiempos[[#This Row],[Fin]]-Tiempos[[#This Row],[Inicio]])*1440) | J8: =COUNTIFS(CRUCE[PASILLO], Tiempos[[#This Row],[Pasillo]], CRUCE[STATUS], "<>CUADRADO",CRUCE[STATUS], "<>PENDIENTE") -> 0 | K8: =IF(Tiempos[[#This Row],[Estado]]="PENDIENTE", "", IF(Tiempos[[#This Row],[DIFERENCIAS]]=0, "Cuadrado", "Reconteo")) | L8: =COUNTIFS(CRUCE[PASILLO], Tiempos[[#This Row],[Pasillo]], CRUCE[STATUS2], "<>CUADRADO",CRUCE[STATUS2], "<>PENDIENTE") -> 0 | M8: =IF(Tiempos[[#This Row],[STATUS]]="cuadrado", "", IF(Tiempos[[#This Row],[DIFERENCIAS2]]=0, "Cuadrado", "Reconteo")) -> Cuadrado | N8: cdd9f442-c8d2-4380-ab8e-f4bf33c7d872
A9: Pasillo 11 | B9: Pendiente | D9: =IFERROR(Tiempos[[#This Row],[Ub. Registradas]]/Tiempos[[#This Row],[Total de Ubicaciones]],"") -> 0 | E9: {=IFERROR(ROWS(_xlfn.UNIQUE(_xlfn._xlws.FILTER('Registros'!D:D, ('Registros'!C:C=Tiempos[[#This Row],[Pasillo]]) * ('Registros'!E:E<>"")))), 0)} -> 0 | F9: =COUNTIF('CRUCE'!A:A, Tiempos[[#This Row],[Pasillo]]) -> 52 | I9: =IF(OR(Tiempos[[#This Row],[Inicio]]="", Tiempos[[#This Row],[Fin]]=""), "", (Tiempos[[#This Row],[Fin]]-Tiempos[[#This Row],[Inicio]])*1440) | J9: =COUNTIFS(CRUCE[PASILLO], Tiempos[[#This Row],[Pasillo]], CRUCE[STATUS], "<>CUADRADO",CRUCE[STATUS], "<>PENDIENTE") -> 0 | K9: =IF(Tiempos[[#This Row],[Estado]]="PENDIENTE", "", IF(Tiempos[[#This Row],[DIFERENCIAS]]=0, "Cuadrado", "Reconteo")) | L9: =COUNTIFS(CRUCE[PASILLO], Tiempos[[#This Row],[Pasillo]], CRUCE[STATUS2], "<>CUADRADO",CRUCE[STATUS2], "<>PENDIENTE") -> 0 | M9: =IF(Tiempos[[#This Row],[STATUS]]="cuadrado", "", IF(Tiempos[[#This Row],[DIFERENCIAS2]]=0, "Cuadrado", "Reconteo")) -> Cuadrado | N9: eb7c406e-0b40-4cac-9f90-c8e6604df8f4
A10: Pasillo 12 | B10: Pendiente | D10: =IFERROR(Tiempos[[#This Row],[Ub. Registradas]]/Tiempos[[#This Row],[Total de Ubicaciones]],"") -> 0 | E10: {=IFERROR(ROWS(_xlfn.UNIQUE(_xlfn._xlws.FILTER('Registros'!D:D, ('Registros'!C:C=Tiempos[[#This Row],[Pasillo]]) * ('Registros'!E:E<>"")))), 0)} -> 0 | F10: =COUNTIF('CRUCE'!A:A, Tiempos[[#This Row],[Pasillo]]) -> 51 | I10: =IF(OR(Tiempos[[#This Row],[Inicio]]="", Tiempos[[#This Row],[Fin]]=""), "", (Tiempos[[#This Row],[Fin]]-Tiempos[[#This Row],[Inicio]])*1440) | J10: =COUNTIFS(CRUCE[PASILLO], Tiempos[[#This Row],[Pasillo]], CRUCE[STATUS], "<>CUADRADO",CRUCE[STATUS], "<>PENDIENTE") -> 0 | K10: =IF(Tiempos[[#This Row],[Estado]]="PENDIENTE", "", IF(Tiempos[[#This Row],[DIFERENCIAS]]=0, "Cuadrado", "Reconteo")) | L10: =COUNTIFS(CRUCE[PASILLO], Tiempos[[#This Row],[Pasillo]], CRUCE[STATUS2], "<>CUADRADO",CRUCE[STATUS2], "<>PENDIENTE") -> 0 | M10: =IF(Tiempos[[#This Row],[STATUS]]="cuadrado", "", IF(Tiempos[[#This Row],[DIFERENCIAS2]]=0, "Cuadrado", "Reconteo")) -> Cuadrado | N10: d4ed75ff-4c90-493f-81d8-db9925e32d24
A11: Pasillo 13 | B11: Pendiente | D11: =IFERROR(Tiempos[[#This Row],[Ub. Registradas]]/Tiempos[[#This Row],[Total de Ubicaciones]],"") -> 0 | E11: {=IFERROR(ROWS(_xlfn.UNIQUE(_xlfn._xlws.FILTER('Registros'!D:D, ('Registros'!C:C=Tiempos[[#This Row],[Pasillo]]) * ('Registros'!E:E<>"")))), 0)} -> 0 | F11: =COUNTIF('CRUCE'!A:A, Tiempos[[#This Row],[Pasillo]]) -> 51 | I11: =IF(OR(Tiempos[[#This Row],[Inicio]]="", Tiempos[[#This Row],[Fin]]=""), "", (Tiempos[[#This Row],[Fin]]-Tiempos[[#This Row],[Inicio]])*1440) | J11: =COUNTIFS(CRUCE[PASILLO], Tiempos[[#This Row],[Pasillo]], CRUCE[STATUS], "<>CUADRADO",CRUCE[STATUS], "<>PENDIENTE") -> 0 | K11: =IF(Tiempos[[#This Row],[Estado]]="PENDIENTE", "", IF(Tiempos[[#This Row],[DIFERENCIAS]]=0, "Cuadrado", "Reconteo")) | L11: =COUNTIFS(CRUCE[PASILLO], Tiempos[[#This Row],[Pasillo]], CRUCE[STATUS2], "<>CUADRADO",CRUCE[STATUS2], "<>PENDIENTE") -> 0 | M11: =IF(Tiempos[[#This Row],[STATUS]]="cuadrado", "", IF(Tiempos[[#This Row],[DIFERENCIAS2]]=0, "Cuadrado", "Reconteo")) -> Cuadrado | N11: 544cb243-e28b-4a62-b8dd-6cb17df0813a
A12: Pasillo 15 | B12: Pendiente | D12: =IFERROR(Tiempos[[#This Row],[Ub. Registradas]]/Tiempos[[#This Row],[Total de Ubicaciones]],"") -> 0 | E12: {=IFERROR(ROWS(_xlfn.UNIQUE(_xlfn._xlws.FILTER('Registros'!D:D, ('Registros'!C:C=Tiempos[[#This Row],[Pasillo]]) * ('Registros'!E:E<>"")))), 0)} -> 0 | F12: =COUNTIF('CRUCE'!A:A, Tiempos[[#This Row],[Pasillo]]) -> 51 | I12: =IF(OR(Tiempos[[#This Row],[Inicio]]="", Tiempos[[#This Row],[Fin]]=""), "", (Tiempos[[#This Row],[Fin]]-Tiempos[[#This Row],[Inicio]])*1440) | J12: =COUNTIFS(CRUCE[PASILLO], Tiempos[[#This Row],[Pasillo]], CRUCE[STATUS], "<>CUADRADO",CRUCE[STATUS], "<>PENDIENTE") -> 0 | K12: =IF(Tiempos[[#This Row],[Estado]]="PENDIENTE", "", IF(Tiempos[[#This Row],[DIFERENCIAS]]=0, "Cuadrado", "Reconteo")) | L12: =COUNTIFS(CRUCE[PASILLO], Tiempos[[#This Row],[Pasillo]], CRUCE[STATUS2], "<>CUADRADO",CRUCE[STATUS2], "<>PENDIENTE") -> 0 | M12: =IF(Tiempos[[#This Row],[STATUS]]="cuadrado", "", IF(Tiempos[[#This Row],[DIFERENCIAS2]]=0, "Cuadrado", "Reconteo")) -> Cuadrado | N12: 22c1e7b9-c56a-40cb-8750-4fe62f376eab
A13: Pasillo 16 | B13: Pendiente | D13: =IFERROR(Tiempos[[#This Row],[Ub. Registradas]]/Tiempos[[#This Row],[Total de Ubicaciones]],"") -> 0 | E13: {=IFERROR(ROWS(_xlfn.UNIQUE(_xlfn._xlws.FILTER('Registros'!D:D, ('Registros'!C:C=Tiempos[[#This Row],[Pasillo]]) * ('Registros'!E:E<>"")))), 0)} -> 0 | F13: =COUNTIF('CRUCE'!A:A, Tiempos[[#This Row],[Pasillo]]) -> 51 | I13: =IF(OR(Tiempos[[#This Row],[Inicio]]="", Tiempos[[#This Row],[Fin]]=""), "", (Tiempos[[#This Row],[Fin]]-Tiempos[[#This Row],[Inicio]])*1440) | J13: =COUNTIFS(CRUCE[PASILLO], Tiempos[[#This Row],[Pasillo]], CRUCE[STATUS], "<>CUADRADO",CRUCE[STATUS], "<>PENDIENTE") -> 0 | K13: =IF(Tiempos[[#This Row],[Estado]]="PENDIENTE", "", IF(Tiempos[[#This Row],[DIFERENCIAS]]=0, "Cuadrado", "Reconteo")) | L13: =COUNTIFS(CRUCE[PASILLO], Tiempos[[#This Row],[Pasillo]], CRUCE[STATUS2], "<>CUADRADO",CRUCE[STATUS2], "<>PENDIENTE") -> 0 | M13: =IF(Tiempos[[#This Row],[STATUS]]="cuadrado", "", IF(Tiempos[[#This Row],[DIFERENCIAS2]]=0, "Cuadrado", "Reconteo")) -> Cuadrado | N13: aa9dda26-5515-41b2-b63c-d291ba000810
A14: Pasillo 23 | B14: Pendiente | D14: =IFERROR(Tiempos[[#This Row],[Ub. Registradas]]/Tiempos[[#This Row],[Total de Ubicaciones]],"") | E14: {=IFERROR(ROWS(_xlfn.UNIQUE(_xlfn._xlws.FILTER('Registros'!D:D, ('Registros'!C:C=Tiempos[[#This Row],[Pasillo]]) * ('Registros'!E:E<>"")))), 0)} -> 0 | F14: =COUNTIF('CRUCE'!A:A, Tiempos[[#This Row],[Pasillo]]) -> 0 | I14: =IF(OR(Tiempos[[#This Row],[Inicio]]="", Tiempos[[#This Row],[Fin]]=""), "", (Tiempos[[#This Row],[Fin]]-Tiempos[[#This Row],[Inicio]])*1440) | J14: =COUNTIFS(CRUCE[PASILLO], Tiempos[[#This Row],[Pasillo]], CRUCE[STATUS], "<>CUADRADO",CRUCE[STATUS], "<>PENDIENTE") -> 0 | K14: =IF(Tiempos[[#This Row],[Estado]]="PENDIENTE", "", IF(Tiempos[[#This Row],[DIFERENCIAS]]=0, "Cuadrado", "Reconteo")) | L14: =COUNTIFS(CRUCE[PASILLO], Tiempos[[#This Row],[Pasillo]], CRUCE[STATUS2], "<>CUADRADO",CRUCE[STATUS2], "<>PENDIENTE") -> 0 | M14: =IF(Tiempos[[#This Row],[STATUS]]="cuadrado", "", IF(Tiempos[[#This Row],[DIFERENCIAS2]]=0, "Cuadrado", "Reconteo")) -> Cuadrado | N14: ecb5d4f6-08b3-43e8-8963-012deccc276b

Sheet Registros
A1: Fecha | B1: Operario | C1: Pasillo | D1: Ubicacion | E1: Codigo | F1: Descripcion | G1: UMA | H1: CamaPqt | I1: Niveles | J1: Saldo | K1: Total
A2: 28 septiembre 2026 13:00 | B2: RUTH | C2: Pasillo 1 | D2: PP-007-001-1 | E2: VACÍO | F2: UBICACIÓN VACÍA | G2: - | H2: 0 | I2: 0 | J2: 0 | K2: 0 | M2: NO DEBE DEJAR GUARDAR CUANDO ESORRO PASILLO
A3: 28 septiembre 2026 13:03 | B3: RUTH | C3: Pasillo 1 | D3: AP-01-005-1 | E3: 8325056 | F3: INSEC.CASA&JARDIN SAPOLIO 2A 360ML 12UND | G3: CJA | H3: 26 | I3: 0 | J3: 5 | K3: 5

Sheet CRUCE
H1: CONTEO 1 | N1: CONTEO 2
A2: PASILLO | B2: Ubicacion | C2: SKU | D2: EAN | E2: DESCRIPCION | F2: BULTOS | G2: UMA | H2: CODIGO | I2: TOTAL | J2: UMA2 | K2: Diferencia | L2: STATUS | M2: RECONTEO | N2: CODIGO2 | O2: TOTAL2 | P2: DIFERENCIA2 | Q2: STATUS2 | R2: C | S2: __PowerAppsId__
A3: PASILLO 1 | B3: AP-01-005-1 | C3: 8325056 | D3: 37751851006645 | E3: INSEC.CASA&JARDIN SAPOLIO 2A 360ML 12UND | F3: 5 | G3: CJA | H3: =_xlfn.XLOOKUP(CRUCE[[#This Row],[Ubicacion]],Registros[Ubicacion],Registros[Codigo], "") -> 8325056 | I3: =_xlfn.XLOOKUP(CRUCE[[#This Row],[Ubicacion]],Registros[Ubicacion],Registros[Total], "") -> 5 | J3: =_xlfn.XLOOKUP(CRUCE[[#This Row],[Ubicacion]],Registros[Ubicacion],Registros[UMA], "") -> CJA | K3: =IF(CRUCE[[#This Row],[TOTAL]]="","",CRUCE[[#This Row],[TOTAL]]-CRUCE[[#This Row],[BULTOS]]) -> 0 | L3: =IF(CRUCE[[#This Row],[TOTAL]]="", "PENDIENTE", IF(CRUCE[[#This Row],[Diferencia]]=0, "CUADRADO", IF(CRUCE[[#This Row],[Diferencia]]>0, "SOBRANTE", "FALTANTE"))) -> CUADRADO | M3: =IF(CRUCE[[#This Row],[Diferencia]]="","",IF(CRUCE[[#This Row],[Diferencia]]=0,"OK","RECONTEO")) -> OK | N3: =_xlfn.XLOOKUP(CRUCE[[#This Row],[Ubicacion]],Registros[Ubicacion],Registros[Codigo], "") -> 8325056 | Q3: =IF(CRUCE[[#This Row],[TOTAL2]]="", "PENDIENTE", IF(CRUCE[[#This Row],[DIFERENCIA2]]=0, "CUADRADO", IF(CRUCE[[#This Row],[DIFERENCIA2]]>0, "SOBRANTE", "FALTANTE"))) -> PENDIENTE | S3: e56a3784-2ab1-4e9f-9639-646dacf26db3
A4: PASILLO 1 | B4: AP-01-006-1 | C4: 8325096 | D4: 37751851006652 | E4: INSEC.MATAPOLILLAS SAPOLIO 2A 360ML 12UN | F4: 9 | G4: CJA | H4: =_xlfn.XLOOKUP(CRUCE[[#This Row],[Ubicacion]],Registros[Ubicacion],Registros[Codigo], "") | I4: =_xlfn.XLOOKUP(CRUCE[[#This Row],[Ubicacion]],Registros[Ubicacion],Registros[Total], "") | J4: =_xlfn.XLOOKUP(CRUCE[[#This Row],[Ubicacion]],Registros[Ubicacion],Registros[UMA], "") | K4: =IF(CRUCE[[#This Row],[TOTAL]]="","",CRUCE[[#This Row],[TOTAL]]-CRUCE[[#This Row],[BULTOS]]) | L4: =IF(CRUCE[[#This Row],[TOTAL]]="", "PENDIENTE", IF(CRUCE[[#This Row],[Diferencia]]=0, "CUADRADO", IF(CRUCE[[#This Row],[Diferencia]]>0, "SOBRANTE", "FALTANTE"))) -> PENDIENTE | M4: =IF(CRUCE[[#This Row],[Diferencia]]="","",IF(CRUCE[[#This Row],[Diferencia]]=0,"OK","RECONTEO")) | N4: =_xlfn.XLOOKUP(CRUCE[[#This Row],[Ubicacion]],Registros[Ubicacion],Registros[Codigo], "") | Q4: =IF(CRUCE[[#This Row],[TOTAL2]]="", "PENDIENTE", IF(CRUCE[[#This Row],[DIFERENCIA2]]=0, "CUADRADO", IF(CRUCE[[#This Row],[DIFERENCIA2]]>0, "SOBRANTE", "FALTANTE"))) -> PENDIENTE | R4: --- | S4: 86523e1f-34b1-46c1-8076-e7a5bc59b858
A5: PASILLO 1 | B5: AP-01-007-1 | C5: 8315030 | D5: 27751851006129 | E5: LIMPIAHORNOS SAPOLIO 360ML 12UND | F5: 39 | G5: CJA | H5: =_xlfn.XLOOKUP(CRUCE[[#This Row],[Ubicacion]],Registros[Ubicacion],Registros[Codigo], "") | I5: =_xlfn.XLOOKUP(CRUCE[[#This Row],[Ubicacion]],Registros[Ubicacion],Registros[Total], "") | J5: =_xlfn.XLOOKUP(CRUCE[[#This Row],[Ubicacion]],Registros[Ubicacion],Registros[UMA], "") | K5: =IF(CRUCE[[#This Row],[TOTAL]]="","",CRUCE[[#This Row],[TOTAL]]-CRUCE[[#This Row],[BULTOS]]) | L5: =IF(CRUCE[[#This Row],[TOTAL]]="", "PENDIENTE", IF(CRUCE[[#This Row],[Diferencia]]=0, "CUADRADO", IF(CRUCE[[#This Row],[Diferencia]]>0, "SOBRANTE", "FALTANTE"))) -> PENDIENTE | M5: =IF(CRUCE[[#This Row],[Diferencia]]="","",IF(CRUCE[[#This Row],[Diferencia]]=0,"OK","RECONTEO")) | N5: =_xlfn.XLOOKUP(CRUCE[[#This Row],[Ubicacion]],Registros[Ubicacion],Registros[Codigo], "") | Q5: =IF(CRUCE[[#This Row],[TOTAL2]]="", "PENDIENTE", IF(CRUCE[[#This Row],[DIFERENCIA2]]=0, "CUADRADO", IF(CRUCE[[#This Row],[DIFERENCIA2]]>0, "SOBRANTE", "FALTANTE"))) -> PENDIENTE | R5: --- | S5: 7e7c8b47-a04c-442e-b2a8-e805b786effc
A6: PASILLO 1 | B6: AP-01-008-1 | C6: 8315000 | D6: 17751851007556 | E6: LUSTRAMUEBLE LAVANDA PREMIO 360ML 12UND | F6: 15 | G6: CJA | H6: =_xlfn.XLOOKUP(CRUCE[[#This Row],[Ubicacion]],Registros[Ubicacion],Registros[Codigo], "") | I6: =_xlfn.XLOOKUP(CRUCE[[#This Row],[Ubicacion]],Registros[Ubicacion],Registros[Total], "") | J6: =_xlfn.XLOOKUP(CRUCE[[#This Row],[Ubicacion]],Registros[Ubicacion],Registros[UMA], "") | K6: =IF(CRUCE[[#This Row],[TOTAL]]="","",CRUCE[[#This Row],[TOTAL]]-CRUCE[[#This Row],[BULTOS]]) | L6: =IF(CRUCE[[#This Row],[TOTAL]]="", "PENDIENTE", IF(CRUCE[[#This Row],[Diferencia]]=0, "CUADRADO", IF(CRUCE[[#This Row],[Diferencia]]>0, "SOBRANTE", "FALTANTE"))) -> PENDIENTE | M6: =IF(CRUCE[[#This Row],[Diferencia]]="","",IF(CRUCE[[#This Row],[Diferencia]]=0,"OK","RECONTEO")) | N6: =_xlfn.XLOOKUP(CRUCE[[#This Row],[Ubicacion]],Registros[Ubicacion],Registros[Codigo], "") | Q6: =IF(CRUCE[[#This Row],[TOTAL2]]="", "PENDIENTE", IF(CRUCE[[#This Row],[DIFERENCIA2]]=0, "CUADRADO", IF(CRUCE[[#This Row],[DIFERENCIA2]]>0, "SOBRANTE", "FALTANTE"))) -> PENDIENTE | R6: --- | S6: a48087b5-f38f-420b-a0b4-24fb19d277bf
A7: PASILLO 1 | B7: AP-01-009-1 | C7: 8315001 | D7: 17751851007563 | E7: LUSTRAMUEBLE LIMON PREMIO 360ML 12UND | F7: 57 | G7: CJA | H7: =_xlfn.XLOOKUP(CRUCE[[#This Row],[Ubicacion]],Registros[Ubicacion],Registros[Codigo], "") | I7: =_xlfn.XLOOKUP(CRUCE[[#This Row],[Ubicacion]],Registros[Ubicacion],Registros[Total], "") | J7: =_xlfn.XLOOKUP(CRUCE[[#This Row],[Ubicacion]],Registros[Ubicacion],Registros[UMA], "") | K7: =IF(CRUCE[[#This Row],[TOTAL]]="","",CRUCE[[#This Row],[TOTAL]]-CRUCE[[#This Row],[BULTOS]]) | L7: =IF(CRUCE[[#This Row],[TOTAL]]="", "PENDIENTE", IF(CRUCE[[#This Row],[Diferencia]]=0, "CUADRADO", IF(CRUCE[[#This Row],[Diferencia]]>0, "SOBRANTE", "FALTANTE"))) -> PENDIENTE | M7: =IF(CRUCE[[#This Row],[Diferencia]]="","",IF(CRUCE[[#This Row],[Diferencia]]=0,"OK","RECONTEO")) | N7: =_xlfn.XLOOKUP(CRUCE[[#This Row],[Ubicacion]],Registros[Ubicacion],Registros[Codigo], "") | Q7: =IF(CRUCE[[#This Row],[TOTAL2]]="", "PENDIENTE", IF(CRUCE[[#This Row],[DIFERENCIA2]]=0, "CUADRADO", IF(CRUCE[[#This Row],[DIFERENCIA2]]>0, "SOBRANTE", "FALTANTE"))) -> PENDIENTE | R7: --- | S7: 3c749e0a-9c53-4dfe-8f70-d6d550127d39
A8: PASILLO 1 | B8: AP-01-010-1 | C8: 8325116 | D8: 47751851011196 | E8: INSEC. MATA ACAROS SAPOLIO RE 360ML 12UN | F8: 76 | G8: CJA | H8: =_xlfn.XLOOKUP(CRUCE[[#This Row],[Ubicacion]],Registros[Ubicacion],Registros[Codigo], "") | I8: =_xlfn.XLOOKUP(CRUCE[[#This Row],[Ubicacion]],Registros[Ubicacion],Registros[Total], "") | J8: =_xlfn.XLOOKUP(CRUCE[[#This Row],[Ubicacion]],Registros[Ubicacion],Registros[UMA], "") | K8: =IF(CRUCE[[#This Row],[TOTAL]]="","",CRUCE[[#This Row],[TOTAL]]-CRUCE[[#This Row],[BULTOS]]) | L8: =IF(CRUCE[[#This Row],[TOTAL]]="", "PENDIENTE", IF(CRUCE[[#This Row],[Diferencia]]=0, "CUADRADO", IF(CRUCE[[#This Row],[Diferencia]]>0, "SOBRANTE", "FALTANTE"))) -> PENDIENTE | M8: =IF(CRUCE[[#This Row],[Diferencia]]="","",IF(CRUCE[[#This Row],[Diferencia]]=0,"OK","RECONTEO")) | N8: =_xlfn.XLOOKUP(CRUCE[[#This Row],[Ubicacion]],Registros[Ubicacion],Registros[Codigo], "") | Q8: =IF(CRUCE[[#This Row],[TOTAL2]]="", "PENDIENTE", IF(CRUCE[[#This Row],[DIFERENCIA2]]=0, "CUADRADO", IF(CRUCE[[#This Row],[DIFERENCIA2]]>0, "SOBRANTE", "FALTANTE"))) -> PENDIENTE | R8: --- | S8: d37699d5-6fdc-40d5-89df-fa6a11f8b4eb
A9: PASILLO 1 | B9: AP-01-011-1 | C9: 8325118 | D9: 47751851006666 | E9: INSEC MATA TERMITAS SAPOLIO RE 360ML12UN | F9: 76 | G9: CJA | H9: =_xlfn.XLOOKUP(CRUCE[[#This Row],[Ubicacion]],Registros[Ubicacion],Registros[Codigo], "") | I9: =_xlfn.XLOOKUP(CRUCE[[#This Row],[Ubicacion]],Registros[Ubicacion],Registros[Total], "") | J9: =_xlfn.XLOOKUP(CRUCE[[#This Row],[Ubicacion]],Registros[Ubicacion],Registros[UMA], "") | K9: =IF(CRUCE[[#This Row],[TOTAL]]="","",CRUCE[[#This Row],[TOTAL]]-CRUCE[[#This Row],[BULTOS]]) | L9: =IF(CRUCE[[#This Row],[TOTAL]]="", "PENDIENTE", IF(CRUCE[[#This Row],[Diferencia]]=0, "CUADRADO", IF(CRUCE[[#This Row],[Diferencia]]>0, "SOBRANTE", "FALTANTE"))) -> PENDIENTE | M9: =IF(CRUCE[[#This Row],[Diferencia]]="","",IF(CRUCE[[#This Row],[Diferencia]]=0,"OK","RECONTEO")) | N9: =_xlfn.XLOOKUP(CRUCE[[#This Row],[Ubicacion]],Registros[Ubicacion],Registros[Codigo], "") | Q9: =IF(CRUCE[[#This Row],[TOTAL2]]="", "PENDIENTE", IF(CRUCE[[#This Row],[DIFERENCIA2]]=0, "CUADRADO", IF(CRUCE[[#This Row],[DIFERENCIA2]]>0, "SOBRANTE", "FALTANTE"))) -> PENDIENTE | R9: --- | S9: c6b4ea8c-82c2-4613-8f9e-b110c4cc6801
A10: PASILLO 1 | B10: AP-01-012-1 | C10: 8309033 | D10: 17751851019634 | E10: PERFU.RPTO V/FRANCESA SAPOLIO 240ML 12UN | F10: 50 | G10: CJA | H10: =_xlfn.XLOOKUP(CRUCE[[#This Row],[Ubicacion]],Registros[Ubicacion],Registros[Codigo], "") | I10: =_xlfn.XLOOKUP(CRUCE[[#This Row],[Ubicacion]],Registros[Ubicacion],Registros[Total], "") | J10: =_xlfn.XLOOKUP(CRUCE[[#This Row],[Ubicacion]],Registros[Ubicacion],Registros[UMA], "") | K10: =IF(CRUCE[[#This Row],[TOTAL]]="","",CRUCE[[#This Row],[TOTAL]]-CRUCE[[#This Row],[BULTOS]]) | L10: =IF(CRUCE[[#This Row],[TOTAL]]="", "PENDIENTE", IF(CRUCE[[#This Row],[Diferencia]]=0, "CUADRADO", IF(CRUCE[[#This Row],[Diferencia]]>0, "SOBRANTE", "FALTANTE"))) -> PENDIENTE | M10: =IF(CRUCE[[#This Row],[Diferencia]]="","",IF(CRUCE[[#This Row],[Diferencia]]=0,"OK","RECONTEO")) | N10: =_xlfn.XLOOKUP(CRUCE[[#This Row],[Ubicacion]],Registros[Ubicacion],Registros[Codigo], "") | Q10: =IF(CRUCE[[#This Row],[TOTAL2]]="", "PENDIENTE", IF(CRUCE[[#This Row],[DIFERENCIA2]]=0, "CUADRADO", IF(CRUCE[[#This Row],[DIFERENCIA2]]>0, "SOBRANTE", "FALTANTE"))) -> PENDIENTE | R10: --- | S10: dd1dbcb3-e43e-4526-b8e7-94dcd1ed66aa
A11: PASILLO 1 | B11: AP-01-013-1 | C11: 8325095 | D11: 37751851006638 | E11: INSEC.MATAPULGAS SAPOLIO 2A 360ML 12UND | F11: 44 | G11: CJA | H11: =_xlfn.XLOOKUP(CRUCE[[#This Row],[Ubicacion]],Registros[Ubicacion],Registros[Codigo], "") | I11: =_xlfn.XLOOKUP(CRUCE[[#This Row],[Ubicacion]],Registros[Ubicacion],Registros[Total], "") | J11: =_xlfn.XLOOKUP(CRUCE[[#This Row],[Ubicacion]],Registros[Ubicacion],Registros[UMA], "") | K11: =IF(CRUCE[[#This Row],[TOTAL]]="","",CRUCE[[#This Row],[TOTAL]]-CRUCE[[#This Row],[BULTOS]]) | L11: =IF(CRUCE[[#This Row],[TOTAL]]="", "PENDIENTE", IF(CRUCE[[#This Row],[Diferencia]]=0, "CUADRADO", IF(CRUCE[[#This Row],[Diferencia]]>0, "SOBRANTE", "FALTANTE"))) -> PENDIENTE | M11: =IF(CRUCE[[#This Row],[Diferencia]]="","",IF(CRUCE[[#This Row],[Diferencia]]=0,"OK","RECONTEO")) | N11: =_xlfn.XLOOKUP(CRUCE[[#This Row],[Ubicacion]],Registros[Ubicacion],Registros[Codigo], "") | Q11: =IF(CRUCE[[#This Row],[TOTAL2]]="", "PENDIENTE", IF(CRUCE[[#This Row],[DIFERENCIA2]]=0, "CUADRADO", IF(CRUCE[[#This Row],[DIFERENCIA2]]>0, "SOBRANTE", "FALTANTE"))) -> PENDIENTE | R11: --- | S11: ff0849b8-9b24-4a7f-b6cf-7baa42fcecad
A12: PASILLO 1 | B12: AP-01-014-1 | C12: 8325093 | D12: 27751851020156 | E12: INSEC.MATATODO SAPOLIO 2A 360ML 12UND | F12: 19 | G12: CJA | H12: =_xlfn.XLOOKUP(CRUCE[[#This Row],[Ubicacion]],Registros[Ubicacion],Registros[Codigo], "") | I12: =_xlfn.XLOOKUP(CRUCE[[#This Row],[Ubicacion]],Registros[Ubicacion],Registros[Total], "") | J12: =_xlfn.XLOOKUP(CRUCE[[#This Row],[Ubicacion]],Registros[Ubicacion],Registros[UMA], "") | K12: =IF(CRUCE[[#This Row],[TOTAL]]="","",CRUCE[[#This Row],[TOTAL]]-CRUCE[[#This Row],[BULTOS]]) | L12: =IF(CRUCE[[#This Row],[TOTAL]]="", "PENDIENTE", IF(CRUCE[[#This Row],[Diferencia]]=0, "CUADRADO", IF(CRUCE[[#This Row],[Diferencia]]>0, "SOBRANTE", "FALTANTE"))) -> PENDIENTE | M12: =IF(CRUCE[[#This Row],[Diferencia]]="","",IF(CRUCE[[#This Row],[Diferencia]]=0,"OK","RECONTEO")) | N12: =_xlfn.XLOOKUP(CRUCE[[#This Row],[Ubicacion]],Registros[Ubicacion],Registros[Codigo], "") | Q12: =IF(CRUCE[[#This Row],[TOTAL2]]="", "PENDIENTE", IF(CRUCE[[#This Row],[DIFERENCIA2]]=0, "CUADRADO", IF(CRUCE[[#This Row],[DIFERENCIA2]]>0, "SOBRANTE", "FALTANTE"))) -> PENDIENTE | R12: --- | S12: e797b998-c5c4-40ab-8ddd-ef25fdf495fb
A13: PASILLO 1 | B13: AP-01-015-1 | H13: =_xlfn.XLOOKUP(CRUCE[[#This Row],[Ubicacion]],Registros[Ubicacion],Registros[Codigo], "") | I13: =_xlfn.XLOOKUP(CRUCE[[#This Row],[Ubicacion]],Registros[Ubicacion],Registros[Total], "") | J13: =_xlfn.XLOOKUP(CRUCE[[#This Row],[Ubicacion]],Registros[Ubicacion],Registros[UMA], "") | K13: =IF(CRUCE[[#This Row],[TOTAL]]="","",CRUCE[[#This Row],[TOTAL]]-CRUCE[[#This Row],[BULTOS]]) | L13: =IF(CRUCE[[#This Row],[TOTAL]]="", "PENDIENTE", IF(CRUCE[[#This Row],[Diferencia]]=0, "CUADRADO", IF(CRUCE[[#This Row],[Diferencia]]>0, "SOBRANTE", "FALTANTE"))) -> PENDIENTE | M13: =IF(CRUCE[[#This Row],[Diferencia]]="","",IF(CRUCE[[#This Row],[Diferencia]]=0,"OK","RECONTEO")) | N13: =_xlfn.XLOOKUP(CRUCE[[#This Row],[Ubicacion]],Registros[Ubicacion],Registros[Codigo], "") | Q13: =IF(CRUCE[[#This Row],[TOTAL2]]="", "PENDIENTE", IF(CRUCE[[#This Row],[DIFERENCIA2]]=0, "CUADRADO", IF(CRUCE[[#This Row],[DIFERENCIA2]]>0, "SOBRANTE", "FALTANTE"))) -> PENDIENTE | R13: --- | S13: 264348ae-3284-4b49-8ebe-1efa0358014b
A14: PASILLO 1 | B14: AP-01-016-1 | C14: 8325084 | D14: 67751851006622 | E14: INSE. SAP. MAT MOS Y ZANC BO 360ML 12UND | F14: 60 | G14: CJA | H14: =_xlfn.XLOOKUP(CRUCE[[#This Row],[Ubicacion]],Registros[Ubicacion],Registros[Codigo], "") | I14: =_xlfn.XLOOKUP(CRUCE[[#This Row],[Ubicacion]],Registros[Ubicacion],Registros[Total], "") | J14: =_xlfn.XLOOKUP(CRUCE[[#This Row],[Ubicacion]],Registros[Ubicacion],Registros[UMA], "") | K14: =IF(CRUCE[[#This Row],[TOTAL]]="","",CRUCE[[#This Row],[TOTAL]]-CRUCE[[#This Row],[BULTOS]]) | L14: =IF(CRUCE[[#This Row],[TOTAL]]="", "PENDIENTE", IF(CRUCE[[#This Row],[Diferencia]]=0, "CUADRADO", IF(CRUCE[[#This Row],[Diferencia]]>0, "SOBRANTE", "FALTANTE"))) -> PENDIENTE | M14: =IF(CRUCE[[#This Row],[Diferencia]]="","",IF(CRUCE[[#This Row],[Diferencia]]=0,"OK","RECONTEO")) | N14: =_xlfn.XLOOKUP(CRUCE[[#This Row],[Ubicacion]],Registros[Ubicacion],Registros[Codigo], "") | Q14: =IF(CRUCE[[#This Row],[TOTAL2]]="", "PENDIENTE", IF(CRUCE[[#This Row],[DIFERENCIA2]]=0, "CUADRADO", IF(CRUCE[[#This Row],[DIFERENCIA2]]>0, "SOBRANTE", "FALTANTE"))) -> PENDIENTE | R14: --- | S14: 19493bac-2d77-4dc7-b666-d88345e9ad66
A15: PASILLO 1 | B15: AP-01-017-1 | C15: 8325115 | D15: 37751851005464 | E15: INSECT. MATA TODO CONTROL RE 360ML12UN | F15: 87 | G15: CJA | H15: =_xlfn.XLOOKUP(CRUCE[[#This Row],[Ubicacion]],Registros[Ubicacion],Registros[Codigo], "") | I15: =_xlfn.XLOOKUP(CRUCE[[#This Row],[Ubicacion]],Registros[Ubicacion],Registros[Total], "") | J15: =_xlfn.XLOOKUP(CRUCE[[#This Row],[Ubicacion]],Registros[Ubicacion],Registros[UMA], "") | K15: =IF(CRUCE[[#This Row],[TOTAL]]="","",CRUCE[[#This Row],[TOTAL]]-CRUCE[[#This Row],[BULTOS]]) | L15: =IF(CRUCE[[#This Row],[TOTAL]]="", "PENDIENTE", IF(CRUCE[[#This Row],[Diferencia]]=0, "CUADRADO", IF(CRUCE[[#This Row],[Diferencia]]>0, "SOBRANTE", "FALTANTE"))) -> PENDIENTE | M15: =IF(CRUCE[[#This Row],[Diferencia]]="","",IF(CRUCE[[#This Row],[Diferencia]]=0,"OK","RECONTEO")) | N15: =_xlfn.XLOOKUP(CRUCE[[#This Row],[Ubicacion]],Registros[Ubicacion],Registros[Codigo], "") | Q15: =IF(CRUCE[[#This Row],[TOTAL2]]="", "PENDIENTE", IF(CRUCE[[#This Row],[DIFERENCIA2]]=0, "CUADRADO", IF(CRUCE[[#This Row],[DIFERENCIA2]]>0, "SOBRANTE", "FALTANTE"))) -> PENDIENTE | R15: --- | S15: 23bc5b3d-e197-4cca-bef2-677b468375a6
A16: PASILLO 1 | B16: AP-01-018-1 | C16: 8309028 | D16: 27751851006419 | E16: PERFUMATIC RPTO POTPOUR SAP.240ML 12UN | F16: 43 | G16: CJA | H16: =_xlfn.XLOOKUP(CRUCE[[#This Row],[Ubicacion]],Registros[Ubicacion],Registros[Codigo], "") | I16: =_xlfn.XLOOKUP(CRUCE[[#This Row],[Ubicacion]],Registros[Ubicacion],Registros[Total], "") | J16: =_xlfn.XLOOKUP(CRUCE[[#This Row],[Ubicacion]],Registros[Ubicacion],Registros[UMA], "") | K16: =IF(CRUCE[[#This Row],[TOTAL]]="","",CRUCE[[#This Row],[TOTAL]]-CRUCE[[#This Row],[BULTOS]]) | L16: =IF(CRUCE[[#This Row],[TOTAL]]="", "PENDIENTE", IF(CRUCE[[#This Row],[Diferencia]]=0, "CUADRADO", IF(CRUCE[[#This Row],[Diferencia]]>0, "SOBRANTE", "FALTANTE"))) -> PENDIENTE | M16: =IF(CRUCE[[#This Row],[Diferencia]]="","",IF(CRUCE[[#This Row],[Diferencia]]=0,"OK","RECONTEO")) | N16: =_xlfn.XLOOKUP(CRUCE[[#This Row],[Ubicacion]],Registros[Ubicacion],Registros[Codigo], "") | Q16: =IF(CRUCE[[#This Row],[TOTAL2]]="", "PENDIENTE", IF(CRUCE[[#This Row],[DIFERENCIA2]]=0, "CUADRADO", IF(CRUCE[[#This Row],[DIFERENCIA2]]>0, "SOBRANTE", "FALTANTE"))) -> PENDIENTE | R16: --- | S16: 033e9500-6cd1-4591-a7c2-53327cbcf6f8
A17: PASILLO 1 | B17: AP-01-019-1 | C17: 8309027 | D17: 27751851006402 | E17: PERFUMATIC RPTO LAVANDA SAP.240ML 12UN | F17: 45 | G17: CJA | H17: =_xlfn.XLOOKUP(CRUCE[[#This Row],[Ubicacion]],Registros[Ubicacion],Registros[Codigo], "") | I17: =_xlfn.XLOOKUP(CRUCE[[#This Row],[Ubicacion]],Registros[Ubicacion],Registros[Total], "") | J17: =_xlfn.XLOOKUP(CRUCE[[#This Row],[Ubicacion]],Registros[Ubicacion],Registros[UMA], "") | K17: =IF(CRUCE[[#This Row],[TOTAL]]="","",CRUCE[[#This Row],[TOTAL]]-CRUCE[[#This Row],[BULTOS]]) | L17: =IF(CRUCE[[#This Row],[TOTAL]]="", "PENDIENTE", IF(CRUCE[[#This Row],[Diferencia]]=0, "CUADRADO", IF(CRUCE[[#This Row],[Diferencia]]>0, "SOBRANTE", "FALTANTE"))) -> PENDIENTE | M17: =IF(CRUCE[[#This Row],[Diferencia]]="","",IF(CRUCE[[#This Row],[Diferencia]]=0,"OK","RECONTEO")) | N17: =_xlfn.XLOOKUP(CRUCE[[#This Row],[Ubicacion]],Registros[Ubicacion],Registros[Codigo], "") | Q17: =IF(CRUCE[[#This Row],[TOTAL2]]="", "PENDIENTE", IF(CRUCE[[#This Row],[DIFERENCIA2]]=0, "CUADRADO", IF(CRUCE[[#This Row],[DIFERENCIA2]]>0, "SOBRANTE", "FALTANTE"))) -> PENDIENTE | R17: --- | S17: c26e17aa-b3c8-46d8-aa40-9f4935d577e6
A18: PASILLO 1 | B18: AP-01-020-1 | C18: 8309194 | D18: 57751851006021 | E18: AMB. SAPOLIO ANTITABACO RW 360ML 12UND | F18: 17 | G18: CJA | H18: =_xlfn.XLOOKUP(CRUCE[[#This Row],[Ubicacion]],Registros[Ubicacion],Registros[Codigo], "") | I18: =_xlfn.XLOOKUP(CRUCE[[#This Row],[Ubicacion]],Registros[Ubicacion],Registros[Total], "") | J18: =_xlfn.XLOOKUP(CRUCE[[#This Row],[Ubicacion]],Registros[Ubicacion],Registros[UMA], "") | K18: =IF(CRUCE[[#This Row],[TOTAL]]="","",CRUCE[[#This Row],[TOTAL]]-CRUCE[[#This Row],[BULTOS]]) | L18: =IF(CRUCE[[#This Row],[TOTAL]]="", "PENDIENTE", IF(CRUCE[[#This Row],[Diferencia]]=0, "CUADRADO", IF(CRUCE[[#This Row],[Diferencia]]>0, "SOBRANTE", "FALTANTE"))) -> PENDIENTE | M18: =IF(CRUCE[[#This Row],[Diferencia]]="","",IF(CRUCE[[#This Row],[Diferencia]]=0,"OK","RECONTEO")) | N18: =_xlfn.XLOOKUP(CRUCE[[#This Row],[Ubicacion]],Registros[Ubicacion],Registros[Codigo], "") | Q18: =IF(CRUCE[[#This Row],[TOTAL2]]="", "PENDIENTE", IF(CRUCE[[#This Row],[DIFERENCIA2]]=0, "CUADRADO", IF(CRUCE[[#This Row],[DIFERENCIA2]]>0, "SOBRANTE", "FALTANTE"))) -> PENDIENTE | R18: --- | S18: 612e67f3-a58a-45ef-9d4d-294d3e27e6f9
A19: PASILLO 1 | B19: AP-01-021-1 | C19: 8309120 | D19: 37751851005990 | E19: AMBIENT.SAPOLIO POTPOURRI 360ML 12UND | F19: 9 | G19: CJA | H19: =_xlfn.XLOOKUP(CRUCE[[#This Row],[Ubicacion]],Registros[Ubicacion],Registros[Codigo], "") | I19: =_xlfn.XLOOKUP(CRUCE[[#This Row],[Ubicacion]],Registros[Ubicacion],Registros[Total], "") | J19: =_xlfn.XLOOKUP(CRUCE[[#This Row],[Ubicacion]],Registros[Ubicacion],Registros[UMA], "") | K19: =IF(CRUCE[[#This Row],[TOTAL]]="","",CRUCE[[#This Row],[TOTAL]]-CRUCE[[#This Row],[BULTOS]]) | L19: =IF(CRUCE[[#This Row],[TOTAL]]="", "PENDIENTE", IF(CRUCE[[#This Row],[Diferencia]]=0, "CUADRADO", IF(CRUCE[[#This Row],[Diferencia]]>0, "SOBRANTE", "FALTANTE"))) -> PENDIENTE | M19: =IF(CRUCE[[#This Row],[Diferencia]]="","",IF(CRUCE[[#This Row],[Diferencia]]=0,"OK","RECONTEO")) | N19: =_xlfn.XLOOKUP(CRUCE[[#This Row],[Ubicacion]],Registros[Ubicacion],Registros[Codigo], "") | Q19: =IF(CRUCE[[#This Row],[TOTAL2]]="", "PENDIENTE", IF(CRUCE[[#This Row],[DIFERENCIA2]]=0, "CUADRADO", IF(CRUCE[[#This Row],[DIFERENCIA2]]>0, "SOBRANTE", "FALTANTE"))) -> PENDIENTE | R19: --- | S19: c61f5665-5f4c-4cff-a8f4-907734c0bb99
A20: PASILLO 1 | B20: AP-01-022-1 | C20: 8309119 | D20: 37751851005983 | E20: AMBIENTADOR SAPOLIO LAVANDA 360ML 12UND | F20: 94 | G20: CJA | H20: =_xlfn.XLOOKUP(CRUCE[[#This Row],[Ubicacion]],Registros[Ubicacion],Registros[Codigo], "") | I20: =_xlfn.XLOOKUP(CRUCE[[#This Row],[Ubicacion]],Registros[Ubicacion],Registros[Total], "") | J20: =_xlfn.XLOOKUP(CRUCE[[#This Row],[Ubicacion]],Registros[Ubicacion],Registros[UMA], "") | K20: =IF(CRUCE[[#This Row],[TOTAL]]="","",CRUCE[[#This Row],[TOTAL]]-CRUCE[[#This Row],[BULTOS]]) | L20: =IF(CRUCE[[#This Row],[TOTAL]]="", "PENDIENTE", IF(CRUCE[[#This Row],[Diferencia]]=0, "CUADRADO", IF(CRUCE[[#This Row],[Diferencia]]>0, "SOBRANTE", "FALTANTE"))) -> PENDIENTE | M20: =IF(CRUCE[[#This Row],[Diferencia]]="","",IF(CRUCE[[#This Row],[Diferencia]]=0,"OK","RECONTEO")) | N20: =_xlfn.XLOOKUP(CRUCE[[#This Row],[Ubicacion]],Registros[Ubicacion],Registros[Codigo], "") | Q20: =IF(CRUCE[[#This Row],[TOTAL2]]="", "PENDIENTE", IF(CRUCE[[#This Row],[DIFERENCIA2]]=0, "CUADRADO", IF(CRUCE[[#This Row],[DIFERENCIA2]]>0, "SOBRANTE", "FALTANTE"))) -> PENDIENTE | R20: --- | S20: 28d51b8f-66c4-4de1-a8d4-9621b6f57d13
A21: PASILLO 1 | B21: AP-01-023-1 | C21: 8309126 | D21: 37751851006089 | E21: AMBIENT.SAPOL.ARRULLO DE BEBE 360ML 12UN | F21: 22 | G21: CJA | H21: =_xlfn.XLOOKUP(CRUCE[[#This Row],[Ubicacion]],Registros[Ubicacion],Registros[Codigo], "") | I21: =_xlfn.XLOOKUP(CRUCE[[#This Row],[Ubicacion]],Registros[Ubicacion],Registros[Total], "") | J21: =_xlfn.XLOOKUP(CRUCE[[#This Row],[Ubicacion]],Registros[Ubicacion],Registros[UMA], "") | K21: =IF(CRUCE[[#This Row],[TOTAL]]="","",CRUCE[[#This Row],[TOTAL]]-CRUCE[[#This Row],[BULTOS]]) | L21: =IF(CRUCE[[#This Row],[TOTAL]]="", "PENDIENTE", IF(CRUCE[[#This Row],[Diferencia]]=0, "CUADRADO", IF(CRUCE[[#This Row],[Diferencia]]>0, "SOBRANTE", "FALTANTE"))) -> PENDIENTE | M21: =IF(CRUCE[[#This Row],[Diferencia]]="","",IF(CRUCE[[#This Row],[Diferencia]]=0,"OK","RECONTEO")) | N21: =_xlfn.XLOOKUP(CRUCE[[#This Row],[Ubicacion]],Registros[Ubicacion],Registros[Codigo], "") | Q21: =IF(CRUCE[[#This Row],[TOTAL2]]="", "PENDIENTE", IF(CRUCE[[#This Row],[DIFERENCIA2]]=0, "CUADRADO", IF(CRUCE[[#This Row],[DIFERENCIA2]]>0, "SOBRANTE", "FALTANTE"))) -> PENDIENTE | R21: --- | S21: 04b1e0df-5f4a-4522-b50a-ddde2afa36d2
A22: PASILLO 1 | B22: AP-01-024-1 | C22: 8309121 | D22: 37751851006003 | E22: AMBIENT.SAPOLIO JARDIN ROSAS 360ML 12UN | F22: 14 | G22: CJA | H22: =_xlfn.XLOOKUP(CRUCE[[#This Row],[Ubicacion]],Registros[Ubicacion],Registros[Codigo], "") | I22: =_xlfn.XLOOKUP(CRUCE[[#This Row],[Ubicacion]],Registros[Ubicacion],Registros[Total], "") | J22: =_xlfn.XLOOKUP(CRUCE[[#This Row],[Ubicacion]],Registros[Ubicacion],Registros[UMA], "") | K22: =IF(CRUCE[[#This Row],[TOTAL]]="","",CRUCE[[#This Row],[TOTAL]]-CRUCE[[#This Row],[BULTOS]]) | L22: =IF(CRUCE[[#This Row],[TOTAL]]="", "PENDIENTE", IF(CRUCE[[#This Row],[Diferencia]]=0, "CUADRADO", IF(CRUCE[[#This Row],[Diferencia]]>0, "SOBRANTE", "FALTANTE"))) -> PENDIENTE | M22: =IF(CRUCE[[#This Row],[Diferencia]]="","",IF(CRUCE[[#This Row],[Diferencia]]=0,"OK","RECONTEO")) | N22: =_xlfn.XLOOKUP(CRUCE[[#This Row],[Ubicacion]],Registros[Ubicacion],Registros[Codigo], "") | Q22: =IF(CRUCE[[#This Row],[TOTAL2]]="", "PENDIENTE", IF(CRUCE[[#This Row],[DIFERENCIA2]]=0, "CUADRADO", IF(CRUCE[[#This Row],[DIFERENCIA2]]>0, "SOBRANTE", "FALTANTE"))) -> PENDIENTE | R22: --- | S22: 398dbbb4-8704-4e01-a0e3-31babc234b09
A23: PASILLO 1 | B23: AP-01-025-1 | C23: 8309131 | D23: 27750243066864 | E23: AMBIE.SAPOLIO COCO 360ML 12UND | F23: 19 | G23: CJA | H23: =_xlfn.XLOOKUP(CRUCE[[#This Row],[Ubicacion]],Registros[Ubicacion],Registros[Codigo], "") | I23: =_xlfn.XLOOKUP(CRUCE[[#This Row],[Ubicacion]],Registros[Ubicacion],Registros[Total], "") | J23: =_xlfn.XLOOKUP(CRUCE[[#This Row],[Ubicacion]],Registros[Ubicacion],Registros[UMA], "") | K23: =IF(CRUCE[[#This Row],[TOTAL]]="","",CRUCE[[#This Row],[TOTAL]]-CRUCE[[#This Row],[BULTOS]]) | L23: =IF(CRUCE[[#This Row],[TOTAL]]="", "PENDIENTE", IF(CRUCE[[#This Row],[Diferencia]]=0, "CUADRADO", IF(CRUCE[[#This Row],[Diferencia]]>0, "SOBRANTE", "FALTANTE"))) -> PENDIENTE | M23: =IF(CRUCE[[#This Row],[Diferencia]]="","",IF(CRUCE[[#This Row],[Diferencia]]=0,"OK","RECONTEO")) | N23: =_xlfn.XLOOKUP(CRUCE[[#This Row],[Ubicacion]],Registros[Ubicacion],Registros[Codigo], "") | Q23: =IF(CRUCE[[#This Row],[TOTAL2]]="", "PENDIENTE", IF(CRUCE[[#This Row],[DIFERENCIA2]]=0, "CUADRADO", IF(CRUCE[[#This Row],[DIFERENCIA2]]>0, "SOBRANTE", "FALTANTE"))) -> PENDIENTE | R23: --- | S23: 6b12f48e-6928-4618-8275-3ba12c100eb5
A24: PASILLO 1 | B24: AP-01-026-1 | C24: 8309128 | D24: 27751851013264 | E24: AMBIENTADOR SAPOLIO VAINILLA 360ML 12UND | F24: 17 | G24: CJA | H24: =_xlfn.XLOOKUP(CRUCE[[#This Row],[Ubicacion]],Registros[Ubicacion],Registros[Codigo], "") | I24: =_xlfn.XLOOKUP(CRUCE[[#This Row],[Ubicacion]],Registros[Ubicacion],Registros[Total], "") | J24: =_xlfn.XLOOKUP(CRUCE[[#This Row],[Ubicacion]],Registros[Ubicacion],Registros[UMA], "") | K24: =IF(CRUCE[[#This Row],[TOTAL]]="","",CRUCE[[#This Row],[TOTAL]]-CRUCE[[#This Row],[BULTOS]]) | L24: =IF(CRUCE[[#This Row],[TOTAL]]="", "PENDIENTE", IF(CRUCE[[#This Row],[Diferencia]]=0, "CUADRADO", IF(CRUCE[[#This Row],[Diferencia]]>0, "SOBRANTE", "FALTANTE"))) -> PENDIENTE | M24: =IF(CRUCE[[#This Row],[Diferencia]]="","",IF(CRUCE[[#This Row],[Diferencia]]=0,"OK","RECONTEO")) | N24: =_xlfn.XLOOKUP(CRUCE[[#This Row],[Ubicacion]],Registros[Ubicacion],Registros[Codigo], "") | Q24: =IF(CRUCE[[#This Row],[TOTAL2]]="", "PENDIENTE", IF(CRUCE[[#This Row],[DIFERENCIA2]]=0, "CUADRADO", IF(CRUCE[[#This Row],[DIFERENCIA2]]>0, "SOBRANTE", "FALTANTE"))) -> PENDIENTE | R24: --- | S24: eb5f614e-340f-41cf-b876-c8a5e2ebed4c
A25: PASILLO 1 | B25: AP-01-027-1 | C25: 8325102 | D25: 47751851010281 | E25: INSECT. MATAARAÑAS SAPOL.2ARE 360ML 12UN | F25: 56 | G25: CJA | H25: =_xlfn.XLOOKUP(CRUCE[[#This Row],[Ubicacion]],Registros[Ubicacion],Registros[Codigo], "") | I25: =_xlfn.XLOOKUP(CRUCE[[#This Row],[Ubicacion]],Registros[Ubicacion],Registros[Total], "") | J25: =_xlfn.XLOOKUP(CRUCE[[#This Row],[Ubicacion]],Registros[Ubicacion],Registros[UMA], "") | K25: =IF(CRUCE[[#This Row],[TOTAL]]="","",CRUCE[[#This Row],[TOTAL]]-CRUCE[[#This Row],[BULTOS]]) | L25: =IF(CRUCE[[#This Row],[TOTAL]]="", "PENDIENTE", IF(CRUCE[[#This Row],[Diferencia]]=0, "CUADRADO", IF(CRUCE[[#This Row],[Diferencia]]>0, "SOBRANTE", "FALTANTE"))) -> PENDIENTE | M25: =IF(CRUCE[[#This Row],[Diferencia]]="","",IF(CRUCE[[#This Row],[Diferencia]]=0,"OK","RECONTEO")) | N25: =_xlfn.XLOOKUP(CRUCE[[#This Row],[Ubicacion]],Registros[Ubicacion],Registros[Codigo], "") | Q25: =IF(CRUCE[[#This Row],[TOTAL2]]="", "PENDIENTE", IF(CRUCE[[#This Row],[DIFERENCIA2]]=0, "CUADRADO", IF(CRUCE[[#This Row],[DIFERENCIA2]]>0, "SOBRANTE", "FALTANTE"))) -> PENDIENTE | R25: --- | S25: 6ef1a0ad-872b-44bd-9077-eef059e1ec94
... A28: PASILLO 1 | B28: AP-01-030-1 | C28: 8325114 | D28: 77751851006612 | E28: INSECT MATA CUCARACHAS SAP.RE 360ML 12UN | F28: 99 | G28: CJA | H28: =_xlfn.XLOOKUP(CRUCE[[#This Row],[Ubicacion]],Registros[Ubicacion],Registros[Codigo], "") | I28: =_xlfn.XLOOKUP(CRUCE[[#This Row],[Ubicacion]],Registros[Ubicacion],Registros[Total], "") | J28: =_xlfn.XLOOKUP(CRUCE[[#This Row],[Ubicacion]],Registros[Ubicacion],Registros[UMA], "") | K28: =IF(CRUCE[[#This Row],[TOTAL]]="","",CRUCE[[#This Row],[TOTAL]]-CRUCE[[#This Row],[BULTOS]]) | L28: =IF(CRUCE[[#This Row],[TOTAL]]="", "PENDIENTE", IF(CRUCE[[#This Row],[Diferencia]]=0, "CUADRADO", IF(CRUCE[[#This Row],[Diferencia]]>0, "SOBRANTE", "FALTANTE"))) -> PENDIENTE | M28: =IF(CRUCE[[#This Row],[Diferencia]]="","",IF(CRUCE[[#This Row],[Diferencia]]=0,"OK","RECONTEO")) | N28: =_xlfn.XLOOKUP(CRUCE[[#This Row],[Ubicacion]],Registros[Ubicacion],Registros[Codigo], "") | Q28: =IF(CRUCE[[#This Row],[TOTAL2]]="", "PENDIENTE", IF(CRUCE[[#This Row],[DIFERENCIA2]]=0, "CUADRADO", IF(CRUCE[[#This Row],[DIFERENCIA2]]>0, "SOBRANTE", "FALTANTE"))) -> PENDIENTE | R28: --- | S28: ce8f10f8-4bc9-4319-a847-35e924a6d66b
A29: PASILLO 1 | B29: AP-01-031-1 | H29: =_xlfn.XLOOKUP(CRUCE[[#This Row],[Ubicacion]],Registros[Ubicacion],Registros[Codigo], "") | I29: =_xlfn.XLOOKUP(CRUCE[[#This Row],[Ubicacion]],Registros[Ubicacion],Registros[Total], "") | J29: =_xlfn.XLOOKUP(CRUCE[[#This Row],[Ubicacion]],Registros[Ubicacion],Registros[UMA], "") | K29: =IF(CRUCE[[#This Row],[TOTAL]]="","",CRUCE[[#This Row],[TOTAL]]-CRUCE[[#This Row],[BULTOS]]) | L29: =IF(CRUCE[[#This Row],[TOTAL]]="", "PENDIENTE", IF(CRUCE[[#This Row],[Diferencia]]=0, "CUADRADO", IF(CRUCE[[#This Row],[Diferencia]]>0, "SOBRANTE", "FALTANTE"))) -> PENDIENTE | M29: =IF(CRUCE[[#This Row],[Diferencia]]="","",IF(CRUCE[[#This Row],[Diferencia]]=0,"OK","RECONTEO")) | N29: =_xlfn.XLOOKUP(CRUCE[[#This Row],[Ubicacion]],Registros[Ubicacion],Registros[Codigo], "") | Q29: =IF(CRUCE[[#This Row],[TOTAL2]]="", "PENDIENTE", IF(CRUCE[[#This Row],[DIFERENCIA2]]=0, "CUADRADO", IF(CRUCE[[#This Row],[DIFERENCIA2]]>0, "SOBRANTE", "FALTANTE"))) -> PENDIENTE | R29: --- | S29: 1fbd6b3d-9a6c-48b5-aac7-e60687c4df94
A30: PASILLO 1 | B30: AP-01-032-1 | H30: =_xlfn.XLOOKUP(CRUCE[[#This Row],[Ubicacion]],Registros[Ubicacion],Registros[Codigo], "") | I30: =_xlfn.XLOOKUP(CRUCE[[#This Row],[Ubicacion]],Registros[Ubicacion],Registros[Total], "") | J30: =_xlfn.XLOOKUP(CRUCE[[#This Row],[Ubicacion]],Registros[Ubicacion],Registros[UMA], "") | K30: =IF(CRUCE[[#This Row],[TOTAL]]="","",CRUCE[[#This Row],[TOTAL]]-CRUCE[[#This Row],[BULTOS]]) | L30: =IF(CRUCE[[#This Row],[TOTAL]]="", "PENDIENTE", IF(CRUCE[[#This Row],[Diferencia]]=0, "CUADRADO", IF(CRUCE[[#This Row],[Diferencia]]>0, "SOBRANTE", "FALTANTE"))) -> PENDIENTE | M30: =IF(CRUCE[[#This Row],[Diferencia]]="","",IF(CRUCE[[#This Row],[Diferencia]]=0,"OK","RECONTEO")) | N30: =_xlfn.XLOOKUP(CRUCE[[#This Row],[Ubicacion]],Registros[Ubicacion],Registros[Codigo], "") | Q30: =IF(CRUCE[[#This Row],[TOTAL2]]="", "PENDIENTE", IF(CRUCE[[#This Row],[DIFERENCIA2]]=0, "CUADRADO", IF(CRUCE[[#This Row],[DIFERENCIA2]]>0, "SOBRANTE", "FALTANTE"))) -> PENDIENTE | R30: --- | S30: 2f0d9e53-86a6-4885-9258-6c82e1465458
A31: PASILLO 1 | B31: AP-01-033-1 | H31: =_xlfn.XLOOKUP(CRUCE[[#This Row],[Ubicacion]],Registros[Ubicacion],Registros[Codigo], "") | I31: =_xlfn.XLOOKUP(CRUCE[[#This Row],[Ubicacion]],Registros[Ubicacion],Registros[Total], "") | J31: =_xlfn.XLOOKUP(CRUCE[[#This Row],[Ubicacion]],Registros[Ubicacion],Registros[UMA], "") | K31: =IF(CRUCE[[#This Row],[TOTAL]]="","",CRUCE[[#This Row],[TOTAL]]-CRUCE[[#This Row],[BULTOS]]) | L31: =IF(CRUCE[[#This Row],[TOTAL]]="", "PENDIENTE", IF(CRUCE[[#This Row],[Diferencia]]=0, "CUADRADO", IF(CRUCE[[#This Row],[Diferencia]]>0, "SOBRANTE", "FALTANTE"))) -> PENDIENTE | M31: =IF(CRUCE[[#This Row],[Diferencia]]="","",IF(CRUCE[[#This Row],[Diferencia]]=0,"OK","RECONTEO")) | N31: =_xlfn.XLOOKUP(CRUCE[[#This Row],[Ubicacion]],Registros[Ubicacion],Registros[Codigo], "") | Q31: =IF(CRUCE[[#This Row],[TOTAL2]]="", "PENDIENTE", IF(CRUCE[[#This Row],[DIFERENCIA2]]=0, "CUADRADO", IF(CRUCE[[#This Row],[DIFERENCIA2]]>0, "SOBRANTE", "FALTANTE"))) -> PENDIENTE | R31: --- | S31: 610fe278-f351-4a56-87d2-d6c154d98ef3
A32: PASILLO 1 | B32: AP-01-034-1 | H32: =_xlfn.XLOOKUP(CRUCE[[#This Row],[Ubicacion]],Registros[Ubicacion],Registros[Codigo], "") | I32: =_xlfn.XLOOKUP(CRUCE[[#This Row],[Ubicacion]],Registros[Ubicacion],Registros[Total], "") | J32: =_xlfn.XLOOKUP(CRUCE[[#This Row],[Ubicacion]],Registros[Ubicacion],Registros[UMA], "") | K32: =IF(CRUCE[[#This Row],[TOTAL]]="","",CRUCE[[#This Row],[TOTAL]]-CRUCE[[#This Row],[BULTOS]]) | L32: =IF(CRUCE[[#This Row],[TOTAL]]="", "PENDIENTE", IF(CRUCE[[#This Row],[Diferencia]]=0, "CUADRADO", IF(CRUCE[[#This Row],[Diferencia]]>0, "SOBRANTE", "FALTANTE"))) -> PENDIENTE | M32: =IF(CRUCE[[#This Row],[Diferencia]]="","",IF(CRUCE[[#This Row],[Diferencia]]=0,"OK","RECONTEO")) | N32: =_xlfn.XLOOKUP(CRUCE[[#This Row],[Ubicacion]],Registros[Ubicacion],Registros[Codigo], "") | Q32: =IF(CRUCE[[#This Row],[TOTAL2]]="", "PENDIENTE", IF(CRUCE[[#This Row],[DIFERENCIA2]]=0, "CUADRADO", IF(CRUCE[[#This Row],[DIFERENCIA2]]>0, "SOBRANTE", "FALTANTE"))) -> PENDIENTE | R32: --- | S32: 8e702fdb-3911-4129-b88f-08a3db2c3f9f
A33: PASILLO 1 | B33: AP-01-035-1 | H33: =_xlfn.XLOOKUP(CRUCE[[#This Row],[Ubicacion]],Registros[Ubicacion],Registros[Codigo], "") | I33: =_xlfn.XLOOKUP(CRUCE[[#This Row],[Ubicacion]],Registros[Ubicacion],Registros[Total], "") | J33: =_xlfn.XLOOKUP(CRUCE[[#This Row],[Ubicacion]],Registros[Ubicacion],Registros[UMA], "") | K33: =IF(CRUCE[[#This Row],[TOTAL]]="","",CRUCE[[#This Row],[TOTAL]]-CRUCE[[#This Row],[BULTOS]]) | L33: =IF(CRUCE[[#This Row],[TOTAL]]="", "PENDIENTE", IF(CRUCE[[#This Row],[Diferencia]]=0, "CUADRADO", IF(CRUCE[[#This Row],[Diferencia]]>0, "SOBRANTE", "FALTANTE"))) -> PENDIENTE | M33: =IF(CRUCE[[#This Row],[Diferencia]]="","",IF(CRUCE[[#This Row],[Diferencia]]=0,"OK","RECONTEO")) | N33: =_xlfn.XLOOKUP(CRUCE[[#This Row],[Ubicacion]],Registros[Ubicacion],Registros[Codigo], "") | Q33: =IF(CRUCE[[#This Row],[TOTAL2]]="", "PENDIENTE", IF(CRUCE[[#This Row],[DIFERENCIA2]]=0, "CUADRADO", IF(CRUCE[[#This Row],[DIFERENCIA2]]>0, "SOBRANTE", "FALTANTE"))) -> PENDIENTE | R33: --- | S33: 5113aa5b-7088-4267-8e1d-7727150fffc9
A34: PASILLO 1 | B34: AP-01-036-1 | H34: =_xlfn.XLOOKUP(CRUCE[[#This Row],[Ubicacion]],Registros[Ubicacion],Registros[Codigo], "") | I34: =_xlfn.XLOOKUP(CRUCE[[#This Row],[Ubicacion]],Registros[Ubicacion],Registros[Total], "") | J34: =_xlfn.XLOOKUP(CRUCE[[#This Row],[Ubicacion]],Registros[Ubicacion],Registros[UMA], "") | K34: =IF(CRUCE[[#This Row],[TOTAL]]="","",CRUCE[[#This Row],[TOTAL]]-CRUCE[[#This Row],[BULTOS]]) | L34: =IF(CRUCE[[#This Row],[TOTAL]]="", "PENDIENTE", IF(CRUCE[[#This Row],[Diferencia]]=0, "CUADRADO", IF(CRUCE[[#This Row],[Diferencia]]>0, "SOBRANTE", "FALTANTE"))) -> PENDIENTE | M34: =IF(CRUCE[[#This Row],[Diferencia]]="","",IF(CRUCE[[#This Row],[Diferencia]]=0,"OK","RECONTEO")) | N34: =_xlfn.XLOOKUP(CRUCE[[#This Row],[Ubicacion]],Registros[Ubicacion],Registros[Codigo], "") | Q34: =IF(CRUCE[[#This Row],[TOTAL2]]="", "PENDIENTE", IF(CRUCE[[#This Row],[DIFERENCIA2]]=0, "CUADRADO", IF(CRUCE[[#This Row],[DIFERENCIA2]]>0, "SOBRANTE", "FALTANTE"))) -> PENDIENTE | R34: --- | S34: 6937b448-4f74-4255-9b82-d0c3865b4095
A35: PASILLO 1 | B35: AP-01-037-1 | H35: =_xlfn.XLOOKUP(CRUCE[[#This Row],[Ubicacion]],Registros[Ubicacion],Registros[Codigo], "") | I35: =_xlfn.XLOOKUP(CRUCE[[#This Row],[Ubicacion]],Registros[Ubicacion],Registros[Total], "") | J35: =_xlfn.XLOOKUP(CRUCE[[#This Row],[Ubicacion]],Registros[Ubicacion],Registros[UMA], "") | K35: =IF(CRUCE[[#This Row],[TOTAL]]="","",CRUCE[[#This Row],[TOTAL]]-CRUCE[[#This Row],[BULTOS]]) | L35: =IF(CRUCE[[#This Row],[TOTAL]]="", "PENDIENTE", IF(CRUCE[[#This Row],[Diferencia]]=0, "CUADRADO", IF(CRUCE[[#This Row],[Diferencia]]>0, "SOBRANTE", "FALTANTE"))) -> PENDIENTE | M35: =IF(CRUCE[[#This Row],[Diferencia]]="","",IF(CRUCE[[#This Row],[Diferencia]]=0,"OK","RECONTEO")) | N35: =_xlfn.XLOOKUP(CRUCE[[#This Row],[Ubicacion]],Registros[Ubicacion],Registros[Codigo], "") | Q35: =IF(CRUCE[[#This Row],[TOTAL2]]="", "PENDIENTE", IF(CRUCE[[#This Row],[DIFERENCIA2]]=0, "CUADRADO", IF(CRUCE[[#This Row],[DIFERENCIA2]]>0, "SOBRANTE", "FALTANTE"))) -> PENDIENTE | R35: --- | S35: 6ce1df0e-6d68-4b39-a1a1-ca5ee1002a47
A36: PASILLO 1 | B36: AP-01-038-1 | H36: =_xlfn.XLOOKUP(CRUCE[[#This Row],[Ubicacion]],Registros[Ubicacion],Registros[Codigo], "") | I36: =_xlfn.XLOOKUP(CRUCE[[#This Row],[Ubicacion]],Registros[Ubicacion],Registros[Total], "") | J36: =_xlfn.XLOOKUP(CRUCE[[#This Row],[Ubicacion]],Registros[Ubicacion],Registros[UMA], "") | K36: =IF(CRUCE[[#This Row],[TOTAL]]="","",CRUCE[[#This Row],[TOTAL]]-CRUCE[[#This Row],[BULTOS]]) | L36: =IF(CRUCE[[#This Row],[TOTAL]]="", "PENDIENTE", IF(CRUCE[[#This Row],[Diferencia]]=0, "CUADRADO", IF(CRUCE[[#This Row],[Diferencia]]>0, "SOBRANTE", "FALTANTE"))) -> PENDIENTE | M36: =IF(CRUCE[[#This Row],[Diferencia]]="","",IF(CRUCE[[#This Row],[Diferencia]]=0,"OK","RECONTEO")) | N36: =_xlfn.XLOOKUP(CRUCE[[#This Row],[Ubicacion]],Registros[Ubicacion],Registros[Codigo], "") | Q36: =IF(CRUCE[[#This Row],[TOTAL2]]="", "PENDIENTE", IF(CRUCE[[#This Row],[DIFERENCIA2]]=0, "CUADRADO", IF(CRUCE[[#This Row],[DIFERENCIA2]]>0, "SOBRANTE", "FALTANTE"))) -> PENDIENTE | R36: --- | S36: 1e615fe9-7b39-4c52-98b6-57f4fb6aded6
A37: PASILLO 1 | B37: AP-01-039-1 | H37: =_xlfn.XLOOKUP(CRUCE[[#This Row],[Ubicacion]],Registros[Ubicacion],Registros[Codigo], "") | I37: =_xlfn.XLOOKUP(CRUCE[[#This Row],[Ubicacion]],Registros[Ubicacion],Registros[Total], "") | J37: =_xlfn.XLOOKUP(CRUCE[[#This Row],[Ubicacion]],Registros[Ubicacion],Registros[UMA], "") | K37: =IF(CRUCE[[#This Row],[TOTAL]]="","",CRUCE[[#This Row],[TOTAL]]-CRUCE[[#This Row],[BULTOS]]) | L37: =IF(CRUCE[[#This Row],[TOTAL]]="", "PENDIENTE", IF(CRUCE[[#This Row],[Diferencia]]=0, "CUADRADO", IF(CRUCE[[#This Row],[Diferencia]]>0, "SOBRANTE", "FALTANTE"))) -> PENDIENTE | M37: =IF(CRUCE[[#This Row],[Diferencia]]="","",IF(CRUCE[[#This Row],[Diferencia]]=0,"OK","RECONTEO")) | N37: =_xlfn.XLOOKUP(CRUCE[[#This Row],[Ubicacion]],Registros[Ubicacion],Registros[Codigo], "") | Q37: =IF(CRUCE[[#This Row],[TOTAL2]]="", "PENDIENTE", IF(CRUCE[[#This Row],[DIFERENCIA2]]=0, "CUADRADO", IF(CRUCE[[#This Row],[DIFERENCIA2]]>0, "SOBRANTE", "FALTANTE"))) -> PENDIENTE | R37: --- | S37: d64561df-3008-4791-9eb6-d47bd5ca3ca8
A38: PASILLO 1 | B38: AP-01-040-1 | H38: =_xlfn.XLOOKUP(CRUCE[[#This Row],[Ubicacion]],Registros[Ubicacion],Registros[Codigo], "") | I38: =_xlfn.XLOOKUP(CRUCE[[#This Row],[Ubicacion]],Registros[Ubicacion],Registros[Total], "") | J38: =_xlfn.XLOOKUP(CRUCE[[#This Row],[Ubicacion]],Registros[Ubicacion],Registros[UMA], "") | K38: =IF(CRUCE[[#This Row],[TOTAL]]="","",CRUCE[[#This Row],[TOTAL]]-CRUCE[[#This Row],[BULTOS]]) | L38: =IF(CRUCE[[#This Row],[TOTAL]]="", "PENDIENTE", IF(CRUCE[[#This Row],[Diferencia]]=0, "CUADRADO", IF(CRUCE[[#This Row],[Diferencia]]>0, "SOBRANTE", "FALTANTE"))) -> PENDIENTE | M38: =IF(CRUCE[[#This Row],[Diferencia]]="","",IF(CRUCE[[#This Row],[Diferencia]]=0,"OK","RECONTEO")) | N38: =_xlfn.XLOOKUP(CRUCE[[#This Row],[Ubicacion]],Registros[Ubicacion],Registros[Codigo], "") | Q38: =IF(CRUCE[[#This Row],[TOTAL2]]="", "PENDIENTE", IF(CRUCE[[#This Row],[DIFERENCIA2]]=0, "CUADRADO", IF(CRUCE[[#This Row],[DIFERENCIA2]]>0, "SOBRANTE", "FALTANTE"))) -> PENDIENTE | R38: --- | S38: 081433da-8bc3-4ec4-859a-0351e59ce7dc
A39: PASILLO 1 | B39: AP-01-041-1 | H39: =_xlfn.XLOOKUP(CRUCE[[#This Row],[Ubicacion]],Registros[Ubicacion],Registros[Codigo], "") | I39: =_xlfn.XLOOKUP(CRUCE[[#This Row],[Ubicacion]],Registros[Ubicacion],Registros[Total], "") | J39: =_xlfn.XLOOKUP(CRUCE[[#This Row],[Ubicacion]],Registros[Ubicacion],Registros[UMA], "") | K39: =IF(CRUCE[[#This Row],[TOTAL]]="","",CRUCE[[#This Row],[TOTAL]]-CRUCE[[#This Row],[BULTOS]]) | L39: =IF(CRUCE[[#This Row],[TOTAL]]="", "PENDIENTE", IF(CRUCE[[#This Row],[Diferencia]]=0, "CUADRADO", IF(CRUCE[[#This Row],[Diferencia]]>0, "SOBRANTE", "FALTANTE"))) -> PENDIENTE | M39: =IF(CRUCE[[#This Row],[Diferencia]]="","",IF(CRUCE[[#This Row],[Diferencia]]=0,"OK","RECONTEO")) | N39: =_xlfn.XLOOKUP(CRUCE[[#This Row],[Ubicacion]],Registros[Ubicacion],Registros[Codigo], "") | Q39: =IF(CRUCE[[#This Row],[TOTAL2]]="", "PENDIENTE", IF(CRUCE[[#This Row],[DIFERENCIA2]]=0, "CUADRADO", IF(CRUCE[[#This Row],[DIFERENCIA2]]>0, "SOBRANTE", "FALTANTE"))) -> PENDIENTE | R39: --- | S39: a1cbcac3-449c-44f8-b95f-5f66481a637d
A40: PASILLO 1 | B40: AP-01-042-1 | H40: =_xlfn.XLOOKUP(CRUCE[[#This Row],[Ubicacion]],Registros[Ubicacion],Registros[Codigo], "") | I40: =_xlfn.XLOOKUP(CRUCE[[#This Row],[Ubicacion]],Registros[Ubicacion],Registros[Total], "") | J40: =_xlfn.XLOOKUP(CRUCE[[#This Row],[Ubicacion]],Registros[Ubicacion],Registros[UMA], "") | K40: =IF(CRUCE[[#This Row],[TOTAL]]="","",CRUCE[[#This Row],[TOTAL]]-CRUCE[[#This Row],[BULTOS]]) | L40: =IF(CRUCE[[#This Row],[TOTAL]]="", "PENDIENTE", IF(CRUCE[[#This Row],[Diferencia]]=0, "CUADRADO", IF(CRUCE[[#This Row],[Diferencia]]>0, "SOBRANTE", "FALTANTE"))) -> PENDIENTE | M40: =IF(CRUCE[[#This Row],[Diferencia]]="","",IF(CRUCE[[#This Row],[Diferencia]]=0,"OK","RECONTEO")) | N40: =_xlfn.XLOOKUP(CRUCE[[#This Row],[Ubicacion]],Registros[Ubicacion],Registros[Codigo], "") | Q40: =IF(CRUCE[[#This Row],[TOTAL2]]="", "PENDIENTE", IF(CRUCE[[#This Row],[DIFERENCIA2]]=0, "CUADRADO", IF(CRUCE[[#This Row],[DIFERENCIA2]]>0, "SOBRANTE", "FALTANTE"))) -> PENDIENTE | R40: --- | S40: 9dfbc586-639b-4d4f-b78b-20293817e132
A41: PASILLO 1 | B41: AP-01-044-1 | H41: =_xlfn.XLOOKUP(CRUCE[[#This Row],[Ubicacion]],Registros[Ubicacion],Registros[Codigo], "") | I41: =_xlfn.XLOOKUP(CRUCE[[#This Row],[Ubicacion]],Registros[Ubicacion],Registros[Total], "") | J41: =_xlfn.XLOOKUP(CRUCE[[#This Row],[Ubicacion]],Registros[Ubicacion],Registros[UMA], "") | K41: =IF(CRUCE[[#This Row],[TOTAL]]="","",CRUCE[[#This Row],[TOTAL]]-CRUCE[[#This Row],[BULTOS]]) | L41: =IF(CRUCE[[#This Row],[TOTAL]]="", "PENDIENTE", IF(CRUCE[[#This Row],[Diferencia]]=0, "CUADRADO", IF(CRUCE[[#This Row],[Diferencia]]>0, "SOBRANTE", "FALTANTE"))) -> PENDIENTE | M41: =IF(CRUCE[[#This Row],[Diferencia]]="","",IF(CRUCE[[#This Row],[Diferencia]]=0,"OK","RECONTEO")) | N41: =_xlfn.XLOOKUP(CRUCE[[#This Row],[Ubicacion]],Registros[Ubicacion],Registros[Codigo], "") | Q41: =IF(CRUCE[[#This Row],[TOTAL2]]="", "PENDIENTE", IF(CRUCE[[#This Row],[DIFERENCIA2]]=0, "CUADRADO", IF(CRUCE[[#This Row],[DIFERENCIA2]]>0, "SOBRANTE", "FALTANTE"))) -> PENDIENTE | R41: --- | S41: 5b120565-66d6-465f-908a-c6a37116c7df
A42: PASILLO 1 | B42: CH-01-043-1 | C42: 8309119 | D42: 37751851005983 | E42: AMBIENTADOR SAPOLIO LAVANDA 360ML 12UND | F42: 94 | G42: CJA | H42: =_xlfn.XLOOKUP(CRUCE[[#This Row],[Ubicacion]],Registros[Ubicacion],Registros[Codigo], "") | I42: =_xlfn.XLOOKUP(CRUCE[[#This Row],[Ubicacion]],Registros[Ubicacion],Registros[Total], "") | J42: =_xlfn.XLOOKUP(CRUCE[[#This Row],[Ubicacion]],Registros[Ubicacion],Registros[UMA], "") | K42: =IF(CRUCE[[#This Row],[TOTAL]]="","",CRUCE[[#This Row],[TOTAL]]-CRUCE[[#This Row],[BULTOS]]) | L42: =IF(CRUCE[[#This Row],[TOTAL]]="", "PENDIENTE", IF(CRUCE[[#This Row],[Diferencia]]=0, "CUADRADO", IF(CRUCE[[#This Row],[Diferencia]]>0, "SOBRANTE", "FALTANTE"))) -> PENDIENTE | M42: =IF(CRUCE[[#This Row],[Diferencia]]="","",IF(CRUCE[[#This Row],[Diferencia]]=0,"OK","RECONTEO")) | N42: =_xlfn.XLOOKUP(CRUCE[[#This Row],[Ubicacion]],Registros[Ubicacion],Registros[Codigo], "") | Q42: =IF(CRUCE[[#This Row],[TOTAL2]]="", "PENDIENTE", IF(CRUCE[[#This Row],[DIFERENCIA2]]=0, "CUADRADO", IF(CRUCE[[#This Row],[DIFERENCIA2]]>0, "SOBRANTE", "FALTANTE"))) -> PENDIENTE | R42: --- | S42: 75520938-2d05-4ff0-b307-f146e213f5cc
A43: PASILLO 5 | B43: PP-05-005-1 | H43: =_xlfn.XLOOKUP(CRUCE[[#This Row],[Ubicacion]],Registros[Ubicacion],Registros[Codigo], "") | I43: =_xlfn.XLOOKUP(CRUCE[[#This Row],[Ubicacion]],Registros[Ubicacion],Registros[Total], "") | J43: =_xlfn.XLOOKUP(CRUCE[[#This Row],[Ubicacion]],Registros[Ubicacion],Registros[UMA], "") | K43: =IF(CRUCE[[#This Row],[TOTAL]]="","",CRUCE[[#This Row],[TOTAL]]-CRUCE[[#This Row],[BULTOS]]) | L43: =IF(CRUCE[[#This Row],[TOTAL]]="", "PENDIENTE", IF(CRUCE[[#This Row],[Diferencia]]=0, "CUADRADO", IF(CRUCE[[#This Row],[Diferencia]]>0, "SOBRANTE", "FALTANTE"))) -> PENDIENTE | M43: =IF(CRUCE[[#This Row],[Diferencia]]="","",IF(CRUCE[[#This Row],[Diferencia]]=0,"OK","RECONTEO")) | N43: =_xlfn.XLOOKUP(CRUCE[[#This Row],[Ubicacion]],Registros[Ubicacion],Registros[Codigo], "") | Q43: =IF(CRUCE[[#This Row],[TOTAL2]]="", "PENDIENTE", IF(CRUCE[[#This Row],[DIFERENCIA2]]=0, "CUADRADO", IF(CRUCE[[#This Row],[DIFERENCIA2]]>0, "SOBRANTE", "FALTANTE"))) -> PENDIENTE | R43: --- | S43: 2654e9b1-5d65-47f1-8c4d-1129124fde2b
A44: PASILLO 5 | B44: PP-05-006-1 | H44: =_xlfn.XLOOKUP(CRUCE[[#This Row],[Ubicacion]],Registros[Ubicacion],Registros[Codigo], "") | I44: =_xlfn.XLOOKUP(CRUCE[[#This Row],[Ubicacion]],Registros[Ubicacion],Registros[Total], "") | J44: =_xlfn.XLOOKUP(CRUCE[[#This Row],[Ubicacion]],Registros[Ubicacion],Registros[UMA], "") | K44: =IF(CRUCE[[#This Row],[TOTAL]]="","",CRUCE[[#This Row],[TOTAL]]-CRUCE[[#This Row],[BULTOS]]) | L44: =IF(CRUCE[[#This Row],[TOTAL]]="", "PENDIENTE", IF(CRUCE[[#This Row],[Diferencia]]=0, "CUADRADO", IF(CRUCE[[#This Row],[Diferencia]]>0, "SOBRANTE", "FALTANTE"))) -> PENDIENTE | M44: =IF(CRUCE[[#This Row],[Diferencia]]="","",IF(CRUCE[[#This Row],[Diferencia]]=0,"OK","RECONTEO")) | N44: =_xlfn.XLOOKUP(CRUCE[[#This Row],[Ubicacion]],Registros[Ubicacion],Registros[Codigo], "") | Q44: =IF(CRUCE[[#This Row],[TOTAL2]]="", "PENDIENTE", IF(CRUCE[[#This Row],[DIFERENCIA2]]=0, "CUADRADO", IF(CRUCE[[#This Row],[DIFERENCIA2]]>0, "SOBRANTE", "FALTANTE"))) -> PENDIENTE | R44: --- | S44: 026307e8-0ef3-4008-b912-450fb4a52740
A45: PASILLO 5 | B45: PP-05-007-1 | H45: =_xlfn.XLOOKUP(CRUCE[[#This Row],[Ubicacion]],Registros[Ubicacion],Registros[Codigo], "") | I45: =_xlfn.XLOOKUP(CRUCE[[#This Row],[Ubicacion]],Registros[Ubicacion],Registros[Total], "") | J45: =_xlfn.XLOOKUP(CRUCE[[#This Row],[Ubicacion]],Registros[Ubicacion],Registros[UMA], "") | K45: =IF(CRUCE[[#This Row],[TOTAL]]="","",CRUCE[[#This Row],[TOTAL]]-CRUCE[[#This Row],[BULTOS]]) | L45: =IF(CRUCE[[#This Row],[TOTAL]]="", "PENDIENTE", IF(CRUCE[[#This Row],[Diferencia]]=0, "CUADRADO", IF(CRUCE[[#This Row],[Diferencia]]>0, "SOBRANTE", "FALTANTE"))) -> PENDIENTE | M45: =IF(CRUCE[[#This Row],[Diferencia]]="","",IF(CRUCE[[#This Row],[Diferencia]]=0,"OK","RECONTEO")) | N45: =_xlfn.XLOOKUP(CRUCE[[#This Row],[Ubicacion]],Registros[Ubicacion],Registros[Codigo], "") | Q45: =IF(CRUCE[[#This Row],[TOTAL2]]="", "PENDIENTE", IF(CRUCE[[#This Row],[DIFERENCIA2]]=0, "CUADRADO", IF(CRUCE[[#This Row],[DIFERENCIA2]]>0, "SOBRANTE", "FALTANTE"))) -> PENDIENTE | R45: --- | S45: 959455ed-188e-48fb-8a2c-11f11f0b3b13
A46: PASILLO 5 | B46: PP-05-008-1 | H46: =_xlfn.XLOOKUP(CRUCE[[#This Row],[Ubicacion]],Registros[Ubicacion],Registros[Codigo], "") | I46: =_xlfn.XLOOKUP(CRUCE[[#This Row],[Ubicacion]],Registros[Ubicacion],Registros[Total], "") | J46: =_xlfn.XLOOKUP(CRUCE[[#This Row],[Ubicacion]],Registros[Ubicacion],Registros[UMA], "") | K46: =IF(CRUCE[[#This Row],[TOTAL]]="","",CRUCE[[#This Row],[TOTAL]]-CRUCE[[#This Row],[BULTOS]]) | L46: =IF(CRUCE[[#This Row],[TOTAL]]="", "PENDIENTE", IF(CRUCE[[#This Row],[Diferencia]]=0, "CUADRADO", IF(CRUCE[[#This Row],[Diferencia]]>0, "SOBRANTE", "FALTANTE"))) -> PENDIENTE | M46: =IF(CRUCE[[#This Row],[Diferencia]]="","",IF(CRUCE[[#This Row],[Diferencia]]=0,"OK","RECONTEO")) | N46: =_xlfn.XLOOKUP(CRUCE[[#This Row],[Ubicacion]],Registros[Ubicacion],Registros[Codigo], "") | Q46: =IF(CRUCE[[#This Row],[TOTAL2]]="", "PENDIENTE", IF(CRUCE[[#This Row],[DIFERENCIA2]]=0, "CUADRADO", IF(CRUCE[[#This Row],[DIFERENCIA2]]>0, "SOBRANTE", "FALTANTE"))) -> PENDIENTE | R46: --- | S46: 447011e0-c81c-4906-bd16-a85b1b00dec0
A47: PASILLO 5 | B47: PP-05-009-1 | H47: =_xlfn.XLOOKUP(CRUCE[[#This Row],[Ubicacion]],Registros[Ubicacion],Registros[Codigo], "") | I47: =_xlfn.XLOOKUP(CRUCE[[#This Row],[Ubicacion]],Registros[Ubicacion],Registros[Total], "") | J47: =_xlfn.XLOOKUP(CRUCE[[#This Row],[Ubicacion]],Registros[Ubicacion],Registros[UMA], "") | K47: =IF(CRUCE[[#This Row],[TOTAL]]="","",CRUCE[[#This Row],[TOTAL]]-CRUCE[[#This Row],[BULTOS]]) | L47: =IF(CRUCE[[#This Row],[TOTAL]]="", "PENDIENTE", IF(CRUCE[[#This Row],[Diferencia]]=0, "CUADRADO", IF(CRUCE[[#This Row],[Diferencia]]>0, "SOBRANTE", "FALTANTE"))) -> PENDIENTE | M47: =IF(CRUCE[[#This Row],[Diferencia]]="","",IF(CRUCE[[#This Row],[Diferencia]]=0,"OK","RECONTEO")) | N47: =_xlfn.XLOOKUP(CRUCE[[#This Row],[Ubicacion]],Registros[Ubicacion],Registros[Codigo], "") | Q47: =IF(CRUCE[[#This Row],[TOTAL2]]="", "PENDIENTE", IF(CRUCE[[#This Row],[DIFERENCIA2]]=0, "CUADRADO", IF(CRUCE[[#This Row],[DIFERENCIA2]]>0, "SOBRANTE", "FALTANTE"))) -> PENDIENTE | R47: --- | S47: ee18dae1-3041-400e-ae7c-3f23cc07d663
A48: PASILLO 5 | B48: PP-05-010-1 | H48: =_xlfn.XLOOKUP(CRUCE[[#This Row],[Ubicacion]],Registros[Ubicacion],Registros[Codigo], "") | I48: =_xlfn.XLOOKUP(CRUCE[[#This Row],[Ubicacion]],Registros[Ubicacion],Registros[Total], "") | J48: =_xlfn.XLOOKUP(CRUCE[[#This Row],[Ubicacion]],Registros[Ubicacion],Registros[UMA], "") | K48: =IF(CRUCE[[#This Row],[TOTAL]]="","",CRUCE[[#This Row],[TOTAL]]-CRUCE[[#This Row],[BULTOS]]) | L48: =IF(CRUCE[[#This Row],[TOTAL]]="", "PENDIENTE", IF(CRUCE[[#This Row],[Diferencia]]=0, "CUADRADO", IF(CRUCE[[#This Row],[Diferencia]]>0, "SOBRANTE", "FALTANTE"))) -> PENDIENTE | M48: =IF(CRUCE[[#This Row],[Diferencia]]="","",IF(CRUCE[[#This Row],[Diferencia]]=0,"OK","RECONTEO")) | N48: =_xlfn.XLOOKUP(CRUCE[[#This Row],[Ubicacion]],Registros[Ubicacion],Registros[Codigo], "") | Q48: =IF(CRUCE[[#This Row],[TOTAL2]]="", "PENDIENTE", IF(CRUCE[[#This Row],[DIFERENCIA2]]=0, "CUADRADO", IF(CRUCE[[#This Row],[DIFERENCIA2]]>0, "SOBRANTE", "FALTANTE"))) -> PENDIENTE | R48: --- | S48: c9e7bc5e-306b-4a72-8426-7df42abb7abd
A49: PASILLO 5 | B49: PP-05-011-1 | H49: =_xlfn.XLOOKUP(CRUCE[[#This Row],[Ubicacion]],Registros[Ubicacion],Registros[Codigo], "") | I49: =_xlfn.XLOOKUP(CRUCE[[#This Row],[Ubicacion]],Registros[Ubicacion],Registros[Total], "") | J49: =_xlfn.XLOOKUP(CRUCE[[#This Row],[Ubicacion]],Registros[Ubicacion],Registros[UMA], "") | K49: =IF(CRUCE[[#This Row],[TOTAL]]="","",CRUCE[[#This Row],[TOTAL]]-CRUCE[[#This Row],[BULTOS]]) | L49: =IF(CRUCE[[#This Row],[TOTAL]]="", "PENDIENTE", IF(CRUCE[[#This Row],[Diferencia]]=0, "CUADRADO", IF(CRUCE[[#This Row],[Diferencia]]>0, "SOBRANTE", "FALTANTE"))) -> PENDIENTE | M49: =IF(CRUCE[[#This Row],[Diferencia]]="","",IF(CRUCE[[#This Row],[Diferencia]]=0,"OK","RECONTEO")) | N49: =_xlfn.XLOOKUP(CRUCE[[#This Row],[Ubicacion]],Registros[Ubicacion],Registros[Codigo], "") | Q49: =IF(CRUCE[[#This Row],[TOTAL2]]="", "PENDIENTE", IF(CRUCE[[#This Row],[DIFERENCIA2]]=0, "CUADRADO", IF(CRUCE[[#This Row],[DIFERENCIA2]]>0, "SOBRANTE", "FALTANTE"))) -> PENDIENTE | R49: --- | S49: 0e31a412-5e9f-40e2-9de7-54c244932263
A50: PASILLO 5 | B50: PP-05-012-1 | H50: =_xlfn.XLOOKUP(CRUCE[[#This Row],[Ubicacion]],Registros[Ubicacion],Registros[Codigo], "") | I50: =_xlfn.XLOOKUP(CRUCE[[#This Row],[Ubicacion]],Registros[Ubicacion],Registros[Total], "") | J50: =_xlfn.XLOOKUP(CRUCE[[#This Row],[Ubicacion]],Registros[Ubicacion],Registros[UMA], "") | K50: =IF(CRUCE[[#This Row],[TOTAL]]="","",CRUCE[[#This Row],[TOTAL]]-CRUCE[[#This Row],[BULTOS]]) | L50: =IF(CRUCE[[#This Row],[TOTAL]]="", "PENDIENTE", IF(CRUCE[[#This Row],[Diferencia]]=0, "CUADRADO", IF(CRUCE[[#This Row],[Diferencia]]>0, "SOBRANTE", "FALTANTE"))) -> PENDIENTE | M50: =IF(CRUCE[[#This Row],[Diferencia]]="","",IF(CRUCE[[#This Row],[Diferencia]]=0,"OK","RECONTEO")) | N50: =_xlfn.XLOOKUP(CRUCE[[#This Row],[Ubicacion]],Registros[Ubicacion],Registros[Codigo], "") | Q50: =IF(CRUCE[[#This Row],[TOTAL2]]="", "PENDIENTE", IF(CRUCE[[#This Row],[DIFERENCIA2]]=0, "CUADRADO", IF(CRUCE[[#This Row],[DIFERENCIA2]]>0, "SOBRANTE", "FALTANTE"))) -> PENDIENTE | R50: --- | S50: 6d3d51cc-edbb-4459-a5a0-fc79e1748716
A51: PASILLO 5 | B51: PP-05-013-1 | H51: =_xlfn.XLOOKUP(CRUCE[[#This Row],[Ubicacion]],Registros[Ubicacion],Registros[Codigo], "") | I51: =_xlfn.XLOOKUP(CRUCE[[#This Row],[Ubicacion]],Registros[Ubicacion],Registros[Total], "") | J51: =_xlfn.XLOOKUP(CRUCE[[#This Row],[Ubicacion]],Registros[Ubicacion],Registros[UMA], "") | K51: =IF(CRUCE[[#This Row],[TOTAL]]="","",CRUCE[[#This Row],[TOTAL]]-CRUCE[[#This Row],[BULTOS]]) | L51: =IF(CRUCE[[#This Row],[TOTAL]]="", "PENDIENTE", IF(CRUCE[[#This Row],[Diferencia]]=0, "CUADRADO", IF(CRUCE[[#This Row],[Diferencia]]>0, "SOBRANTE", "FALTANTE"))) -> PENDIENTE | M51: =IF(CRUCE[[#This Row],[Diferencia]]="","",IF(CRUCE[[#This Row],[Diferencia]]=0,"OK","RECONTEO")) | N51: =_xlfn.XLOOKUP(CRUCE[[#This Row],[Ubicacion]],Registros[Ubicacion],Registros[Codigo], "") | Q51: =IF(CRUCE[[#This Row],[TOTAL2]]="", "PENDIENTE", IF(CRUCE[[#This Row],[DIFERENCIA2]]=0, "CUADRADO", IF(CRUCE[[#This Row],[DIFERENCIA2]]>0, "SOBRANTE", "FALTANTE"))) -> PENDIENTE | R51: --- | S51: 42ba55ce-3efa-4705-a1f7-a6ab53458529
A52: PASILLO 5 | B52: PP-05-014-1 | H52: =_xlfn.XLOOKUP(CRUCE[[#This Row],[Ubicacion]],Registros[Ubicacion],Registros[Codigo], "") | I52: =_xlfn.XLOOKUP(CRUCE[[#This Row],[Ubicacion]],Registros[Ubicacion],Registros[Total], "") | J52: =_xlfn.XLOOKUP(CRUCE[[#This Row],[Ubicacion]],Registros[Ubicacion],Registros[UMA], "") | K52: =IF(CRUCE[[#This Row],[TOTAL]]="","",CRUCE[[#This Row],[TOTAL]]-CRUCE[[#This Row],[BULTOS]]) | L52: =IF(CRUCE[[#This Row],[TOTAL]]="", "PENDIENTE", IF(CRUCE[[#This Row],[Diferencia]]=0, "CUADRADO", IF(CRUCE[[#This Row],[Diferencia]]>0, "SOBRANTE", "FALTANTE"))) -> PENDIENTE | M52: =IF(CRUCE[[#This Row],[Diferencia]]="","",IF(CRUCE[[#This Row],[Diferencia]]=0,"OK","RECONTEO")) | N52: =_xlfn.XLOOKUP(CRUCE[[#This Row],[Ubicacion]],Registros[Ubicacion],Registros[Codigo], "") | Q52: =IF(CRUCE[[#This Row],[TOTAL2]]="", "PENDIENTE", IF(CRUCE[[#This Row],[DIFERENCIA2]]=0, "CUADRADO", IF(CRUCE[[#This Row],[DIFERENCIA2]]>0, "SOBRANTE", "FALTANTE"))) -> PENDIENTE | R52: --- | S52: a4f1ae19-cc92-41fb-9e09-3c8c3f16f836
A53: PASILLO 5 | B53: PP-05-015-1 | H53: =_xlfn.XLOOKUP(CRUCE[[#This Row],[Ubicacion]],Registros[Ubicacion],Registros[Codigo], "") | I53: =_xlfn.XLOOKUP(CRUCE[[#This Row],[Ubicacion]],Registros[Ubicacion],Registros[Total], "") | J53: =_xlfn.XLOOKUP(CRUCE[[#This Row],[Ubicacion]],Registros[Ubicacion],Registros[UMA], "") | K53: =IF(CRUCE[[#This Row],[TOTAL]]="","",CRUCE[[#This Row],[TOTAL]]-CRUCE[[#This Row],[BULTOS]]) | L53: =IF(CRUCE[[#This Row],[TOTAL]]="", "PENDIENTE", IF(CRUCE[[#This Row],[Diferencia]]=0, "CUADRADO", IF(CRUCE[[#This Row],[Diferencia]]>0, "SOBRANTE", "FALTANTE"))) -> PENDIENTE | M53: =IF(CRUCE[[#This Row],[Diferencia]]="","",IF(CRUCE[[#This Row],[Diferencia]]=0,"OK","RECONTEO")) | N53: =_xlfn.XLOOKUP(CRUCE[[#This Row],[Ubicacion]],Registros[Ubicacion],Registros[Codigo], "") | Q53: =IF(CRUCE[[#This Row],[TOTAL2]]="", "PENDIENTE", IF(CRUCE[[#This Row],[DIFERENCIA2]]=0, "CUADRADO", IF(CRUCE[[#This Row],[DIFERENCIA2]]>0, "SOBRANTE", "FALTANTE"))) -> PENDIENTE | R53: --- | S53: 6b3b6c25-5f13-469f-8386-cf4cd2aa19a1
A54: PASILLO 5 | B54: PP-05-016-1 | H54: =_xlfn.XLOOKUP(CRUCE[[#This Row],[Ubicacion]],Registros[Ubicacion],Registros[Codigo], "") | I54: =_xlfn.XLOOKUP(CRUCE[[#This Row],[Ubicacion]],Registros[Ubicacion],Registros[Total], "") | J54: =_xlfn.XLOOKUP(CRUCE[[#This Row],[Ubicacion]],Registros[Ubicacion],Registros[UMA], "") | K54: =IF(CRUCE[[#This Row],[TOTAL]]="","",CRUCE[[#This Row],[TOTAL]]-CRUCE[[#This Row],[BULTOS]]) | L54: =IF(CRUCE[[#This Row],[TOTAL]]="", "PENDIENTE", IF(CRUCE[[#This Row],[Diferencia]]=0, "CUADRADO", IF(CRUCE[[#This Row],[Diferencia]]>0, "SOBRANTE", "FALTANTE"))) -> PENDIENTE | M54: =IF(CRUCE[[#This Row],[Diferencia]]="","",IF(CRUCE[[#This Row],[Diferencia]]=0,"OK","RECONTEO")) | N54: =_xlfn.XLOOKUP(CRUCE[[#This Row],[Ubicacion]],Registros[Ubicacion],Registros[Codigo], "") | Q54: =IF(CRUCE[[#This Row],[TOTAL2]]="", "PENDIENTE", IF(CRUCE[[#This Row],[DIFERENCIA2]]=0, "CUADRADO", IF(CRUCE[[#This Row],[DIFERENCIA2]]>0, "SOBRANTE", "FALTANTE"))) -> PENDIENTE | R54: --- | S54: 459a3525-d5cd-4f3d-8d25-5637c3cee1f2
... A141: PASILLO 6 | B141: PP-06-052-1 | H141: =_xlfn.XLOOKUP(CRUCE[[#This Row],[Ubicacion]],Registros[Ubicacion],Registros[Codigo], "") | I141: =_xlfn.XLOOKUP(CRUCE[[#This Row],[Ubicacion]],Registros[Ubicacion],Registros[Total], "") | J141: =_xlfn.XLOOKUP(CRUCE[[#This Row],[Ubicacion]],Registros[Ubicacion],Registros[UMA], "") | K141: =IF(CRUCE[[#This Row],[TOTAL]]="","",CRUCE[[#This Row],[TOTAL]]-CRUCE[[#This Row],[BULTOS]]) | L141: =IF(CRUCE[[#This Row],[TOTAL]]="", "PENDIENTE", IF(CRUCE[[#This Row],[Diferencia]]=0, "CUADRADO", IF(CRUCE[[#This Row],[Diferencia]]>0, "SOBRANTE", "FALTANTE"))) -> PENDIENTE | M141: =IF(CRUCE[[#This Row],[Diferencia]]="","",IF(CRUCE[[#This Row],[Diferencia]]=0,"OK","RECONTEO")) | N141: =_xlfn.XLOOKUP(CRUCE[[#This Row],[Ubicacion]],Registros[Ubicacion],Registros[Codigo], "") | Q141: =IF(CRUCE[[#This Row],[TOTAL2]]="", "PENDIENTE", IF(CRUCE[[#This Row],[DIFERENCIA2]]=0, "CUADRADO", IF(CRUCE[[#This Row],[DIFERENCIA2]]>0, "SOBRANTE", "FALTANTE"))) -> PENDIENTE | R141: --- | S141: b6aa9f63-7e14-402c-88ac-d14f141f009d
A142: PASILLO 7 | B142: PP-07-001-1 | C142: 8300013 | D142: 7751851029292 | E142: LEJIA 4.63% ORIG SAPOLIO JC 5GL 1UND | F142: 19 | G142: UND | H142: =_xlfn.XLOOKUP(CRUCE[[#This Row],[Ubicacion]],Registros[Ubicacion],Registros[Codigo], "") | I142: =_xlfn.XLOOKUP(CRUCE[[#This Row],[Ubicacion]],Registros[Ubicacion],Registros[Total], "") | J142: =_xlfn.XLOOKUP(CRUCE[[#This Row],[Ubicacion]],Registros[Ubicacion],Registros[UMA], "") | K142: =IF(CRUCE[[#This Row],[TOTAL]]="","",CRUCE[[#This Row],[TOTAL]]-CRUCE[[#This Row],[BULTOS]]) | L142: =IF(CRUCE[[#This Row],[TOTAL]]="", "PENDIENTE", IF(CRUCE[[#This Row],[Diferencia]]=0, "CUADRADO", IF(CRUCE[[#This Row],[Diferencia]]>0, "SOBRANTE", "FALTANTE"))) -> PENDIENTE | M142: =IF(CRUCE[[#This Row],[Diferencia]]="","",IF(CRUCE[[#This Row],[Diferencia]]=0,"OK","RECONTEO")) | N142: =_xlfn.XLOOKUP(CRUCE[[#This Row],[Ubicacion]],Registros[Ubicacion],Registros[Codigo], "") | Q142: =IF(CRUCE[[#This Row],[TOTAL2]]="", "PENDIENTE", IF(CRUCE[[#This Row],[DIFERENCIA2]]=0, "CUADRADO", IF(CRUCE[[#This Row],[DIFERENCIA2]]>0, "SOBRANTE", "FALTANTE"))) -> PENDIENTE | R142: --- | S142: 995e5720-036d-42e4-86e2-edb8b4d14c80
A143: PASILLO 7 | B143: PP-07-002-1 | C143: 8303047 | D143: 7751851028998 | E143: DET.LIQUIDO FLORES SAP. JC 5GL 1UND | F143: 34 | G143: UND | H143: =_xlfn.XLOOKUP(CRUCE[[#This Row],[Ubicacion]],Registros[Ubicacion],Registros[Codigo], "") | I143: =_xlfn.XLOOKUP(CRUCE[[#This Row],[Ubicacion]],Registros[Ubicacion],Registros[Total], "") | J143: =_xlfn.XLOOKUP(CRUCE[[#This Row],[Ubicacion]],Registros[Ubicacion],Registros[UMA], "") | K143: =IF(CRUCE[[#This Row],[TOTAL]]="","",CRUCE[[#This Row],[TOTAL]]-CRUCE[[#This Row],[BULTOS]]) | L143: =IF(CRUCE[[#This Row],[TOTAL]]="", "PENDIENTE", IF(CRUCE[[#This Row],[Diferencia]]=0, "CUADRADO", IF(CRUCE[[#This Row],[Diferencia]]>0, "SOBRANTE", "FALTANTE"))) -> PENDIENTE | M143: =IF(CRUCE[[#This Row],[Diferencia]]="","",IF(CRUCE[[#This Row],[Diferencia]]=0,"OK","RECONTEO")) | N143: =_xlfn.XLOOKUP(CRUCE[[#This Row],[Ubicacion]],Registros[Ubicacion],Registros[Codigo], "") | Q143: =IF(CRUCE[[#This Row],[TOTAL2]]="", "PENDIENTE", IF(CRUCE[[#This Row],[DIFERENCIA2]]=0, "CUADRADO", IF(CRUCE[[#This Row],[DIFERENCIA2]]>0, "SOBRANTE", "FALTANTE"))) -> PENDIENTE | R143: --- | S143: 10d953fc-1c86-49e1-ab91-31a5b1ec7c22
A144: PASILLO 7 | B144: PP-07-003-1 | C144: 8414023 | D144: 7750243073486 | E144: DET. LÍQ. KLINTEX QUITAPRO 5GL | F144: 29 | G144: UND | H144: =_xlfn.XLOOKUP(CRUCE[[#This Row],[Ubicacion]],Registros[Ubicacion],Registros[Codigo], "") | I144: =_xlfn.XLOOKUP(CRUCE[[#This Row],[Ubicacion]],Registros[Ubicacion],Registros[Total], "") | J144: =_xlfn.XLOOKUP(CRUCE[[#This Row],[Ubicacion]],Registros[Ubicacion],Registros[UMA], "") | K144: =IF(CRUCE[[#This Row],[TOTAL]]="","",CRUCE[[#This Row],[TOTAL]]-CRUCE[[#This Row],[BULTOS]]) | L144: =IF(CRUCE[[#This Row],[TOTAL]]="", "PENDIENTE", IF(CRUCE[[#This Row],[Diferencia]]=0, "CUADRADO", IF(CRUCE[[#This Row],[Diferencia]]>0, "SOBRANTE", "FALTANTE"))) -> PENDIENTE | M144: =IF(CRUCE[[#This Row],[Diferencia]]="","",IF(CRUCE[[#This Row],[Diferencia]]=0,"OK","RECONTEO")) | N144: =_xlfn.XLOOKUP(CRUCE[[#This Row],[Ubicacion]],Registros[Ubicacion],Registros[Codigo], "") | Q144: =IF(CRUCE[[#This Row],[TOTAL2]]="", "PENDIENTE", IF(CRUCE[[#This Row],[DIFERENCIA2]]=0, "CUADRADO", IF(CRUCE[[#This Row],[DIFERENCIA2]]>0, "SOBRANTE", "FALTANTE"))) -> PENDIENTE | R144: --- | S144: b6601afc-7773-4cca-b62c-9cebbe8df643
A145: PASILLO 7 | B145: PP-07-004-1 | C145: 8303007 | D145: 17751851022016 | E145: DET.LIQUIDO FRESCO LIMON SAP. 5L 4UND | F145: 7 | G145: CJA | H145: =_xlfn.XLOOKUP(CRUCE[[#This Row],[Ubicacion]],Registros[Ubicacion],Registros[Codigo], "") | I145: =_xlfn.XLOOKUP(CRUCE[[#This Row],[Ubicacion]],Registros[Ubicacion],Registros[Total], "") | J145: =_xlfn.XLOOKUP(CRUCE[[#This Row],[Ubicacion]],Registros[Ubicacion],Registros[UMA], "") | K145: =IF(CRUCE[[#This Row],[TOTAL]]="","",CRUCE[[#This Row],[TOTAL]]-CRUCE[[#This Row],[BULTOS]]) | L145: =IF(CRUCE[[#This Row],[TOTAL]]="", "PENDIENTE", IF(CRUCE[[#This Row],[Diferencia]]=0, "CUADRADO", IF(CRUCE[[#This Row],[Diferencia]]>0, "SOBRANTE", "FALTANTE"))) -> PENDIENTE | M145: =IF(CRUCE[[#This Row],[Diferencia]]="","",IF(CRUCE[[#This Row],[Diferencia]]=0,"OK","RECONTEO")) | N145: =_xlfn.XLOOKUP(CRUCE[[#This Row],[Ubicacion]],Registros[Ubicacion],Registros[Codigo], "") | Q145: =IF(CRUCE[[#This Row],[TOTAL2]]="", "PENDIENTE", IF(CRUCE[[#This Row],[DIFERENCIA2]]=0, "CUADRADO", IF(CRUCE[[#This Row],[DIFERENCIA2]]>0, "SOBRANTE", "FALTANTE"))) -> PENDIENTE | R145: --- | S145: df20c326-6307-4494-a0aa-43ff6e2a475b
A146: PASILLO 7 | B146: PP-07-005-1 | C146: 8305191 | D146: 17750243080535 | E146: SAP.PROF.LAVAV. LIQ. LIMÓN 5L 4FCO | F146: 19 | G146: CJA | H146: =_xlfn.XLOOKUP(CRUCE[[#This Row],[Ubicacion]],Registros[Ubicacion],Registros[Codigo], "") | I146: =_xlfn.XLOOKUP(CRUCE[[#This Row],[Ubicacion]],Registros[Ubicacion],Registros[Total], "") | J146: =_xlfn.XLOOKUP(CRUCE[[#This Row],[Ubicacion]],Registros[Ubicacion],Registros[UMA], "") | K146: =IF(CRUCE[[#This Row],[TOTAL]]="","",CRUCE[[#This Row],[TOTAL]]-CRUCE[[#This Row],[BULTOS]]) | L146: =IF(CRUCE[[#This Row],[TOTAL]]="", "PENDIENTE", IF(CRUCE[[#This Row],[Diferencia]]=0, "CUADRADO", IF(CRUCE[[#This Row],[Diferencia]]>0, "SOBRANTE", "FALTANTE"))) -> PENDIENTE | M146: =IF(CRUCE[[#This Row],[Diferencia]]="","",IF(CRUCE[[#This Row],[Diferencia]]=0,"OK","RECONTEO")) | N146: =_xlfn.XLOOKUP(CRUCE[[#This Row],[Ubicacion]],Registros[Ubicacion],Registros[Codigo], "") | Q146: =IF(CRUCE[[#This Row],[TOTAL2]]="", "PENDIENTE", IF(CRUCE[[#This Row],[DIFERENCIA2]]=0, "CUADRADO", IF(CRUCE[[#This Row],[DIFERENCIA2]]>0, "SOBRANTE", "FALTANTE"))) -> PENDIENTE | R146: --- | S146: f969bbe5-eb2a-496a-aa23-93cef8995972
A147: PASILLO 7 | B147: PP-07-006-1 | C147: 8305192 | D147: 17750243080542 | E147: SAP.PROF.LAVAV. LIQ. MANZANA 5L 4FCO | F147: 10 | G147: CJA | H147: =_xlfn.XLOOKUP(CRUCE[[#This Row],[Ubicacion]],Registros[Ubicacion],Registros[Codigo], "") | I147: =_xlfn.XLOOKUP(CRUCE[[#This Row],[Ubicacion]],Registros[Ubicacion],Registros[Total], "") | J147: =_xlfn.XLOOKUP(CRUCE[[#This Row],[Ubicacion]],Registros[Ubicacion],Registros[UMA], "") | K147: =IF(CRUCE[[#This Row],[TOTAL]]="","",CRUCE[[#This Row],[TOTAL]]-CRUCE[[#This Row],[BULTOS]]) | L147: =IF(CRUCE[[#This Row],[TOTAL]]="", "PENDIENTE", IF(CRUCE[[#This Row],[Diferencia]]=0, "CUADRADO", IF(CRUCE[[#This Row],[Diferencia]]>0, "SOBRANTE", "FALTANTE"))) -> PENDIENTE | M147: =IF(CRUCE[[#This Row],[Diferencia]]="","",IF(CRUCE[[#This Row],[Diferencia]]=0,"OK","RECONTEO")) | N147: =_xlfn.XLOOKUP(CRUCE[[#This Row],[Ubicacion]],Registros[Ubicacion],Registros[Codigo], "") | Q147: =IF(CRUCE[[#This Row],[TOTAL2]]="", "PENDIENTE", IF(CRUCE[[#This Row],[DIFERENCIA2]]=0, "CUADRADO", IF(CRUCE[[#This Row],[DIFERENCIA2]]>0, "SOBRANTE", "FALTANTE"))) -> PENDIENTE | R147: --- | S147: 8ba70364-7739-4f49-b4c6-a8dc769f9c27
A148: PASILLO 7 | B148: PP-07-007-1 | C148: 8317173 | D148: 17750243077351 | E148: SAP. LIMPIA TODO AB LIMÓN 4.9L FR 4UND | F148: 27 | G148: CJA | H148: =_xlfn.XLOOKUP(CRUCE[[#This Row],[Ubicacion]],Registros[Ubicacion],Registros[Codigo], "") | I148: =_xlfn.XLOOKUP(CRUCE[[#This Row],[Ubicacion]],Registros[Ubicacion],Registros[Total], "") | J148: =_xlfn.XLOOKUP(CRUCE[[#This Row],[Ubicacion]],Registros[Ubicacion],Registros[UMA], "") | K148: =IF(CRUCE[[#This Row],[TOTAL]]="","",CRUCE[[#This Row],[TOTAL]]-CRUCE[[#This Row],[BULTOS]]) | L148: =IF(CRUCE[[#This Row],[TOTAL]]="", "PENDIENTE", IF(CRUCE[[#This Row],[Diferencia]]=0, "CUADRADO", IF(CRUCE[[#This Row],[Diferencia]]>0, "SOBRANTE", "FALTANTE"))) -> PENDIENTE | M148: =IF(CRUCE[[#This Row],[Diferencia]]="","",IF(CRUCE[[#This Row],[Diferencia]]=0,"OK","RECONTEO")) | N148: =_xlfn.XLOOKUP(CRUCE[[#This Row],[Ubicacion]],Registros[Ubicacion],Registros[Codigo], "") | Q148: =IF(CRUCE[[#This Row],[TOTAL2]]="", "PENDIENTE", IF(CRUCE[[#This Row],[DIFERENCIA2]]=0, "CUADRADO", IF(CRUCE[[#This Row],[DIFERENCIA2]]>0, "SOBRANTE", "FALTANTE"))) -> PENDIENTE | R148: --- | S148: 2a102b1d-58d7-40ab-875f-4c7cbc6c41de
A149: PASILLO 7 | B149: PP-07-008-1 | C149: 8300041 | D149: 17750243060643 | E149: LEJIA PROFESIONAL SAPOLIO 4.63% 5KG.4UND | F149: 22 | G149: CJA | H149: =_xlfn.XLOOKUP(CRUCE[[#This Row],[Ubicacion]],Registros[Ubicacion],Registros[Codigo], "") | I149: =_xlfn.XLOOKUP(CRUCE[[#This Row],[Ubicacion]],Registros[Ubicacion],Registros[Total], "") | J149: =_xlfn.XLOOKUP(CRUCE[[#This Row],[Ubicacion]],Registros[Ubicacion],Registros[UMA], "") | K149: =IF(CRUCE[[#This Row],[TOTAL]]="","",CRUCE[[#This Row],[TOTAL]]-CRUCE[[#This Row],[BULTOS]]) | L149: =IF(CRUCE[[#This Row],[TOTAL]]="", "PENDIENTE", IF(CRUCE[[#This Row],[Diferencia]]=0, "CUADRADO", IF(CRUCE[[#This Row],[Diferencia]]>0, "SOBRANTE", "FALTANTE"))) -> PENDIENTE | M149: =IF(CRUCE[[#This Row],[Diferencia]]="","",IF(CRUCE[[#This Row],[Diferencia]]=0,"OK","RECONTEO")) | N149: =_xlfn.XLOOKUP(CRUCE[[#This Row],[Ubicacion]],Registros[Ubicacion],Registros[Codigo], "") | Q149: =IF(CRUCE[[#This Row],[TOTAL2]]="", "PENDIENTE", IF(CRUCE[[#This Row],[DIFERENCIA2]]=0, "CUADRADO", IF(CRUCE[[#This Row],[DIFERENCIA2]]>0, "SOBRANTE", "FALTANTE"))) -> PENDIENTE | R149: --- | S149: 5c06daca-6ab3-41a5-952b-159bf7ab8012
A150: PASILLO 7 | B150: PP-07-009-1 | C150: 8304035 | D150: 17751851020302 | E150: AMOR LIBRE ENJUAGUE BEBE C/A 5L X4 | F150: 15 | G150: CJA | H150: =_xlfn.XLOOKUP(CRUCE[[#This Row],[Ubicacion]],Registros[Ubicacion],Registros[Codigo], "") | I150: =_xlfn.XLOOKUP(CRUCE[[#This Row],[Ubicacion]],Registros[Ubicacion],Registros[Total], "") | J150: =_xlfn.XLOOKUP(CRUCE[[#This Row],[Ubicacion]],Registros[Ubicacion],Registros[UMA], "") | K150: =IF(CRUCE[[#This Row],[TOTAL]]="","",CRUCE[[#This Row],[TOTAL]]-CRUCE[[#This Row],[BULTOS]]) | L150: =IF(CRUCE[[#This Row],[TOTAL]]="", "PENDIENTE", IF(CRUCE[[#This Row],[Diferencia]]=0, "CUADRADO", IF(CRUCE[[#This Row],[Diferencia]]>0, "SOBRANTE", "FALTANTE"))) -> PENDIENTE | M150: =IF(CRUCE[[#This Row],[Diferencia]]="","",IF(CRUCE[[#This Row],[Diferencia]]=0,"OK","RECONTEO")) | N150: =_xlfn.XLOOKUP(CRUCE[[#This Row],[Ubicacion]],Registros[Ubicacion],Registros[Codigo], "") | Q150: =IF(CRUCE[[#This Row],[TOTAL2]]="", "PENDIENTE", IF(CRUCE[[#This Row],[DIFERENCIA2]]=0, "CUADRADO", IF(CRUCE[[#This Row],[DIFERENCIA2]]>0, "SOBRANTE", "FALTANTE"))) -> PENDIENTE | R150: --- | S150: 90a47300-a611-477c-9bec-f63cb4477a04
A151: PASILLO 7 | B151: PP-07-010-1 | C151: 8304034 | D151: 17751851020296 | E151: AMOR LIBRE ENJUAGUE LAVANDA C/A 5L X4 | F151: 22 | G151: CJA | H151: =_xlfn.XLOOKUP(CRUCE[[#This Row],[Ubicacion]],Registros[Ubicacion],Registros[Codigo], "") | I151: =_xlfn.XLOOKUP(CRUCE[[#This Row],[Ubicacion]],Registros[Ubicacion],Registros[Total], "") | J151: =_xlfn.XLOOKUP(CRUCE[[#This Row],[Ubicacion]],Registros[Ubicacion],Registros[UMA], "") | K151: =IF(CRUCE[[#This Row],[TOTAL]]="","",CRUCE[[#This Row],[TOTAL]]-CRUCE[[#This Row],[BULTOS]]) | L151: =IF(CRUCE[[#This Row],[TOTAL]]="", "PENDIENTE", IF(CRUCE[[#This Row],[Diferencia]]=0, "CUADRADO", IF(CRUCE[[#This Row],[Diferencia]]>0, "SOBRANTE", "FALTANTE"))) -> PENDIENTE | M151: =IF(CRUCE[[#This Row],[Diferencia]]="","",IF(CRUCE[[#This Row],[Diferencia]]=0,"OK","RECONTEO")) | N151: =_xlfn.XLOOKUP(CRUCE[[#This Row],[Ubicacion]],Registros[Ubicacion],Registros[Codigo], "") | Q151: =IF(CRUCE[[#This Row],[TOTAL2]]="", "PENDIENTE", IF(CRUCE[[#This Row],[DIFERENCIA2]]=0, "CUADRADO", IF(CRUCE[[#This Row],[DIFERENCIA2]]>0, "SOBRANTE", "FALTANTE"))) -> PENDIENTE | R151: --- | S151: d9f8f839-2f18-4292-8af2-be4b5661f476
A152: PASILLO 7 | B152: PP-07-011-1 | C152: 8304033 | D152: 17751851020289 | E152: AMOR LIBRE ENJUAGUE FLORES C/A/ 5L X 4 | F152: 22 | G152: CJA | H152: =_xlfn.XLOOKUP(CRUCE[[#This Row],[Ubicacion]],Registros[Ubicacion],Registros[Codigo], "") | I152: =_xlfn.XLOOKUP(CRUCE[[#This Row],[Ubicacion]],Registros[Ubicacion],Registros[Total], "") | J152: =_xlfn.XLOOKUP(CRUCE[[#This Row],[Ubicacion]],Registros[Ubicacion],Registros[UMA], "") | K152: =IF(CRUCE[[#This Row],[TOTAL]]="","",CRUCE[[#This Row],[TOTAL]]-CRUCE[[#This Row],[BULTOS]]) | L152: =IF(CRUCE[[#This Row],[TOTAL]]="", "PENDIENTE", IF(CRUCE[[#This Row],[Diferencia]]=0, "CUADRADO", IF(CRUCE[[#This Row],[Diferencia]]>0, "SOBRANTE", "FALTANTE"))) -> PENDIENTE | M152: =IF(CRUCE[[#This Row],[Diferencia]]="","",IF(CRUCE[[#This Row],[Diferencia]]=0,"OK","RECONTEO")) | N152: =_xlfn.XLOOKUP(CRUCE[[#This Row],[Ubicacion]],Registros[Ubicacion],Registros[Codigo], "") | Q152: =IF(CRUCE[[#This Row],[TOTAL2]]="", "PENDIENTE", IF(CRUCE[[#This Row],[DIFERENCIA2]]=0, "CUADRADO", IF(CRUCE[[#This Row],[DIFERENCIA2]]>0, "SOBRANTE", "FALTANTE"))) -> PENDIENTE | R152: --- | S152: 0704705b-b828-4dc8-916f-8cdba5cd5ab9
A153: PASILLO 7 | B153: PP-07-012-1 | C153: 8316108 | D153: 17750243077221 | E153: ESINF. SAPOLIO PROF LIMÓN 5L 4UND | F153: 19 | G153: CJA | H153: =_xlfn.XLOOKUP(CRUCE[[#This Row],[Ubicacion]],Registros[Ubicacion],Registros[Codigo], "") | I153: =_xlfn.XLOOKUP(CRUCE[[#This Row],[Ubicacion]],Registros[Ubicacion],Registros[Total], "") | J153: =_xlfn.XLOOKUP(CRUCE[[#This Row],[Ubicacion]],Registros[Ubicacion],Registros[UMA], "") | K153: =IF(CRUCE[[#This Row],[TOTAL]]="","",CRUCE[[#This Row],[TOTAL]]-CRUCE[[#This Row],[BULTOS]]) | L153: =IF(CRUCE[[#This Row],[TOTAL]]="", "PENDIENTE", IF(CRUCE[[#This Row],[Diferencia]]=0, "CUADRADO", IF(CRUCE[[#This Row],[Diferencia]]>0, "SOBRANTE", "FALTANTE"))) -> PENDIENTE | M153: =IF(CRUCE[[#This Row],[Diferencia]]="","",IF(CRUCE[[#This Row],[Diferencia]]=0,"OK","RECONTEO")) | N153: =_xlfn.XLOOKUP(CRUCE[[#This Row],[Ubicacion]],Registros[Ubicacion],Registros[Codigo], "") | Q153: =IF(CRUCE[[#This Row],[TOTAL2]]="", "PENDIENTE", IF(CRUCE[[#This Row],[DIFERENCIA2]]=0, "CUADRADO", IF(CRUCE[[#This Row],[DIFERENCIA2]]>0, "SOBRANTE", "FALTANTE"))) -> PENDIENTE | R153: --- | S153: b5432d23-b31c-47a8-8ae9-8d50638861b3
... A156: PASILLO 7 | B156: PP-07-015-1 | C156: 8315135 | D156: 17750243060681 | E156: SACAGRASA LIMON SAPOLIO PROF 5L 4UND | F156: 7 | G156: CJA | H156: =_xlfn.XLOOKUP(CRUCE[[#This Row],[Ubicacion]],Registros[Ubicacion],Registros[Codigo], "") | I156: =_xlfn.XLOOKUP(CRUCE[[#This Row],[Ubicacion]],Registros[Ubicacion],Registros[Total], "") | J156: =_xlfn.XLOOKUP(CRUCE[[#This Row],[Ubicacion]],Registros[Ubicacion],Registros[UMA], "") | K156: =IF(CRUCE[[#This Row],[TOTAL]]="","",CRUCE[[#This Row],[TOTAL]]-CRUCE[[#This Row],[BULTOS]]) | L156: =IF(CRUCE[[#This Row],[TOTAL]]="", "PENDIENTE", IF(CRUCE[[#This Row],[Diferencia]]=0, "CUADRADO", IF(CRUCE[[#This Row],[Diferencia]]>0, "SOBRANTE", "FALTANTE"))) -> PENDIENTE | M156: =IF(CRUCE[[#This Row],[Diferencia]]="","",IF(CRUCE[[#This Row],[Diferencia]]=0,"OK","RECONTEO")) | N156: =_xlfn.XLOOKUP(CRUCE[[#This Row],[Ubicacion]],Registros[Ubicacion],Registros[Codigo], "") | Q156: =IF(CRUCE[[#This Row],[TOTAL2]]="", "PENDIENTE", IF(CRUCE[[#This Row],[DIFERENCIA2]]=0, "CUADRADO", IF(CRUCE[[#This Row],[DIFERENCIA2]]>0, "SOBRANTE", "FALTANTE"))) -> PENDIENTE | R156: --- | S156: 96195929-85a7-4256-8527-583df734e49c
A157: PASILLO 7 | B157: PP-07-016-1 | H157: =_xlfn.XLOOKUP(CRUCE[[#This Row],[Ubicacion]],Registros[Ubicacion],Registros[Codigo], "") | I157: =_xlfn.XLOOKUP(CRUCE[[#This Row],[Ubicacion]],Registros[Ubicacion],Registros[Total], "") | J157: =_xlfn.XLOOKUP(CRUCE[[#This Row],[Ubicacion]],Registros[Ubicacion],Registros[UMA], "") | K157: =IF(CRUCE[[#This Row],[TOTAL]]="","",CRUCE[[#This Row],[TOTAL]]-CRUCE[[#This Row],[BULTOS]]) | L157: =IF(CRUCE[[#This Row],[TOTAL]]="", "PENDIENTE", IF(CRUCE[[#This Row],[Diferencia]]=0, "CUADRADO", IF(CRUCE[[#This Row],[Diferencia]]>0, "SOBRANTE", "FALTANTE"))) -> PENDIENTE | M157: =IF(CRUCE[[#This Row],[Diferencia]]="","",IF(CRUCE[[#This Row],[Diferencia]]=0,"OK","RECONTEO")) | N157: =_xlfn.XLOOKUP(CRUCE[[#This Row],[Ubicacion]],Registros[Ubicacion],Registros[Codigo], "") | Q157: =IF(CRUCE[[#This Row],[TOTAL2]]="", "PENDIENTE", IF(CRUCE[[#This Row],[DIFERENCIA2]]=0, "CUADRADO", IF(CRUCE[[#This Row],[DIFERENCIA2]]>0, "SOBRANTE", "FALTANTE"))) -> PENDIENTE | R157: --- | S157: bb56be3c-6511-4a58-bcf9-f6c21b042e47
A158: PASILLO 7 | B158: PP-07-017-1 | C158: 8317171 | D158: 17750243077337 | E158: SAP. LIMPIA TODO AB FLORAL 4.9L FR 4UND | F158: 20 | G158: CJA | H158: =_xlfn.XLOOKUP(CRUCE[[#This Row],[Ubicacion]],Registros[Ubicacion],Registros[Codigo], "") | I158: =_xlfn.XLOOKUP(CRUCE[[#This Row],[Ubicacion]],Registros[Ubicacion],Registros[Total], "") | J158: =_xlfn.XLOOKUP(CRUCE[[#This Row],[Ubicacion]],Registros[Ubicacion],Registros[UMA], "") | K158: =IF(CRUCE[[#This Row],[TOTAL]]="","",CRUCE[[#This Row],[TOTAL]]-CRUCE[[#This Row],[BULTOS]]) | L158: =IF(CRUCE[[#This Row],[TOTAL]]="", "PENDIENTE", IF(CRUCE[[#This Row],[Diferencia]]=0, "CUADRADO", IF(CRUCE[[#This Row],[Diferencia]]>0, "SOBRANTE", "FALTANTE"))) -> PENDIENTE | M158: =IF(CRUCE[[#This Row],[Diferencia]]="","",IF(CRUCE[[#This Row],[Diferencia]]=0,"OK","RECONTEO")) | N158: =_xlfn.XLOOKUP(CRUCE[[#This Row],[Ubicacion]],Registros[Ubicacion],Registros[Codigo], "") | Q158: =IF(CRUCE[[#This Row],[TOTAL2]]="", "PENDIENTE", IF(CRUCE[[#This Row],[DIFERENCIA2]]=0, "CUADRADO", IF(CRUCE[[#This Row],[DIFERENCIA2]]>0, "SOBRANTE", "FALTANTE"))) -> PENDIENTE | R158: --- | S158: 392ca1a3-99a6-41c5-9f90-cfcc51747565
A159: PASILLO 7 | B159: PP-07-018-1 | C159: 8317179 | D159: 17750243077412 | E159: SAP. LIMPIA TODO AB COCO 4.9L FR 4UND | F159: 15 | G159: CJA | H159: =_xlfn.XLOOKUP(CRUCE[[#This Row],[Ubicacion]],Registros[Ubicacion],Registros[Codigo], "") | I159: =_xlfn.XLOOKUP(CRUCE[[#This Row],[Ubicacion]],Registros[Ubicacion],Registros[Total], "") | J159: =_xlfn.XLOOKUP(CRUCE[[#This Row],[Ubicacion]],Registros[Ubicacion],Registros[UMA], "") | K159: =IF(CRUCE[[#This Row],[TOTAL]]="","",CRUCE[[#This Row],[TOTAL]]-CRUCE[[#This Row],[BULTOS]]) | L159: =IF(CRUCE[[#This Row],[TOTAL]]="", "PENDIENTE", IF(CRUCE[[#This Row],[Diferencia]]=0, "CUADRADO", IF(CRUCE[[#This Row],[Diferencia]]>0, "SOBRANTE", "FALTANTE"))) -> PENDIENTE | M159: =IF(CRUCE[[#This Row],[Diferencia]]="","",IF(CRUCE[[#This Row],[Diferencia]]=0,"OK","RECONTEO")) | N159: =_xlfn.XLOOKUP(CRUCE[[#This Row],[Ubicacion]],Registros[Ubicacion],Registros[Codigo], "") | Q159: =IF(CRUCE[[#This Row],[TOTAL2]]="", "PENDIENTE", IF(CRUCE[[#This Row],[DIFERENCIA2]]=0, "CUADRADO", IF(CRUCE[[#This Row],[DIFERENCIA2]]>0, "SOBRANTE", "FALTANTE"))) -> PENDIENTE | R159: --- | S159: 18bd4a05-ca34-47b1-90c4-2553fcc41ee3
A160: PASILLO 7 | B160: PP-07-019-1 | C160: 8317170 | D160: 17750243077320 | E160: SAP. LIMPIA TODO AB LAVANDA 4.9L FR 4UND | F160: 2 | G160: CJA | H160: =_xlfn.XLOOKUP(CRUCE[[#This Row],[Ubicacion]],Registros[Ubicacion],Registros[Codigo], "") | I160: =_xlfn.XLOOKUP(CRUCE[[#This Row],[Ubicacion]],Registros[Ubicacion],Registros[Total], "") | J160: =_xlfn.XLOOKUP(CRUCE[[#This Row],[Ubicacion]],Registros[Ubicacion],Registros[UMA], "") | K160: =IF(CRUCE[[#This Row],[TOTAL]]="","",CRUCE[[#This Row],[TOTAL]]-CRUCE[[#This Row],[BULTOS]]) | L160: =IF(CRUCE[[#This Row],[TOTAL]]="", "PENDIENTE", IF(CRUCE[[#This Row],[Diferencia]]=0, "CUADRADO", IF(CRUCE[[#This Row],[Diferencia]]>0, "SOBRANTE", "FALTANTE"))) -> PENDIENTE | M160: =IF(CRUCE[[#This Row],[Diferencia]]="","",IF(CRUCE[[#This Row],[Diferencia]]=0,"OK","RECONTEO")) | N160: =_xlfn.XLOOKUP(CRUCE[[#This Row],[Ubicacion]],Registros[Ubicacion],Registros[Codigo], "") | Q160: =IF(CRUCE[[#This Row],[TOTAL2]]="", "PENDIENTE", IF(CRUCE[[#This Row],[DIFERENCIA2]]=0, "CUADRADO", IF(CRUCE[[#This Row],[DIFERENCIA2]]>0, "SOBRANTE", "FALTANTE"))) -> PENDIENTE | R160: --- | S160: 0d7892b8-9300-40c3-8384-3f34644711cc
A161: PASILLO 7 | B161: PP-07-020-1 | C161: 8317172 | D161: 17750243077344 | E161: SAP. LIMPIA TODO AB BEBÉ 4.9L FR 4UND | F161: 16 | G161: CJA | H161: =_xlfn.XLOOKUP(CRUCE[[#This Row],[Ubicacion]],Registros[Ubicacion],Registros[Codigo], "") | I161: =_xlfn.XLOOKUP(CRUCE[[#This Row],[Ubicacion]],Registros[Ubicacion],Registros[Total], "") | J161: =_xlfn.XLOOKUP(CRUCE[[#This Row],[Ubicacion]],Registros[Ubicacion],Registros[UMA], "") | K161: =IF(CRUCE[[#This Row],[TOTAL]]="","",CRUCE[[#This Row],[TOTAL]]-CRUCE[[#This Row],[BULTOS]]) | L161: =IF(CRUCE[[#This Row],[TOTAL]]="", "PENDIENTE", IF(CRUCE[[#This Row],[Diferencia]]=0, "CUADRADO", IF(CRUCE[[#This Row],[Diferencia]]>0, "SOBRANTE", "FALTANTE"))) -> PENDIENTE | M161: =IF(CRUCE[[#This Row],[Diferencia]]="","",IF(CRUCE[[#This Row],[Diferencia]]=0,"OK","RECONTEO")) | N161: =_xlfn.XLOOKUP(CRUCE[[#This Row],[Ubicacion]],Registros[Ubicacion],Registros[Codigo], "") | Q161: =IF(CRUCE[[#This Row],[TOTAL2]]="", "PENDIENTE", IF(CRUCE[[#This Row],[DIFERENCIA2]]=0, "CUADRADO", IF(CRUCE[[#This Row],[DIFERENCIA2]]>0, "SOBRANTE", "FALTANTE"))) -> PENDIENTE | R161: --- | S161: f11fc19a-5ee5-4c87-8570-573d2e58dd8c
A162: PASILLO 7 | B162: PP-07-021-1 | H162: =_xlfn.XLOOKUP(CRUCE[[#This Row],[Ubicacion]],Registros[Ubicacion],Registros[Codigo], "") | I162: =_xlfn.XLOOKUP(CRUCE[[#This Row],[Ubicacion]],Registros[Ubicacion],Registros[Total], "") | J162: =_xlfn.XLOOKUP(CRUCE[[#This Row],[Ubicacion]],Registros[Ubicacion],Registros[UMA], "") | K162: =IF(CRUCE[[#This Row],[TOTAL]]="","",CRUCE[[#This Row],[TOTAL]]-CRUCE[[#This Row],[BULTOS]]) | L162: =IF(CRUCE[[#This Row],[TOTAL]]="", "PENDIENTE", IF(CRUCE[[#This Row],[Diferencia]]=0, "CUADRADO", IF(CRUCE[[#This Row],[Diferencia]]>0, "SOBRANTE", "FALTANTE"))) -> PENDIENTE | M162: =IF(CRUCE[[#This Row],[Diferencia]]="","",IF(CRUCE[[#This Row],[Diferencia]]=0,"OK","RECONTEO")) | N162: =_xlfn.XLOOKUP(CRUCE[[#This Row],[Ubicacion]],Registros[Ubicacion],Registros[Codigo], "") | Q162: =IF(CRUCE[[#This Row],[TOTAL2]]="", "PENDIENTE", IF(CRUCE[[#This Row],[DIFERENCIA2]]=0, "CUADRADO", IF(CRUCE[[#This Row],[DIFERENCIA2]]>0, "SOBRANTE", "FALTANTE"))) -> PENDIENTE | R162: --- | S162: 1849875f-e8fb-4c1a-a849-5a6c2457f020
A163: PASILLO 7 | B163: PP-07-022-1 | H163: =_xlfn.XLOOKUP(CRUCE[[#This Row],[Ubicacion]],Registros[Ubicacion],Registros[Codigo], "") | I163: =_xlfn.XLOOKUP(CRUCE[[#This Row],[Ubicacion]],Registros[Ubicacion],Registros[Total], "") | J163: =_xlfn.XLOOKUP(CRUCE[[#This Row],[Ubicacion]],Registros[Ubicacion],Registros[UMA], "") | K163: =IF(CRUCE[[#This Row],[TOTAL]]="","",CRUCE[[#This Row],[TOTAL]]-CRUCE[[#This Row],[BULTOS]]) | L163: =IF(CRUCE[[#This Row],[TOTAL]]="", "PENDIENTE", IF(CRUCE[[#This Row],[Diferencia]]=0, "CUADRADO", IF(CRUCE[[#This Row],[Diferencia]]>0, "SOBRANTE", "FALTANTE"))) -> PENDIENTE | M163: =IF(CRUCE[[#This Row],[Diferencia]]="","",IF(CRUCE[[#This Row],[Diferencia]]=0,"OK","RECONTEO")) | N163: =_xlfn.XLOOKUP(CRUCE[[#This Row],[Ubicacion]],Registros[Ubicacion],Registros[Codigo], "") | Q163: =IF(CRUCE[[#This Row],[TOTAL2]]="", "PENDIENTE", IF(CRUCE[[#This Row],[DIFERENCIA2]]=0, "CUADRADO", IF(CRUCE[[#This Row],[DIFERENCIA2]]>0, "SOBRANTE", "FALTANTE"))) -> PENDIENTE | R163: --- | S163: a510be32-7a75-493c-ae0f-033092198706
A164: PASILLO 7 | B164: PP-07-023-1 | H164: =_xlfn.XLOOKUP(CRUCE[[#This Row],[Ubicacion]],Registros[Ubicacion],Registros[Codigo], "") | I164: =_xlfn.XLOOKUP(CRUCE[[#This Row],[Ubicacion]],Registros[Ubicacion],Registros[Total], "") | J164: =_xlfn.XLOOKUP(CRUCE[[#This Row],[Ubicacion]],Registros[Ubicacion],Registros[UMA], "") | K164: =IF(CRUCE[[#This Row],[TOTAL]]="","",CRUCE[[#This Row],[TOTAL]]-CRUCE[[#This Row],[BULTOS]]) | L164: =IF(CRUCE[[#This Row],[TOTAL]]="", "PENDIENTE", IF(CRUCE[[#This Row],[Diferencia]]=0, "CUADRADO", IF(CRUCE[[#This Row],[Diferencia]]>0, "SOBRANTE", "FALTANTE"))) -> PENDIENTE | M164: =IF(CRUCE[[#This Row],[Diferencia]]="","",IF(CRUCE[[#This Row],[Diferencia]]=0,"OK","RECONTEO")) | N164: =_xlfn.XLOOKUP(CRUCE[[#This Row],[Ubicacion]],Registros[Ubicacion],Registros[Codigo], "") | Q164: =IF(CRUCE[[#This Row],[TOTAL2]]="", "PENDIENTE", IF(CRUCE[[#This Row],[DIFERENCIA2]]=0, "CUADRADO", IF(CRUCE[[#This Row],[DIFERENCIA2]]>0, "SOBRANTE", "FALTANTE"))) -> PENDIENTE | R164: --- | S164: 5acfb4db-9d27-4e7f-aef5-b19764f82340
A165: PASILLO 7 | B165: PP-07-024-1 | H165: =_xlfn.XLOOKUP(CRUCE[[#This Row],[Ubicacion]],Registros[Ubicacion],Registros[Codigo], "") | I165: =_xlfn.XLOOKUP(CRUCE[[#This Row],[Ubicacion]],Registros[Ubicacion],Registros[Total], "") | J165: =_xlfn.XLOOKUP(CRUCE[[#This Row],[Ubicacion]],Registros[Ubicacion],Registros[UMA], "") | K165: =IF(CRUCE[[#This Row],[TOTAL]]="","",CRUCE[[#This Row],[TOTAL]]-CRUCE[[#This Row],[BULTOS]]) | L165: =IF(CRUCE[[#This Row],[TOTAL]]="", "PENDIENTE", IF(CRUCE[[#This Row],[Diferencia]]=0, "CUADRADO", IF(CRUCE[[#This Row],[Diferencia]]>0, "SOBRANTE", "FALTANTE"))) -> PENDIENTE | M165: =IF(CRUCE[[#This Row],[Diferencia]]="","",IF(CRUCE[[#This Row],[Diferencia]]=0,"OK","RECONTEO")) | N165: =_xlfn.XLOOKUP(CRUCE[[#This Row],[Ubicacion]],Registros[Ubicacion],Registros[Codigo], "") | Q165: =IF(CRUCE[[#This Row],[TOTAL2]]="", "PENDIENTE", IF(CRUCE[[#This Row],[DIFERENCIA2]]=0, "CUADRADO", IF(CRUCE[[#This Row],[DIFERENCIA2]]>0, "SOBRANTE", "FALTANTE"))) -> PENDIENTE | R165: --- | S165: 86afc407-8df5-4090-8949-90641feeffbf
A166: PASILLO 7 | B166: PP-07-025-1 | H166: =_xlfn.XLOOKUP(CRUCE[[#This Row],[Ubicacion]],Registros[Ubicacion],Registros[Codigo], "") | I166: =_xlfn.XLOOKUP(CRUCE[[#This Row],[Ubicacion]],Registros[Ubicacion],Registros[Total], "") | J166: =_xlfn.XLOOKUP(CRUCE[[#This Row],[Ubicacion]],Registros[Ubicacion],Registros[UMA], "") | K166: =IF(CRUCE[[#This Row],[TOTAL]]="","",CRUCE[[#This Row],[TOTAL]]-CRUCE[[#This Row],[BULTOS]]) | L166: =IF(CRUCE[[#This Row],[TOTAL]]="", "PENDIENTE", IF(CRUCE[[#This Row],[Diferencia]]=0, "CUADRADO", IF(CRUCE[[#This Row],[Diferencia]]>0, "SOBRANTE", "FALTANTE"))) -> PENDIENTE | M166: =IF(CRUCE[[#This Row],[Diferencia]]="","",IF(CRUCE[[#This Row],[Diferencia]]=0,"OK","RECONTEO")) | N166: =_xlfn.XLOOKUP(CRUCE[[#This Row],[Ubicacion]],Registros[Ubicacion],Registros[Codigo], "") | Q166: =IF(CRUCE[[#This Row],[TOTAL2]]="", "PENDIENTE", IF(CRUCE[[#This Row],[DIFERENCIA2]]=0, "CUADRADO", IF(CRUCE[[#This Row],[DIFERENCIA2]]>0, "SOBRANTE", "FALTANTE"))) -> PENDIENTE | R166: --- | S166: 5f3d7688-e61a-454c-822a-aaba0d421823
A167: PASILLO 7 | B167: PP-07-026-1 | C167: 8300117 | D167: 17750243082287 | E167: LEJIA SAPOLIO CLORO B 4.8 KG 4UND | F167: 9 | G167: CJA | H167: =_xlfn.XLOOKUP(CRUCE[[#This Row],[Ubicacion]],Registros[Ubicacion],Registros[Codigo], "") | I167: =_xlfn.XLOOKUP(CRUCE[[#This Row],[Ubicacion]],Registros[Ubicacion],Registros[Total], "") | J167: =_xlfn.XLOOKUP(CRUCE[[#This Row],[Ubicacion]],Registros[Ubicacion],Registros[UMA], "") | K167: =IF(CRUCE[[#This Row],[TOTAL]]="","",CRUCE[[#This Row],[TOTAL]]-CRUCE[[#This Row],[BULTOS]]) | L167: =IF(CRUCE[[#This Row],[TOTAL]]="", "PENDIENTE", IF(CRUCE[[#This Row],[Diferencia]]=0, "CUADRADO", IF(CRUCE[[#This Row],[Diferencia]]>0, "SOBRANTE", "FALTANTE"))) -> PENDIENTE | M167: =IF(CRUCE[[#This Row],[Diferencia]]="","",IF(CRUCE[[#This Row],[Diferencia]]=0,"OK","RECONTEO")) | N167: =_xlfn.XLOOKUP(CRUCE[[#This Row],[Ubicacion]],Registros[Ubicacion],Registros[Codigo], "") | Q167: =IF(CRUCE[[#This Row],[TOTAL2]]="", "PENDIENTE", IF(CRUCE[[#This Row],[DIFERENCIA2]]=0, "CUADRADO", IF(CRUCE[[#This Row],[DIFERENCIA2]]>0, "SOBRANTE", "FALTANTE"))) -> PENDIENTE | R167: --- | S167: 3515d5f2-5f45-4869-a6ba-b59c697cd8e6
A168: PASILLO 7 | B168: PP-07-027-1 | C168: 8300117 | D168: 17750243082287 | E168: LEJIA SAPOLIO CLORO B 4.8 KG 4UND | F168: 9 | G168: CJA | H168: =_xlfn.XLOOKUP(CRUCE[[#This Row],[Ubicacion]],Registros[Ubicacion],Registros[Codigo], "") | I168: =_xlfn.XLOOKUP(CRUCE[[#This Row],[Ubicacion]],Registros[Ubicacion],Registros[Total], "") | J168: =_xlfn.XLOOKUP(CRUCE[[#This Row],[Ubicacion]],Registros[Ubicacion],Registros[UMA], "") | K168: =IF(CRUCE[[#This Row],[TOTAL]]="","",CRUCE[[#This Row],[TOTAL]]-CRUCE[[#This Row],[BULTOS]]) | L168: =IF(CRUCE[[#This Row],[TOTAL]]="", "PENDIENTE", IF(CRUCE[[#This Row],[Diferencia]]=0, "CUADRADO", IF(CRUCE[[#This Row],[Diferencia]]>0, "SOBRANTE", "FALTANTE"))) -> PENDIENTE | M168: =IF(CRUCE[[#This Row],[Diferencia]]="","",IF(CRUCE[[#This Row],[Diferencia]]=0,"OK","RECONTEO")) | N168: =_xlfn.XLOOKUP(CRUCE[[#This Row],[Ubicacion]],Registros[Ubicacion],Registros[Codigo], "") | Q168: =IF(CRUCE[[#This Row],[TOTAL2]]="", "PENDIENTE", IF(CRUCE[[#This Row],[DIFERENCIA2]]=0, "CUADRADO", IF(CRUCE[[#This Row],[DIFERENCIA2]]>0, "SOBRANTE", "FALTANTE"))) -> PENDIENTE | R168: --- | S168: 2cf0c525-2934-4f86-9f8a-f2e4a7c277e5
A169: PASILLO 7 | B169: PP-07-028-1 | C169: 9350416 | D169: 17750243083543 | E169: SUAV. BOLIVAR BEBESYNINOS 2800ML 6FCO NV | F169: 3 | G169: CJA | H169: =_xlfn.XLOOKUP(CRUCE[[#This Row],[Ubicacion]],Registros[Ubicacion],Registros[Codigo], "") | I169: =_xlfn.XLOOKUP(CRUCE[[#This Row],[Ubicacion]],Registros[Ubicacion],Registros[Total], "") | J169: =_xlfn.XLOOKUP(CRUCE[[#This Row],[Ubicacion]],Registros[Ubicacion],Registros[UMA], "") | K169: =IF(CRUCE[[#This Row],[TOTAL]]="","",CRUCE[[#This Row],[TOTAL]]-CRUCE[[#This Row],[BULTOS]]) | L169: =IF(CRUCE[[#This Row],[TOTAL]]="", "PENDIENTE", IF(CRUCE[[#This Row],[Diferencia]]=0, "CUADRADO", IF(CRUCE[[#This Row],[Diferencia]]>0, "SOBRANTE", "FALTANTE"))) -> PENDIENTE | M169: =IF(CRUCE[[#This Row],[Diferencia]]="","",IF(CRUCE[[#This Row],[Diferencia]]=0,"OK","RECONTEO")) | N169: =_xlfn.XLOOKUP(CRUCE[[#This Row],[Ubicacion]],Registros[Ubicacion],Registros[Codigo], "") | Q169: =IF(CRUCE[[#This Row],[TOTAL2]]="", "PENDIENTE", IF(CRUCE[[#This Row],[DIFERENCIA2]]=0, "CUADRADO", IF(CRUCE[[#This Row],[DIFERENCIA2]]>0, "SOBRANTE", "FALTANTE"))) -> PENDIENTE | R169: --- | S169: 01ba9d0a-a06e-423c-9110-c8a2b96b2294
A170: PASILLO 7 | B170: PP-07-030-1 | C170: 9350382 | D170: 17750243059883 | E170: SUAV. BOLIVAR BEBE 2800ML 6FCO | F170: 7 | G170: CJA | H170: =_xlfn.XLOOKUP(CRUCE[[#This Row],[Ubicacion]],Registros[Ubicacion],Registros[Codigo], "") | I170: =_xlfn.XLOOKUP(CRUCE[[#This Row],[Ubicacion]],Registros[Ubicacion],Registros[Total], "") | J170: =_xlfn.XLOOKUP(CRUCE[[#This Row],[Ubicacion]],Registros[Ubicacion],Registros[UMA], "") | K170: =IF(CRUCE[[#This Row],[TOTAL]]="","",CRUCE[[#This Row],[TOTAL]]-CRUCE[[#This Row],[BULTOS]]) | L170: =IF(CRUCE[[#This Row],[TOTAL]]="", "PENDIENTE", IF(CRUCE[[#This Row],[Diferencia]]=0, "CUADRADO", IF(CRUCE[[#This Row],[Diferencia]]>0, "SOBRANTE", "FALTANTE"))) -> PENDIENTE | M170: =IF(CRUCE[[#This Row],[Diferencia]]="","",IF(CRUCE[[#This Row],[Diferencia]]=0,"OK","RECONTEO")) | N170: =_xlfn.XLOOKUP(CRUCE[[#This Row],[Ubicacion]],Registros[Ubicacion],Registros[Codigo], "") | Q170: =IF(CRUCE[[#This Row],[TOTAL2]]="", "PENDIENTE", IF(CRUCE[[#This Row],[DIFERENCIA2]]=0, "CUADRADO", IF(CRUCE[[#This Row],[DIFERENCIA2]]>0, "SOBRANTE", "FALTANTE"))) -> PENDIENTE | R170: --- | S170: efcef1a6-540b-4524-b645-617ed6489f10
A171: PASILLO 7 | B171: PP-07-031-1 | C171: 9350411 | D171: 17750243083475 | E171: SUA.BOL. FLORAL 2.8L.6FCO | F171: 7 | G171: CJA | H171: =_xlfn.XLOOKUP(CRUCE[[#This Row],[Ubicacion]],Registros[Ubicacion],Registros[Codigo], "") | I171: =_xlfn.XLOOKUP(CRUCE[[#This Row],[Ubicacion]],Registros[Ubicacion],Registros[Total], "") | J171: =_xlfn.XLOOKUP(CRUCE[[#This Row],[Ubicacion]],Registros[Ubicacion],Registros[UMA], "") | K171: =IF(CRUCE[[#This Row],[TOTAL]]="","",CRUCE[[#This Row],[TOTAL]]-CRUCE[[#This Row],[BULTOS]]) | L171: =IF(CRUCE[[#This Row],[TOTAL]]="", "PENDIENTE", IF(CRUCE[[#This Row],[Diferencia]]=0, "CUADRADO", IF(CRUCE[[#This Row],[Diferencia]]>0, "SOBRANTE", "FALTANTE"))) -> PENDIENTE | M171: =IF(CRUCE[[#This Row],[Diferencia]]="","",IF(CRUCE[[#This Row],[Diferencia]]=0,"OK","RECONTEO")) | N171: =_xlfn.XLOOKUP(CRUCE[[#This Row],[Ubicacion]],Registros[Ubicacion],Registros[Codigo], "") | Q171: =IF(CRUCE[[#This Row],[TOTAL2]]="", "PENDIENTE", IF(CRUCE[[#This Row],[DIFERENCIA2]]=0, "CUADRADO", IF(CRUCE[[#This Row],[DIFERENCIA2]]>0, "SOBRANTE", "FALTANTE"))) -> PENDIENTE | R171: --- | S171: def98c5d-a50d-4871-8994-ba1091a24193
A172: PASILLO 7 | B172: PP-07-032-1 | C172: 9350414 | D172: 17750243083529 | E172: SUAVI. BOLIV PLUS.LAV 2.8L 6FCO NV | F172: 22 | G172: CJA | H172: =_xlfn.XLOOKUP(CRUCE[[#This Row],[Ubicacion]],Registros[Ubicacion],Registros[Codigo], "") | I172: =_xlfn.XLOOKUP(CRUCE[[#This Row],[Ubicacion]],Registros[Ubicacion],Registros[Total], "") | J172: =_xlfn.XLOOKUP(CRUCE[[#This Row],[Ubicacion]],Registros[Ubicacion],Registros[UMA], "") | K172: =IF(CRUCE[[#This Row],[TOTAL]]="","",CRUCE[[#This Row],[TOTAL]]-CRUCE[[#This Row],[BULTOS]]) | L172: =IF(CRUCE[[#This Row],[TOTAL]]="", "PENDIENTE", IF(CRUCE[[#This Row],[Diferencia]]=0, "CUADRADO", IF(CRUCE[[#This Row],[Diferencia]]>0, "SOBRANTE", "FALTANTE"))) -> PENDIENTE | M172: =IF(CRUCE[[#This Row],[Diferencia]]="","",IF(CRUCE[[#This Row],[Diferencia]]=0,"OK","RECONTEO")) | N172: =_xlfn.XLOOKUP(CRUCE[[#This Row],[Ubicacion]],Registros[Ubicacion],Registros[Codigo], "") | Q172: =IF(CRUCE[[#This Row],[TOTAL2]]="", "PENDIENTE", IF(CRUCE[[#This Row],[DIFERENCIA2]]=0, "CUADRADO", IF(CRUCE[[#This Row],[DIFERENCIA2]]>0, "SOBRANTE", "FALTANTE"))) -> PENDIENTE | R172: --- | S172: 5b42493f-2bd8-4c92-8663-1b908d485e7f
A173: PASILLO 7 | B173: PP-07-033-1 | C173: 9350415 | D173: 17750243083536 | E173: SUAVI. BOLIV PLUS.ORQ 2.8L 6FCO NV | F173: 21 | G173: CJA | H173: =_xlfn.XLOOKUP(CRUCE[[#This Row],[Ubicacion]],Registros[Ubicacion],Registros[Codigo], "") | I173: =_xlfn.XLOOKUP(CRUCE[[#This Row],[Ubicacion]],Registros[Ubicacion],Registros[Total], "") | J173: =_xlfn.XLOOKUP(CRUCE[[#This Row],[Ubicacion]],Registros[Ubicacion],Registros[UMA], "") | K173: =IF(CRUCE[[#This Row],[TOTAL]]="","",CRUCE[[#This Row],[TOTAL]]-CRUCE[[#This Row],[BULTOS]]) | L173: =IF(CRUCE[[#This Row],[TOTAL]]="", "PENDIENTE", IF(CRUCE[[#This Row],[Diferencia]]=0, "CUADRADO", IF(CRUCE[[#This Row],[Diferencia]]>0, "SOBRANTE", "FALTANTE"))) -> PENDIENTE | M173: =IF(CRUCE[[#This Row],[Diferencia]]="","",IF(CRUCE[[#This Row],[Diferencia]]=0,"OK","RECONTEO")) | N173: =_xlfn.XLOOKUP(CRUCE[[#This Row],[Ubicacion]],Registros[Ubicacion],Registros[Codigo], "") | Q173: =IF(CRUCE[[#This Row],[TOTAL2]]="", "PENDIENTE", IF(CRUCE[[#This Row],[DIFERENCIA2]]=0, "CUADRADO", IF(CRUCE[[#This Row],[DIFERENCIA2]]>0, "SOBRANTE", "FALTANTE"))) -> PENDIENTE | R173: --- | S173: 4dd0f789-4f9d-4450-ae4c-77768e9e6592
A174: PASILLO 7 | B174: PP-07-034-1 | C174: 9350397 | D174: 17750243072042 | E174: SUA.BOLIV. AROMA ACTIVO REVIVE 2.8L.6FCO | F174: 8 | G174: CJA | H174: =_xlfn.XLOOKUP(CRUCE[[#This Row],[Ubicacion]],Registros[Ubicacion],Registros[Codigo], "") | I174: =_xlfn.XLOOKUP(CRUCE[[#This Row],[Ubicacion]],Registros[Ubicacion],Registros[Total], "") | J174: =_xlfn.XLOOKUP(CRUCE[[#This Row],[Ubicacion]],Registros[Ubicacion],Registros[UMA], "") | K174: =IF(CRUCE[[#This Row],[TOTAL]]="","",CRUCE[[#This Row],[TOTAL]]-CRUCE[[#This Row],[BULTOS]]) | L174: =IF(CRUCE[[#This Row],[TOTAL]]="", "PENDIENTE", IF(CRUCE[[#This Row],[Diferencia]]=0, "CUADRADO", IF(CRUCE[[#This Row],[Diferencia]]>0, "SOBRANTE", "FALTANTE"))) -> PENDIENTE | M174: =IF(CRUCE[[#This Row],[Diferencia]]="","",IF(CRUCE[[#This Row],[Diferencia]]=0,"OK","RECONTEO")) | N174: =_xlfn.XLOOKUP(CRUCE[[#This Row],[Ubicacion]],Registros[Ubicacion],Registros[Codigo], "") | Q174: =IF(CRUCE[[#This Row],[TOTAL2]]="", "PENDIENTE", IF(CRUCE[[#This Row],[DIFERENCIA2]]=0, "CUADRADO", IF(CRUCE[[#This Row],[DIFERENCIA2]]>0, "SOBRANTE", "FALTANTE"))) -> PENDIENTE | R174: --- | S174: b53215dc-202e-4134-9bc0-efc19e316e4d
A175: PASILLO 7 | B175: PP-07-035-1 | C175: 8317216 | D175: 17750243084533 | E175: LIMP. SAPOLIO PROF LAVANDA 4.2L 4UND | F175: 23 | G175: CJA | H175: =_xlfn.XLOOKUP(CRUCE[[#This Row],[Ubicacion]],Registros[Ubicacion],Registros[Codigo], "") | I175: =_xlfn.XLOOKUP(CRUCE[[#This Row],[Ubicacion]],Registros[Ubicacion],Registros[Total], "") | J175: =_xlfn.XLOOKUP(CRUCE[[#This Row],[Ubicacion]],Registros[Ubicacion],Registros[UMA], "") | K175: =IF(CRUCE[[#This Row],[TOTAL]]="","",CRUCE[[#This Row],[TOTAL]]-CRUCE[[#This Row],[BULTOS]]) | L175: =IF(CRUCE[[#This Row],[TOTAL]]="", "PENDIENTE", IF(CRUCE[[#This Row],[Diferencia]]=0, "CUADRADO", IF(CRUCE[[#This Row],[Diferencia]]>0, "SOBRANTE", "FALTANTE"))) -> PENDIENTE | M175: =IF(CRUCE[[#This Row],[Diferencia]]="","",IF(CRUCE[[#This Row],[Diferencia]]=0,"OK","RECONTEO")) | N175: =_xlfn.XLOOKUP(CRUCE[[#This Row],[Ubicacion]],Registros[Ubicacion],Registros[Codigo], "") | Q175: =IF(CRUCE[[#This Row],[TOTAL2]]="", "PENDIENTE", IF(CRUCE[[#This Row],[DIFERENCIA2]]=0, "CUADRADO", IF(CRUCE[[#This Row],[DIFERENCIA2]]>0, "SOBRANTE", "FALTANTE"))) -> PENDIENTE | R175: --- | S175: a0979642-a708-4b71-a3b4-05b66f31a8e0
A176: PASILLO 7 | B176: PP-07-036-1 | C176: 8317216 | D176: 17750243084533 | E176: LIMP. SAPOLIO PROF LAVANDA 4.2L 4UND | F176: 23 | G176: CJA | H176: =_xlfn.XLOOKUP(CRUCE[[#This Row],[Ubicacion]],Registros[Ubicacion],Registros[Codigo], "") | I176: =_xlfn.XLOOKUP(CRUCE[[#This Row],[Ubicacion]],Registros[Ubicacion],Registros[Total], "") | J176: =_xlfn.XLOOKUP(CRUCE[[#This Row],[Ubicacion]],Registros[Ubicacion],Registros[UMA], "") | K176: =IF(CRUCE[[#This Row],[TOTAL]]="","",CRUCE[[#This Row],[TOTAL]]-CRUCE[[#This Row],[BULTOS]]) | L176: =IF(CRUCE[[#This Row],[TOTAL]]="", "PENDIENTE", IF(CRUCE[[#This Row],[Diferencia]]=0, "CUADRADO", IF(CRUCE[[#This Row],[Diferencia]]>0, "SOBRANTE", "FALTANTE"))) -> PENDIENTE | M176: =IF(CRUCE[[#This Row],[Diferencia]]="","",IF(CRUCE[[#This Row],[Diferencia]]=0,"OK","RECONTEO")) | N176: =_xlfn.XLOOKUP(CRUCE[[#This Row],[Ubicacion]],Registros[Ubicacion],Registros[Codigo], "") | Q176: =IF(CRUCE[[#This Row],[TOTAL2]]="", "PENDIENTE", IF(CRUCE[[#This Row],[DIFERENCIA2]]=0, "CUADRADO", IF(CRUCE[[#This Row],[DIFERENCIA2]]>0, "SOBRANTE", "FALTANTE"))) -> PENDIENTE | R176: --- | S176: cbde5c09-5113-45d4-bd51-3c7000af9532
A177: PASILLO 7 | B177: PP-07-037-1 | C177: 8317215 | D177: 17750243084526 | E177: LIMP. SAPOLIO PROF COCO 4.2L 4UND | F177: 10 | G177: CJA | H177: =_xlfn.XLOOKUP(CRUCE[[#This Row],[Ubicacion]],Registros[Ubicacion],Registros[Codigo], "") | I177: =_xlfn.XLOOKUP(CRUCE[[#This Row],[Ubicacion]],Registros[Ubicacion],Registros[Total], "") | J177: =_xlfn.XLOOKUP(CRUCE[[#This Row],[Ubicacion]],Registros[Ubicacion],Registros[UMA], "") | K177: =IF(CRUCE[[#This Row],[TOTAL]]="","",CRUCE[[#This Row],[TOTAL]]-CRUCE[[#This Row],[BULTOS]]) | L177: =IF(CRUCE[[#This Row],[TOTAL]]="", "PENDIENTE", IF(CRUCE[[#This Row],[Diferencia]]=0, "CUADRADO", IF(CRUCE[[#This Row],[Diferencia]]>0, "SOBRANTE", "FALTANTE"))) -> PENDIENTE | M177: =IF(CRUCE[[#This Row],[Diferencia]]="","",IF(CRUCE[[#This Row],[Diferencia]]=0,"OK","RECONTEO")) | N177: =_xlfn.XLOOKUP(CRUCE[[#This Row],[Ubicacion]],Registros[Ubicacion],Registros[Codigo], "") | Q177: =IF(CRUCE[[#This Row],[TOTAL2]]="", "PENDIENTE", IF(CRUCE[[#This Row],[DIFERENCIA2]]=0, "CUADRADO", IF(CRUCE[[#This Row],[DIFERENCIA2]]>0, "SOBRANTE", "FALTANTE"))) -> PENDIENTE | R177: --- | S177: 5f93029e-a8a6-4ba9-8061-fd19fd428810
A178: PASILLO 7 | B178: PP-07-038-1 | C178: 8317213 | D178: 17750243084502 | E178: LIMP. SAPOLIO PROF FLORAL 4.2L 4UND | F178: 5 | G178: CJA | H178: =_xlfn.XLOOKUP(CRUCE[[#This Row],[Ubicacion]],Registros[Ubicacion],Registros[Codigo], "") | I178: =_xlfn.XLOOKUP(CRUCE[[#This Row],[Ubicacion]],Registros[Ubicacion],Registros[Total], "") | J178: =_xlfn.XLOOKUP(CRUCE[[#This Row],[Ubicacion]],Registros[Ubicacion],Registros[UMA], "") | K178: =IF(CRUCE[[#This Row],[TOTAL]]="","",CRUCE[[#This Row],[TOTAL]]-CRUCE[[#This Row],[BULTOS]]) | L178: =IF(CRUCE[[#This Row],[TOTAL]]="", "PENDIENTE", IF(CRUCE[[#This Row],[Diferencia]]=0, "CUADRADO", IF(CRUCE[[#This Row],[Diferencia]]>0, "SOBRANTE", "FALTANTE"))) -> PENDIENTE | M178: =IF(CRUCE[[#This Row],[Diferencia]]="","",IF(CRUCE[[#This Row],[Diferencia]]=0,"OK","RECONTEO")) | N178: =_xlfn.XLOOKUP(CRUCE[[#This Row],[Ubicacion]],Registros[Ubicacion],Registros[Codigo], "") | Q178: =IF(CRUCE[[#This Row],[TOTAL2]]="", "PENDIENTE", IF(CRUCE[[#This Row],[DIFERENCIA2]]=0, "CUADRADO", IF(CRUCE[[#This Row],[DIFERENCIA2]]>0, "SOBRANTE", "FALTANTE"))) -> PENDIENTE | R178: --- | S178: 65a102e2-0e3a-46c5-b0ad-597502d55c75
... A182: PASILLO 7 | B182: PP-07-042-1 | C182: 8305332 | D182: 17750243084441 | E182: SAP.PROF.LAVAV. LIQ. LIMÓN 4L 4FCO | F182: 20 | G182: CJA | H182: =_xlfn.XLOOKUP(CRUCE[[#This Row],[Ubicacion]],Registros[Ubicacion],Registros[Codigo], "") | I182: =_xlfn.XLOOKUP(CRUCE[[#This Row],[Ubicacion]],Registros[Ubicacion],Registros[Total], "") | J182: =_xlfn.XLOOKUP(CRUCE[[#This Row],[Ubicacion]],Registros[Ubicacion],Registros[UMA], "") | K182: =IF(CRUCE[[#This Row],[TOTAL]]="","",CRUCE[[#This Row],[TOTAL]]-CRUCE[[#This Row],[BULTOS]]) | L182: =IF(CRUCE[[#This Row],[TOTAL]]="", "PENDIENTE", IF(CRUCE[[#This Row],[Diferencia]]=0, "CUADRADO", IF(CRUCE[[#This Row],[Diferencia]]>0, "SOBRANTE", "FALTANTE"))) -> PENDIENTE | M182: =IF(CRUCE[[#This Row],[Diferencia]]="","",IF(CRUCE[[#This Row],[Diferencia]]=0,"OK","RECONTEO")) | N182: =_xlfn.XLOOKUP(CRUCE[[#This Row],[Ubicacion]],Registros[Ubicacion],Registros[Codigo], "") | Q182: =IF(CRUCE[[#This Row],[TOTAL2]]="", "PENDIENTE", IF(CRUCE[[#This Row],[DIFERENCIA2]]=0, "CUADRADO", IF(CRUCE[[#This Row],[DIFERENCIA2]]>0, "SOBRANTE", "FALTANTE"))) -> PENDIENTE | R182: --- | S182: 683c1231-4097-442c-808b-ce8772683f9e
A183: PASILLO 7 | B183: PP-07-043-1 | H183: =_xlfn.XLOOKUP(CRUCE[[#This Row],[Ubicacion]],Registros[Ubicacion],Registros[Codigo], "") | I183: =_xlfn.XLOOKUP(CRUCE[[#This Row],[Ubicacion]],Registros[Ubicacion],Registros[Total], "") | J183: =_xlfn.XLOOKUP(CRUCE[[#This Row],[Ubicacion]],Registros[Ubicacion],Registros[UMA], "") | K183: =IF(CRUCE[[#This Row],[TOTAL]]="","",CRUCE[[#This Row],[TOTAL]]-CRUCE[[#This Row],[BULTOS]]) | L183: =IF(CRUCE[[#This Row],[TOTAL]]="", "PENDIENTE", IF(CRUCE[[#This Row],[Diferencia]]=0, "CUADRADO", IF(CRUCE[[#This Row],[Diferencia]]>0, "SOBRANTE", "FALTANTE"))) -> PENDIENTE | M183: =IF(CRUCE[[#This Row],[Diferencia]]="","",IF(CRUCE[[#This Row],[Diferencia]]=0,"OK","RECONTEO")) | N183: =_xlfn.XLOOKUP(CRUCE[[#This Row],[Ubicacion]],Registros[Ubicacion],Registros[Codigo], "") | Q183: =IF(CRUCE[[#This Row],[TOTAL2]]="", "PENDIENTE", IF(CRUCE[[#This Row],[DIFERENCIA2]]=0, "CUADRADO", IF(CRUCE[[#This Row],[DIFERENCIA2]]>0, "SOBRANTE", "FALTANTE"))) -> PENDIENTE | R183: --- | S183: 1e1645c7-a443-436b-90c1-42ce2fa5bbe9
A184: PASILLO 7 | B184: PP-07-044-1 | H184: =_xlfn.XLOOKUP(CRUCE[[#This Row],[Ubicacion]],Registros[Ubicacion],Registros[Codigo], "") | I184: =_xlfn.XLOOKUP(CRUCE[[#This Row],[Ubicacion]],Registros[Ubicacion],Registros[Total], "") | J184: =_xlfn.XLOOKUP(CRUCE[[#This Row],[Ubicacion]],Registros[Ubicacion],Registros[UMA], "") | K184: =IF(CRUCE[[#This Row],[TOTAL]]="","",CRUCE[[#This Row],[TOTAL]]-CRUCE[[#This Row],[BULTOS]]) | L184: =IF(CRUCE[[#This Row],[TOTAL]]="", "PENDIENTE", IF(CRUCE[[#This Row],[Diferencia]]=0, "CUADRADO", IF(CRUCE[[#This Row],[Diferencia]]>0, "SOBRANTE", "FALTANTE"))) -> PENDIENTE | M184: =IF(CRUCE[[#This Row],[Diferencia]]="","",IF(CRUCE[[#This Row],[Diferencia]]=0,"OK","RECONTEO")) | N184: =_xlfn.XLOOKUP(CRUCE[[#This Row],[Ubicacion]],Registros[Ubicacion],Registros[Codigo], "") | Q184: =IF(CRUCE[[#This Row],[TOTAL2]]="", "PENDIENTE", IF(CRUCE[[#This Row],[DIFERENCIA2]]=0, "CUADRADO", IF(CRUCE[[#This Row],[DIFERENCIA2]]>0, "SOBRANTE", "FALTANTE"))) -> PENDIENTE | R184: --- | S184: 023dbc2f-3bcd-49de-8058-5814a8a0481d
A185: PASILLO 7 | B185: PP-07-045-1 | C185: 8316111 | D185: 17750243084489 | E185: DESINFECTANTE PINO SAPOL. PROF 4L 4UND | F185: 1 | G185: CJA | H185: =_xlfn.XLOOKUP(CRUCE[[#This Row],[Ubicacion]],Registros[Ubicacion],Registros[Codigo], "") | I185: =_xlfn.XLOOKUP(CRUCE[[#This Row],[Ubicacion]],Registros[Ubicacion],Registros[Total], "") | J185: =_xlfn.XLOOKUP(CRUCE[[#This Row],[Ubicacion]],Registros[Ubicacion],Registros[UMA], "") | K185: =IF(CRUCE[[#This Row],[TOTAL]]="","",CRUCE[[#This Row],[TOTAL]]-CRUCE[[#This Row],[BULTOS]]) | L185: =IF(CRUCE[[#This Row],[TOTAL]]="", "PENDIENTE", IF(CRUCE[[#This Row],[Diferencia]]=0, "CUADRADO", IF(CRUCE[[#This Row],[Diferencia]]>0, "SOBRANTE", "FALTANTE"))) -> PENDIENTE | M185: =IF(CRUCE[[#This Row],[Diferencia]]="","",IF(CRUCE[[#This Row],[Diferencia]]=0,"OK","RECONTEO")) | N185: =_xlfn.XLOOKUP(CRUCE[[#This Row],[Ubicacion]],Registros[Ubicacion],Registros[Codigo], "") | Q185: =IF(CRUCE[[#This Row],[TOTAL2]]="", "PENDIENTE", IF(CRUCE[[#This Row],[DIFERENCIA2]]=0, "CUADRADO", IF(CRUCE[[#This Row],[DIFERENCIA2]]>0, "SOBRANTE", "FALTANTE"))) -> PENDIENTE | R185: --- | S185: a112c719-4cd9-4e52-bcdb-8b5687c879c9
A186: PASILLO 7 | B186: PP-07-046-1 | C186: 8315147 | D186: 17750243084465 | E186: SACAGRASA LIMON SAPOLIO PROF 4L 4UND | F186: 6 | G186: CJA | H186: =_xlfn.XLOOKUP(CRUCE[[#This Row],[Ubicacion]],Registros[Ubicacion],Registros[Codigo], "") | I186: =_xlfn.XLOOKUP(CRUCE[[#This Row],[Ubicacion]],Registros[Ubicacion],Registros[Total], "") | J186: =_xlfn.XLOOKUP(CRUCE[[#This Row],[Ubicacion]],Registros[Ubicacion],Registros[UMA], "") | K186: =IF(CRUCE[[#This Row],[TOTAL]]="","",CRUCE[[#This Row],[TOTAL]]-CRUCE[[#This Row],[BULTOS]]) | L186: =IF(CRUCE[[#This Row],[TOTAL]]="", "PENDIENTE", IF(CRUCE[[#This Row],[Diferencia]]=0, "CUADRADO", IF(CRUCE[[#This Row],[Diferencia]]>0, "SOBRANTE", "FALTANTE"))) -> PENDIENTE | M186: =IF(CRUCE[[#This Row],[Diferencia]]="","",IF(CRUCE[[#This Row],[Diferencia]]=0,"OK","RECONTEO")) | N186: =_xlfn.XLOOKUP(CRUCE[[#This Row],[Ubicacion]],Registros[Ubicacion],Registros[Codigo], "") | Q186: =IF(CRUCE[[#This Row],[TOTAL2]]="", "PENDIENTE", IF(CRUCE[[#This Row],[DIFERENCIA2]]=0, "CUADRADO", IF(CRUCE[[#This Row],[DIFERENCIA2]]>0, "SOBRANTE", "FALTANTE"))) -> PENDIENTE | R186: --- | S186: e6d7d365-7268-4bd2-baf6-d4beec88d712
A187: PASILLO 7 | B187: PP-07-047-1 | C187: 8315148 | D187: 17750243084472 | E187: LIMPIAVIDRIOS SAPOLIO PROF. 4L 4UN | F187: 18 | G187: CJA | H187: =_xlfn.XLOOKUP(CRUCE[[#This Row],[Ubicacion]],Registros[Ubicacion],Registros[Codigo], "") | I187: =_xlfn.XLOOKUP(CRUCE[[#This Row],[Ubicacion]],Registros[Ubicacion],Registros[Total], "") | J187: =_xlfn.XLOOKUP(CRUCE[[#This Row],[Ubicacion]],Registros[Ubicacion],Registros[UMA], "") | K187: =IF(CRUCE[[#This Row],[TOTAL]]="","",CRUCE[[#This Row],[TOTAL]]-CRUCE[[#This Row],[BULTOS]]) | L187: =IF(CRUCE[[#This Row],[TOTAL]]="", "PENDIENTE", IF(CRUCE[[#This Row],[Diferencia]]=0, "CUADRADO", IF(CRUCE[[#This Row],[Diferencia]]>0, "SOBRANTE", "FALTANTE"))) -> PENDIENTE | M187: =IF(CRUCE[[#This Row],[Diferencia]]="","",IF(CRUCE[[#This Row],[Diferencia]]=0,"OK","RECONTEO")) | N187: =_xlfn.XLOOKUP(CRUCE[[#This Row],[Ubicacion]],Registros[Ubicacion],Registros[Codigo], "") | Q187: =IF(CRUCE[[#This Row],[TOTAL2]]="", "PENDIENTE", IF(CRUCE[[#This Row],[DIFERENCIA2]]=0, "CUADRADO", IF(CRUCE[[#This Row],[DIFERENCIA2]]>0, "SOBRANTE", "FALTANTE"))) -> PENDIENTE | R187: --- | S187: b3e4b3a8-a98b-450e-92a4-0fea9ca4f250
A188: PASILLO 7 | B188: PP-07-048-1 | C188: 8306007 | D188: 17751851016572 | E188: QUITAM.ROPA COLOR SAPOLIO 3785ML 4UND | F188: 31 | G188: CJA | H188: =_xlfn.XLOOKUP(CRUCE[[#This Row],[Ubicacion]],Registros[Ubicacion],Registros[Codigo], "") | I188: =_xlfn.XLOOKUP(CRUCE[[#This Row],[Ubicacion]],Registros[Ubicacion],Registros[Total], "") | J188: =_xlfn.XLOOKUP(CRUCE[[#This Row],[Ubicacion]],Registros[Ubicacion],Registros[UMA], "") | K188: =IF(CRUCE[[#This Row],[TOTAL]]="","",CRUCE[[#This Row],[TOTAL]]-CRUCE[[#This Row],[BULTOS]]) | L188: =IF(CRUCE[[#This Row],[TOTAL]]="", "PENDIENTE", IF(CRUCE[[#This Row],[Diferencia]]=0, "CUADRADO", IF(CRUCE[[#This Row],[Diferencia]]>0, "SOBRANTE", "FALTANTE"))) -> PENDIENTE | M188: =IF(CRUCE[[#This Row],[Diferencia]]="","",IF(CRUCE[[#This Row],[Diferencia]]=0,"OK","RECONTEO")) | N188: =_xlfn.XLOOKUP(CRUCE[[#This Row],[Ubicacion]],Registros[Ubicacion],Registros[Codigo], "") | Q188: =IF(CRUCE[[#This Row],[TOTAL2]]="", "PENDIENTE", IF(CRUCE[[#This Row],[DIFERENCIA2]]=0, "CUADRADO", IF(CRUCE[[#This Row],[DIFERENCIA2]]>0, "SOBRANTE", "FALTANTE"))) -> PENDIENTE | R188: --- | S188: f31b5990-5b10-4560-b2df-4a9e0b569651
A189: PASILLO 7 | B189: PP-07-049-1 | H189: =_xlfn.XLOOKUP(CRUCE[[#This Row],[Ubicacion]],Registros[Ubicacion],Registros[Codigo], "") | I189: =_xlfn.XLOOKUP(CRUCE[[#This Row],[Ubicacion]],Registros[Ubicacion],Registros[Total], "") | J189: =_xlfn.XLOOKUP(CRUCE[[#This Row],[Ubicacion]],Registros[Ubicacion],Registros[UMA], "") | K189: =IF(CRUCE[[#This Row],[TOTAL]]="","",CRUCE[[#This Row],[TOTAL]]-CRUCE[[#This Row],[BULTOS]]) | L189: =IF(CRUCE[[#This Row],[TOTAL]]="", "PENDIENTE", IF(CRUCE[[#This Row],[Diferencia]]=0, "CUADRADO", IF(CRUCE[[#This Row],[Diferencia]]>0, "SOBRANTE", "FALTANTE"))) -> PENDIENTE | M189: =IF(CRUCE[[#This Row],[Diferencia]]="","",IF(CRUCE[[#This Row],[Diferencia]]=0,"OK","RECONTEO")) | N189: =_xlfn.XLOOKUP(CRUCE[[#This Row],[Ubicacion]],Registros[Ubicacion],Registros[Codigo], "") | Q189: =IF(CRUCE[[#This Row],[TOTAL2]]="", "PENDIENTE", IF(CRUCE[[#This Row],[DIFERENCIA2]]=0, "CUADRADO", IF(CRUCE[[#This Row],[DIFERENCIA2]]>0, "SOBRANTE", "FALTANTE"))) -> PENDIENTE | R189: --- | S189: 5b52eb51-ce90-455e-9519-4c0faa945294
A190: PASILLO 7 | B190: PP-07-050-1 | C190: 8306030 | D190: 17750243070727 | E190: QUITAM. KLINTEX 3785ML 4UND | F190: 27 | G190: CJA | H190: =_xlfn.XLOOKUP(CRUCE[[#This Row],[Ubicacion]],Registros[Ubicacion],Registros[Codigo], "") | I190: =_xlfn.XLOOKUP(CRUCE[[#This Row],[Ubicacion]],Registros[Ubicacion],Registros[Total], "") | J190: =_xlfn.XLOOKUP(CRUCE[[#This Row],[Ubicacion]],Registros[Ubicacion],Registros[UMA], "") | K190: =IF(CRUCE[[#This Row],[TOTAL]]="","",CRUCE[[#This Row],[TOTAL]]-CRUCE[[#This Row],[BULTOS]]) | L190: =IF(CRUCE[[#This Row],[TOTAL]]="", "PENDIENTE", IF(CRUCE[[#This Row],[Diferencia]]=0, "CUADRADO", IF(CRUCE[[#This Row],[Diferencia]]>0, "SOBRANTE", "FALTANTE"))) -> PENDIENTE | M190: =IF(CRUCE[[#This Row],[Diferencia]]="","",IF(CRUCE[[#This Row],[Diferencia]]=0,"OK","RECONTEO")) | N190: =_xlfn.XLOOKUP(CRUCE[[#This Row],[Ubicacion]],Registros[Ubicacion],Registros[Codigo], "") | Q190: =IF(CRUCE[[#This Row],[TOTAL2]]="", "PENDIENTE", IF(CRUCE[[#This Row],[DIFERENCIA2]]=0, "CUADRADO", IF(CRUCE[[#This Row],[DIFERENCIA2]]>0, "SOBRANTE", "FALTANTE"))) -> PENDIENTE | R190: --- | S190: a1ae1332-90a4-4b0a-ba5d-469d3d92f0c9
A191: PASILLO 7 | B191: PP-07-051-1 | C191: 8400702 | D191: 27750243085025 | E191: DET. LIQ.BOLIVAR FLORAL FLUYE 5L 3FCO | F191: 24 | G191: CJA | H191: =_xlfn.XLOOKUP(CRUCE[[#This Row],[Ubicacion]],Registros[Ubicacion],Registros[Codigo], "") | I191: =_xlfn.XLOOKUP(CRUCE[[#This Row],[Ubicacion]],Registros[Ubicacion],Registros[Total], "") | J191: =_xlfn.XLOOKUP(CRUCE[[#This Row],[Ubicacion]],Registros[Ubicacion],Registros[UMA], "") | K191: =IF(CRUCE[[#This Row],[TOTAL]]="","",CRUCE[[#This Row],[TOTAL]]-CRUCE[[#This Row],[BULTOS]]) | L191: =IF(CRUCE[[#This Row],[TOTAL]]="", "PENDIENTE", IF(CRUCE[[#This Row],[Diferencia]]=0, "CUADRADO", IF(CRUCE[[#This Row],[Diferencia]]>0, "SOBRANTE", "FALTANTE"))) -> PENDIENTE | M191: =IF(CRUCE[[#This Row],[Diferencia]]="","",IF(CRUCE[[#This Row],[Diferencia]]=0,"OK","RECONTEO")) | N191: =_xlfn.XLOOKUP(CRUCE[[#This Row],[Ubicacion]],Registros[Ubicacion],Registros[Codigo], "") | Q191: =IF(CRUCE[[#This Row],[TOTAL2]]="", "PENDIENTE", IF(CRUCE[[#This Row],[DIFERENCIA2]]=0, "CUADRADO", IF(CRUCE[[#This Row],[DIFERENCIA2]]>0, "SOBRANTE", "FALTANTE"))) -> PENDIENTE | R191: --- | S191: f646b98d-c4a2-4dea-b4c6-42ef4cf33a79
A192: PASILLO 7 | B192: PP-07-052-1 | C192: 8316019 | D192: 17751851008164 | E192: DESINF.PINO NATURAL SAPOLIO 3785ML 4UND | F192: 16 | G192: CJA | H192: =_xlfn.XLOOKUP(CRUCE[[#This Row],[Ubicacion]],Registros[Ubicacion],Registros[Codigo], "") | I192: =_xlfn.XLOOKUP(CRUCE[[#This Row],[Ubicacion]],Registros[Ubicacion],Registros[Total], "") | J192: =_xlfn.XLOOKUP(CRUCE[[#This Row],[Ubicacion]],Registros[Ubicacion],Registros[UMA], "") | K192: =IF(CRUCE[[#This Row],[TOTAL]]="","",CRUCE[[#This Row],[TOTAL]]-CRUCE[[#This Row],[BULTOS]]) | L192: =IF(CRUCE[[#This Row],[TOTAL]]="", "PENDIENTE", IF(CRUCE[[#This Row],[Diferencia]]=0, "CUADRADO", IF(CRUCE[[#This Row],[Diferencia]]>0, "SOBRANTE", "FALTANTE"))) -> PENDIENTE | M192: =IF(CRUCE[[#This Row],[Diferencia]]="","",IF(CRUCE[[#This Row],[Diferencia]]=0,"OK","RECONTEO")) | N192: =_xlfn.XLOOKUP(CRUCE[[#This Row],[Ubicacion]],Registros[Ubicacion],Registros[Codigo], "") | Q192: =IF(CRUCE[[#This Row],[TOTAL2]]="", "PENDIENTE", IF(CRUCE[[#This Row],[DIFERENCIA2]]=0, "CUADRADO", IF(CRUCE[[#This Row],[DIFERENCIA2]]>0, "SOBRANTE", "FALTANTE"))) -> PENDIENTE | R192: --- | S192: af7506ef-0ee2-45b9-ade0-60fa65a469cf
A193: PASILLO 8 | B193: PP-08-001-1 | H193: =_xlfn.XLOOKUP(CRUCE[[#This Row],[Ubicacion]],Registros[Ubicacion],Registros[Codigo], "") | I193: =_xlfn.XLOOKUP(CRUCE[[#This Row],[Ubicacion]],Registros[Ubicacion],Registros[Total], "") | J193: =_xlfn.XLOOKUP(CRUCE[[#This Row],[Ubicacion]],Registros[Ubicacion],Registros[UMA], "") | K193: =IF(CRUCE[[#This Row],[TOTAL]]="","",CRUCE[[#This Row],[TOTAL]]-CRUCE[[#This Row],[BULTOS]]) | L193: =IF(CRUCE[[#This Row],[TOTAL]]="", "PENDIENTE", IF(CRUCE[[#This Row],[Diferencia]]=0, "CUADRADO", IF(CRUCE[[#This Row],[Diferencia]]>0, "SOBRANTE", "FALTANTE"))) -> PENDIENTE | M193: =IF(CRUCE[[#This Row],[Diferencia]]="","",IF(CRUCE[[#This Row],[Diferencia]]=0,"OK","RECONTEO")) | N193: =_xlfn.XLOOKUP(CRUCE[[#This Row],[Ubicacion]],Registros[Ubicacion],Registros[Codigo], "") | Q193: =IF(CRUCE[[#This Row],[TOTAL2]]="", "PENDIENTE", IF(CRUCE[[#This Row],[DIFERENCIA2]]=0, "CUADRADO", IF(CRUCE[[#This Row],[DIFERENCIA2]]>0, "SOBRANTE", "FALTANTE"))) -> PENDIENTE | R193: --- | S193: 79c22d5c-6399-42f1-947d-7d0af556ecf1
...
